Workbook

Sheet DB
D3: Current scheme slab | O3: Current scheme slab
A4: State | B4: Zone | C4: Total # Dealers | D4: A | E4: B | F4: C | G4: D | H4: E | K4: Distributor Name | L4: State | M4: Zone | N4: Total # Dealers | O4: A | P4: B | Q4: C | R4: D | S4: E
A5: CHHATTISGARH | B5: =IFERROR(VLOOKUP(A5,$L$5:$M$69,2,0),"-") -> Central | C5: =SUMIFS(N$5:N$69,$L$5:$L$69,$A5,$M$5:$M$69,$B5) -> 38 | D5: =SUMIFS(O$5:O$69,$L$5:$L$69,$A5,$M$5:$M$69,$B5) -> 0 | E5: =SUMIFS(P$5:P$69,$L$5:$L$69,$A5,$M$5:$M$69,$B5) -> 0 | F5: =SUMIFS(Q$5:Q$69,$L$5:$L$69,$A5,$M$5:$M$69,$B5) -> 0 | G5: =SUMIFS(R$5:R$69,$L$5:$L$69,$A5,$M$5:$M$69,$B5) -> 0 | H5: =SUMIFS(S$5:S$69,$L$5:$L$69,$A5,$M$5:$M$69,$B5) -> 0 | K5: AGGARWAL TRADERS | L5: JAMMU AND KASHMIR | M5: North | N5: =COUNTIFS('FY 26_qualification scenario'!$I:$I,DB!$K5,'FY 26_qualification scenario'!$F:$F,DB!$L5,'FY 26_qualification scenario'!$M:$M,DB!$M5) -> 34 | O5: =COUNTIFS('FY 26_qualification scenario'!$BI:$BI,DB!O$4,'FY 26_qualification scenario'!$I:$I,DB!$K5,'FY 26_qualification scenario'!$F:$F,DB!$L5,'FY 26_qualification scenario'!$M:$M,DB!$M5) -> 1 | P5: =COUNTIFS('FY 26_qualification scenario'!$BI:$BI,DB!P$4,'FY 26_qualification scenario'!$I:$I,DB!$K5,'FY 26_qualification scenario'!$F:$F,DB!$L5,'FY 26_qualification scenario'!$M:$M,DB!$M5) -> 1 | Q5: =COUNTIFS('FY 26_qualification scenario'!$BI:$BI,DB!Q$4,'FY 26_qualification scenario'!$I:$I,DB!$K5,'FY 26_qualification scenario'!$F:$F,DB!$L5,'FY 26_qualification scenario'!$M:$M,DB!$M5) -> 1 | R5: =COUNTIFS('FY 26_qualification scenario'!$BI:$BI,DB!R$4,'FY 26_qualification scenario'!$I:$I,DB!$K5,'FY 26_qualification scenario'!$F:$F,DB!$L5,'FY 26_qualification scenario'!$M:$M,DB!$M5) -> 0 | S5: =COUNTIFS('FY 26_qualification scenario'!$BI:$BI,DB!S$4,'FY 26_qualification scenario'!$I:$I,DB!$K5,'FY 26_qualification scenario'!$F:$F,DB!$L5,'FY 26_qualification scenario'!$M:$M,DB!$M5) -> 0
A6: MADHYA PRADESH | B6: =IFERROR(VLOOKUP(A6,$L$5:$M$69,2,0),"-") -> Central | C6: =SUMIFS(N$5:N$69,$L$5:$L$69,$A6,$M$5:$M$69,$B6) -> 142 | D6: =SUMIFS(O$5:O$69,$L$5:$L$69,$A6,$M$5:$M$69,$B6) -> 5 | E6: =SUMIFS(P$5:P$69,$L$5:$L$69,$A6,$M$5:$M$69,$B6) -> 2 | F6: =SUMIFS(Q$5:Q$69,$L$5:$L$69,$A6,$M$5:$M$69,$B6) -> 3 | G6: =SUMIFS(R$5:R$69,$L$5:$L$69,$A6,$M$5:$M$69,$B6) -> 4 | H6: =SUMIFS(S$5:S$69,$L$5:$L$69,$A6,$M$5:$M$69,$B6) -> 1 | K6: Amco Associates | L6: JHARKHAND | M6: East | N6: =COUNTIFS('FY 26_qualification scenario'!$I:$I,DB!$K6,'FY 26_qualification scenario'!$F:$F,DB!$L6,'FY 26_qualification scenario'!$M:$M,DB!$M6) -> 5 | O6: =COUNTIFS('FY 26_qualification scenario'!$BI:$BI,DB!O$4,'FY 26_qualification scenario'!$I:$I,DB!$K6,'FY 26_qualification scenario'!$F:$F,DB!$L6,'FY 26_qualification scenario'!$M:$M,DB!$M6) -> 0 | P6: =COUNTIFS('FY 26_qualification scenario'!$BI:$BI,DB!P$4,'FY 26_qualification scenario'!$I:$I,DB!$K6,'FY 26_qualification scenario'!$F:$F,DB!$L6,'FY 26_qualification scenario'!$M:$M,DB!$M6) -> 0 | Q6: =COUNTIFS('FY 26_qualification scenario'!$BI:$BI,DB!Q$4,'FY 26_qualification scenario'!$I:$I,DB!$K6,'FY 26_qualification scenario'!$F:$F,DB!$L6,'FY 26_qualification scenario'!$M:$M,DB!$M6) -> 0 | R6: =COUNTIFS('FY 26_qualification scenario'!$BI:$BI,DB!R$4,'FY 26_qualification scenario'!$I:$I,DB!$K6,'FY 26_qualification scenario'!$F:$F,DB!$L6,'FY 26_qualification scenario'!$M:$M,DB!$M6) -> 0 | S6: =COUNTIFS('FY 26_qualification scenario'!$BI:$BI,DB!S$4,'FY 26_qualification scenario'!$I:$I,DB!$K6,'FY 26_qualification scenario'!$F:$F,DB!$L6,'FY 26_qualification scenario'!$M:$M,DB!$M6) -> 0
A7: ODISHA | B7: =IFERROR(VLOOKUP(A7,$L$5:$M$69,2,0),"-") -> Central | C7: =SUMIFS(N$5:N$69,$L$5:$L$69,$A7,$M$5:$M$69,$B7) -> 136 | D7: =SUMIFS(O$5:O$69,$L$5:$L$69,$A7,$M$5:$M$69,$B7) -> 1 | E7: =SUMIFS(P$5:P$69,$L$5:$L$69,$A7,$M$5:$M$69,$B7) -> 5 | F7: =SUMIFS(Q$5:Q$69,$L$5:$L$69,$A7,$M$5:$M$69,$B7) -> 1 | G7: =SUMIFS(R$5:R$69,$L$5:$L$69,$A7,$M$5:$M$69,$B7) -> 0 | H7: =SUMIFS(S$5:S$69,$L$5:$L$69,$A7,$M$5:$M$69,$B7) -> 0 | K7: ARS INFRA | L7: GUJARAT | M7: West | N7: =COUNTIFS('FY 26_qualification scenario'!$I:$I,DB!$K7,'FY 26_qualification scenario'!$F:$F,DB!$L7,'FY 26_qualification scenario'!$M:$M,DB!$M7) -> 2 | O7: =COUNTIFS('FY 26_qualification scenario'!$BI:$BI,DB!O$4,'FY 26_qualification scenario'!$I:$I,DB!$K7,'FY 26_qualification scenario'!$F:$F,DB!$L7,'FY 26_qualification scenario'!$M:$M,DB!$M7) -> 0 | P7: =COUNTIFS('FY 26_qualification scenario'!$BI:$BI,DB!P$4,'FY 26_qualification scenario'!$I:$I,DB!$K7,'FY 26_qualification scenario'!$F:$F,DB!$L7,'FY 26_qualification scenario'!$M:$M,DB!$M7) -> 0 | Q7: =COUNTIFS('FY 26_qualification scenario'!$BI:$BI,DB!Q$4,'FY 26_qualification scenario'!$I:$I,DB!$K7,'FY 26_qualification scenario'!$F:$F,DB!$L7,'FY 26_qualification scenario'!$M:$M,DB!$M7) -> 0 | R7: =COUNTIFS('FY 26_qualification scenario'!$BI:$BI,DB!R$4,'FY 26_qualification scenario'!$I:$I,DB!$K7,'FY 26_qualification scenario'!$F:$F,DB!$L7,'FY 26_qualification scenario'!$M:$M,DB!$M7) -> 0 | S7: =COUNTIFS('FY 26_qualification scenario'!$BI:$BI,DB!S$4,'FY 26_qualification scenario'!$I:$I,DB!$K7,'FY 26_qualification scenario'!$F:$F,DB!$L7,'FY 26_qualification scenario'!$M:$M,DB!$M7) -> 0
A8: MAHARASHTRA | B8: =IFERROR(VLOOKUP(A8,$L$5:$M$69,2,0),"-") -> Central | C8: =SUMIFS(N$5:N$69,$L$5:$L$69,$A8,$M$5:$M$69,$B8) -> 1 | D8: =SUMIFS(O$5:O$69,$L$5:$L$69,$A8,$M$5:$M$69,$B8) -> 0 | E8: =SUMIFS(P$5:P$69,$L$5:$L$69,$A8,$M$5:$M$69,$B8) -> 0 | F8: =SUMIFS(Q$5:Q$69,$L$5:$L$69,$A8,$M$5:$M$69,$B8) -> 0 | G8: =SUMIFS(R$5:R$69,$L$5:$L$69,$A8,$M$5:$M$69,$B8) -> 0 | H8: =SUMIFS(S$5:S$69,$L$5:$L$69,$A8,$M$5:$M$69,$B8) -> 0 | K8: BD ISPAT AND ALLOYS | L8: RAJASTHAN | M8: North | N8: =COUNTIFS('FY 26_qualification scenario'!$I:$I,DB!$K8,'FY 26_qualification scenario'!$F:$F,DB!$L8,'FY 26_qualification scenario'!$M:$M,DB!$M8) -> 1 | O8: =COUNTIFS('FY 26_qualification scenario'!$BI:$BI,DB!O$4,'FY 26_qualification scenario'!$I:$I,DB!$K8,'FY 26_qualification scenario'!$F:$F,DB!$L8,'FY 26_qualification scenario'!$M:$M,DB!$M8) -> 0 | P8: =COUNTIFS('FY 26_qualification scenario'!$BI:$BI,DB!P$4,'FY 26_qualification scenario'!$I:$I,DB!$K8,'FY 26_qualification scenario'!$F:$F,DB!$L8,'FY 26_qualification scenario'!$M:$M,DB!$M8) -> 0 | Q8: =COUNTIFS('FY 26_qualification scenario'!$BI:$BI,DB!Q$4,'FY 26_qualification scenario'!$I:$I,DB!$K8,'FY 26_qualification scenario'!$F:$F,DB!$L8,'FY 26_qualification scenario'!$M:$M,DB!$M8) -> 0 | R8: =COUNTIFS('FY 26_qualification scenario'!$BI:$BI,DB!R$4,'FY 26_qualification scenario'!$I:$I,DB!$K8,'FY 26_qualification scenario'!$F:$F,DB!$L8,'FY 26_qualification scenario'!$M:$M,DB!$M8) -> 0 | S8: =COUNTIFS('FY 26_qualification scenario'!$BI:$BI,DB!S$4,'FY 26_qualification scenario'!$I:$I,DB!$K8,'FY 26_qualification scenario'!$F:$F,DB!$L8,'FY 26_qualification scenario'!$M:$M,DB!$M8) -> 0
A9: JHARKHAND | B9: =IFERROR(VLOOKUP(A9,$L$5:$M$69,2,0),"-") -> East | C9: =SUMIFS(N$5:N$69,$L$5:$L$69,$A9,$M$5:$M$69,$B9) -> 35 | D9: =SUMIFS(O$5:O$69,$L$5:$L$69,$A9,$M$5:$M$69,$B9) -> 1 | E9: =SUMIFS(P$5:P$69,$L$5:$L$69,$A9,$M$5:$M$69,$B9) -> 0 | F9: =SUMIFS(Q$5:Q$69,$L$5:$L$69,$A9,$M$5:$M$69,$B9) -> 0 | G9: =SUMIFS(R$5:R$69,$L$5:$L$69,$A9,$M$5:$M$69,$B9) -> 0 | H9: =SUMIFS(S$5:S$69,$L$5:$L$69,$A9,$M$5:$M$69,$B9) -> 0 | K9: CHANDRA TRADERS | L9: WEST BENGAL | M9: East | N9: =COUNTIFS('FY 26_qualification scenario'!$I:$I,DB!$K9,'FY 26_qualification scenario'!$F:$F,DB!$L9,'FY 26_qualification scenario'!$M:$M,DB!$M9) -> 26 | O9: =COUNTIFS('FY 26_qualification scenario'!$BI:$BI,DB!O$4,'FY 26_qualification scenario'!$I:$I,DB!$K9,'FY 26_qualification scenario'!$F:$F,DB!$L9,'FY 26_qualification scenario'!$M:$M,DB!$M9) -> 0 | P9: =COUNTIFS('FY 26_qualification scenario'!$BI:$BI,DB!P$4,'FY 26_qualification scenario'!$I:$I,DB!$K9,'FY 26_qualification scenario'!$F:$F,DB!$L9,'FY 26_qualification scenario'!$M:$M,DB!$M9) -> 0 | Q9: =COUNTIFS('FY 26_qualification scenario'!$BI:$BI,DB!Q$4,'FY 26_qualification scenario'!$I:$I,DB!$K9,'FY 26_qualification scenario'!$F:$F,DB!$L9,'FY 26_qualification scenario'!$M:$M,DB!$M9) -> 0 | R9: =COUNTIFS('FY 26_qualification scenario'!$BI:$BI,DB!R$4,'FY 26_qualification scenario'!$I:$I,DB!$K9,'FY 26_qualification scenario'!$F:$F,DB!$L9,'FY 26_qualification scenario'!$M:$M,DB!$M9) -> 0 | S9: =COUNTIFS('FY 26_qualification scenario'!$BI:$BI,DB!S$4,'FY 26_qualification scenario'!$I:$I,DB!$K9,'FY 26_qualification scenario'!$F:$F,DB!$L9,'FY 26_qualification scenario'!$M:$M,DB!$M9) -> 0
A10: WEST BENGAL | B10: =IFERROR(VLOOKUP(A10,$L$5:$M$69,2,0),"-") -> East | C10: =SUMIFS(N$5:N$69,$L$5:$L$69,$A10,$M$5:$M$69,$B10) -> 119 | D10: =SUMIFS(O$5:O$69,$L$5:$L$69,$A10,$M$5:$M$69,$B10) -> 0 | E10: =SUMIFS(P$5:P$69,$L$5:$L$69,$A10,$M$5:$M$69,$B10) -> 0 | F10: =SUMIFS(Q$5:Q$69,$L$5:$L$69,$A10,$M$5:$M$69,$B10) -> 0 | G10: =SUMIFS(R$5:R$69,$L$5:$L$69,$A10,$M$5:$M$69,$B10) -> 0 | H10: =SUMIFS(S$5:S$69,$L$5:$L$69,$A10,$M$5:$M$69,$B10) -> 0 | K10: DINESH STEEL PRIVATE LIMITED | L10: UTTAR PRADESH | M10: North | N10: =COUNTIFS('FY 26_qualification scenario'!$I:$I,DB!$K10,'FY 26_qualification scenario'!$F:$F,DB!$L10,'FY 26_qualification scenario'!$M:$M,DB!$M10) -> 45 | O10: =COUNTIFS('FY 26_qualification scenario'!$BI:$BI,DB!O$4,'FY 26_qualification scenario'!$I:$I,DB!$K10,'FY 26_qualification scenario'!$F:$F,DB!$L10,'FY 26_qualification scenario'!$M:$M,DB!$M10) -> 3 | P10: =COUNTIFS('FY 26_qualification scenario'!$BI:$BI,DB!P$4,'FY 26_qualification scenario'!$I:$I,DB!$K10,'FY 26_qualification scenario'!$F:$F,DB!$L10,'FY 26_qualification scenario'!$M:$M,DB!$M10) -> 3 | Q10: =COUNTIFS('FY 26_qualification scenario'!$BI:$BI,DB!Q$4,'FY 26_qualification scenario'!$I:$I,DB!$K10,'FY 26_qualification scenario'!$F:$F,DB!$L10,'FY 26_qualification scenario'!$M:$M,DB!$M10) -> 1 | R10: =COUNTIFS('FY 26_qualification scenario'!$BI:$BI,DB!R$4,'FY 26_qualification scenario'!$I:$I,DB!$K10,'FY 26_qualification scenario'!$F:$F,DB!$L10,'FY 26_qualification scenario'!$M:$M,DB!$M10) -> 0 | S10: =COUNTIFS('FY 26_qualification scenario'!$BI:$BI,DB!S$4,'FY 26_qualification scenario'!$I:$I,DB!$K10,'FY 26_qualification scenario'!$F:$F,DB!$L10,'FY 26_qualification scenario'!$M:$M,DB!$M10) -> 0
A11: BIHAR | B11: =IFERROR(VLOOKUP(A11,$L$5:$M$69,2,0),"-") -> East | C11: =SUMIFS(N$5:N$69,$L$5:$L$69,$A11,$M$5:$M$69,$B11) -> 49 | D11: =SUMIFS(O$5:O$69,$L$5:$L$69,$A11,$M$5:$M$69,$B11) -> 1 | E11: =SUMIFS(P$5:P$69,$L$5:$L$69,$A11,$M$5:$M$69,$B11) -> 0 | F11: =SUMIFS(Q$5:Q$69,$L$5:$L$69,$A11,$M$5:$M$69,$B11) -> 0 | G11: =SUMIFS(R$5:R$69,$L$5:$L$69,$A11,$M$5:$M$69,$B11) -> 0 | H11: =SUMIFS(S$5:S$69,$L$5:$L$69,$A11,$M$5:$M$69,$B11) -> 0 | K11: FAIRDEAL STEELS | L11: JAMMU AND KASHMIR | M11: North | N11: =COUNTIFS('FY 26_qualification scenario'!$I:$I,DB!$K11,'FY 26_qualification scenario'!$F:$F,DB!$L11,'FY 26_qualification scenario'!$M:$M,DB!$M11) -> 1 | O11: =COUNTIFS('FY 26_qualification scenario'!$BI:$BI,DB!O$4,'FY 26_qualification scenario'!$I:$I,DB!$K11,'FY 26_qualification scenario'!$F:$F,DB!$L11,'FY 26_qualification scenario'!$M:$M,DB!$M11) -> 0 | P11: =COUNTIFS('FY 26_qualification scenario'!$BI:$BI,DB!P$4,'FY 26_qualification scenario'!$I:$I,DB!$K11,'FY 26_qualification scenario'!$F:$F,DB!$L11,'FY 26_qualification scenario'!$M:$M,DB!$M11) -> 0 | Q11: =COUNTIFS('FY 26_qualification scenario'!$BI:$BI,DB!Q$4,'FY 26_qualification scenario'!$I:$I,DB!$K11,'FY 26_qualification scenario'!$F:$F,DB!$L11,'FY 26_qualification scenario'!$M:$M,DB!$M11) -> 0 | R11: =COUNTIFS('FY 26_qualification scenario'!$BI:$BI,DB!R$4,'FY 26_qualification scenario'!$I:$I,DB!$K11,'FY 26_qualification scenario'!$F:$F,DB!$L11,'FY 26_qualification scenario'!$M:$M,DB!$M11) -> 0 | S11: =COUNTIFS('FY 26_qualification scenario'!$BI:$BI,DB!S$4,'FY 26_qualification scenario'!$I:$I,DB!$K11,'FY 26_qualification scenario'!$F:$F,DB!$L11,'FY 26_qualification scenario'!$M:$M,DB!$M11) -> 0
A12: SIKKIM | B12: =IFERROR(VLOOKUP(A12,$L$5:$M$69,2,0),"-") -> East | C12: =SUMIFS(N$5:N$69,$L$5:$L$69,$A12,$M$5:$M$69,$B12) -> 1 | D12: =SUMIFS(O$5:O$69,$L$5:$L$69,$A12,$M$5:$M$69,$B12) -> 0 | E12: =SUMIFS(P$5:P$69,$L$5:$L$69,$A12,$M$5:$M$69,$B12) -> 0 | F12: =SUMIFS(Q$5:Q$69,$L$5:$L$69,$A12,$M$5:$M$69,$B12) -> 0 | G12: =SUMIFS(R$5:R$69,$L$5:$L$69,$A12,$M$5:$M$69,$B12) -> 0 | H12: =SUMIFS(S$5:S$69,$L$5:$L$69,$A12,$M$5:$M$69,$B12) -> 0 | K12: G.C. Steels (India) Pvt. Ltd. | L12: HARYANA | M12: North | N12: =COUNTIFS('FY 26_qualification scenario'!$I:$I,DB!$K12,'FY 26_qualification scenario'!$F:$F,DB!$L12,'FY 26_qualification scenario'!$M:$M,DB!$M12) -> 7 | O12: =COUNTIFS('FY 26_qualification scenario'!$BI:$BI,DB!O$4,'FY 26_qualification scenario'!$I:$I,DB!$K12,'FY 26_qualification scenario'!$F:$F,DB!$L12,'FY 26_qualification scenario'!$M:$M,DB!$M12) -> 0 | P12: =COUNTIFS('FY 26_qualification scenario'!$BI:$BI,DB!P$4,'FY 26_qualification scenario'!$I:$I,DB!$K12,'FY 26_qualification scenario'!$F:$F,DB!$L12,'FY 26_qualification scenario'!$M:$M,DB!$M12) -> 0 | Q12: =COUNTIFS('FY 26_qualification scenario'!$BI:$BI,DB!Q$4,'FY 26_qualification scenario'!$I:$I,DB!$K12,'FY 26_qualification scenario'!$F:$F,DB!$L12,'FY 26_qualification scenario'!$M:$M,DB!$M12) -> 0 | R12: =COUNTIFS('FY 26_qualification scenario'!$BI:$BI,DB!R$4,'FY 26_qualification scenario'!$I:$I,DB!$K12,'FY 26_qualification scenario'!$F:$F,DB!$L12,'FY 26_qualification scenario'!$M:$M,DB!$M12) -> 0 | S12: =COUNTIFS('FY 26_qualification scenario'!$BI:$BI,DB!S$4,'FY 26_qualification scenario'!$I:$I,DB!$K12,'FY 26_qualification scenario'!$F:$F,DB!$L12,'FY 26_qualification scenario'!$M:$M,DB!$M12) -> 0
A13: MADHYA PRADESH | B13: North | C13: =SUMIFS(N$5:N$69,$L$5:$L$69,$A13,$M$5:$M$69,$B13) -> 23 | D13: =SUMIFS(O$5:O$69,$L$5:$L$69,$A13,$M$5:$M$69,$B13) -> 1 | E13: =SUMIFS(P$5:P$69,$L$5:$L$69,$A13,$M$5:$M$69,$B13) -> 0 | F13: =SUMIFS(Q$5:Q$69,$L$5:$L$69,$A13,$M$5:$M$69,$B13) -> 0 | G13: =SUMIFS(R$5:R$69,$L$5:$L$69,$A13,$M$5:$M$69,$B13) -> 0 | H13: =SUMIFS(S$5:S$69,$L$5:$L$69,$A13,$M$5:$M$69,$B13) -> 0 | K13: GLOBAL IRONTRADING PVT. LTD. | L13: UTTAR PRADESH | M13: North | N13: =COUNTIFS('FY 26_qualification scenario'!$I:$I,DB!$K13,'FY 26_qualification scenario'!$F:$F,DB!$L13,'FY 26_qualification scenario'!$M:$M,DB!$M13) -> 26 | O13: =COUNTIFS('FY 26_qualification scenario'!$BI:$BI,DB!O$4,'FY 26_qualification scenario'!$I:$I,DB!$K13,'FY 26_qualification scenario'!$F:$F,DB!$L13,'FY 26_qualification scenario'!$M:$M,DB!$M13) -> 1 | P13: =COUNTIFS('FY 26_qualification scenario'!$BI:$BI,DB!P$4,'FY 26_qualification scenario'!$I:$I,DB!$K13,'FY 26_qualification scenario'!$F:$F,DB!$L13,'FY 26_qualification scenario'!$M:$M,DB!$M13) -> 1 | Q13: =COUNTIFS('FY 26_qualification scenario'!$BI:$BI,DB!Q$4,'FY 26_qualification scenario'!$I:$I,DB!$K13,'FY 26_qualification scenario'!$F:$F,DB!$L13,'FY 26_qualification scenario'!$M:$M,DB!$M13) -> 1 | R13: =COUNTIFS('FY 26_qualification scenario'!$BI:$BI,DB!R$4,'FY 26_qualification scenario'!$I:$I,DB!$K13,'FY 26_qualification scenario'!$F:$F,DB!$L13,'FY 26_qualification scenario'!$M:$M,DB!$M13) -> 0 | S13: =COUNTIFS('FY 26_qualification scenario'!$BI:$BI,DB!S$4,'FY 26_qualification scenario'!$I:$I,DB!$K13,'FY 26_qualification scenario'!$F:$F,DB!$L13,'FY 26_qualification scenario'!$M:$M,DB!$M13) -> 0
A14: JAMMU AND KASHMIR | B14: =IFERROR(VLOOKUP(A14,$L$5:$M$69,2,0),"-") -> North | C14: =SUMIFS(N$5:N$69,$L$5:$L$69,$A14,$M$5:$M$69,$B14) -> 43 | D14: =SUMIFS(O$5:O$69,$L$5:$L$69,$A14,$M$5:$M$69,$B14) -> 1 | E14: =SUMIFS(P$5:P$69,$L$5:$L$69,$A14,$M$5:$M$69,$B14) -> 1 | F14: =SUMIFS(Q$5:Q$69,$L$5:$L$69,$A14,$M$5:$M$69,$B14) -> 1 | G14: =SUMIFS(R$5:R$69,$L$5:$L$69,$A14,$M$5:$M$69,$B14) -> 0 | H14: =SUMIFS(S$5:S$69,$L$5:$L$69,$A14,$M$5:$M$69,$B14) -> 0 | K14: Global Steel | L14: CHHATTISGARH | M14: Central | N14: =COUNTIFS('FY 26_qualification scenario'!$I:$I,DB!$K14,'FY 26_qualification scenario'!$F:$F,DB!$L14,'FY 26_qualification scenario'!$M:$M,DB!$M14) -> 4 | O14: =COUNTIFS('FY 26_qualification scenario'!$BI:$BI,DB!O$4,'FY 26_qualification scenario'!$I:$I,DB!$K14,'FY 26_qualification scenario'!$F:$F,DB!$L14,'FY 26_qualification scenario'!$M:$M,DB!$M14) -> 0 | P14: =COUNTIFS('FY 26_qualification scenario'!$BI:$BI,DB!P$4,'FY 26_qualification scenario'!$I:$I,DB!$K14,'FY 26_qualification scenario'!$F:$F,DB!$L14,'FY 26_qualification scenario'!$M:$M,DB!$M14) -> 0 | Q14: =COUNTIFS('FY 26_qualification scenario'!$BI:$BI,DB!Q$4,'FY 26_qualification scenario'!$I:$I,DB!$K14,'FY 26_qualification scenario'!$F:$F,DB!$L14,'FY 26_qualification scenario'!$M:$M,DB!$M14) -> 0 | R14: =COUNTIFS('FY 26_qualification scenario'!$BI:$BI,DB!R$4,'FY 26_qualification scenario'!$I:$I,DB!$K14,'FY 26_qualification scenario'!$F:$F,DB!$L14,'FY 26_qualification scenario'!$M:$M,DB!$M14) -> 0 | S14: =COUNTIFS('FY 26_qualification scenario'!$BI:$BI,DB!S$4,'FY 26_qualification scenario'!$I:$I,DB!$K14,'FY 26_qualification scenario'!$F:$F,DB!$L14,'FY 26_qualification scenario'!$M:$M,DB!$M14) -> 0
A15: RAJASTHAN | B15: =IFERROR(VLOOKUP(A15,$L$5:$M$69,2,0),"-") -> North | C15: =SUMIFS(N$5:N$69,$L$5:$L$69,$A15,$M$5:$M$69,$B15) -> 210 | D15: =SUMIFS(O$5:O$69,$L$5:$L$69,$A15,$M$5:$M$69,$B15) -> 8 | E15: =SUMIFS(P$5:P$69,$L$5:$L$69,$A15,$M$5:$M$69,$B15) -> 12 | F15: =SUMIFS(Q$5:Q$69,$L$5:$L$69,$A15,$M$5:$M$69,$B15) -> 3 | G15: =SUMIFS(R$5:R$69,$L$5:$L$69,$A15,$M$5:$M$69,$B15) -> 7 | H15: =SUMIFS(S$5:S$69,$L$5:$L$69,$A15,$M$5:$M$69,$B15) -> 0 | K15: Global Steel | L15: MADHYA PRADESH | M15: Central | N15: =COUNTIFS('FY 26_qualification scenario'!$I:$I,DB!$K15,'FY 26_qualification scenario'!$F:$F,DB!$L15,'FY 26_qualification scenario'!$M:$M,DB!$M15) -> 71 | O15: =COUNTIFS('FY 26_qualification scenario'!$BI:$BI,DB!O$4,'FY 26_qualification scenario'!$I:$I,DB!$K15,'FY 26_qualification scenario'!$F:$F,DB!$L15,'FY 26_qualification scenario'!$M:$M,DB!$M15) -> 4 | P15: =COUNTIFS('FY 26_qualification scenario'!$BI:$BI,DB!P$4,'FY 26_qualification scenario'!$I:$I,DB!$K15,'FY 26_qualification scenario'!$F:$F,DB!$L15,'FY 26_qualification scenario'!$M:$M,DB!$M15) -> 0 | Q15: =COUNTIFS('FY 26_qualification scenario'!$BI:$BI,DB!Q$4,'FY 26_qualification scenario'!$I:$I,DB!$K15,'FY 26_qualification scenario'!$F:$F,DB!$L15,'FY 26_qualification scenario'!$M:$M,DB!$M15) -> 2 | R15: =COUNTIFS('FY 26_qualification scenario'!$BI:$BI,DB!R$4,'FY 26_qualification scenario'!$I:$I,DB!$K15,'FY 26_qualification scenario'!$F:$F,DB!$L15,'FY 26_qualification scenario'!$M:$M,DB!$M15) -> 1 | S15: =COUNTIFS('FY 26_qualification scenario'!$BI:$BI,DB!S$4,'FY 26_qualification scenario'!$I:$I,DB!$K15,'FY 26_qualification scenario'!$F:$F,DB!$L15,'FY 26_qualification scenario'!$M:$M,DB!$M15) -> 0
A16: UTTAR PRADESH | B16: =IFERROR(VLOOKUP(A16,$L$5:$M$69,2,0),"-") -> North | C16: =SUMIFS(N$5:N$69,$L$5:$L$69,$A16,$M$5:$M$69,$B16) -> 378 | D16: =SUMIFS(O$5:O$69,$L$5:$L$69,$A16,$M$5:$M$69,$B16) -> 13 | E16: =SUMIFS(P$5:P$69,$L$5:$L$69,$A16,$M$5:$M$69,$B16) -> 11 | F16: =SUMIFS(Q$5:Q$69,$L$5:$L$69,$A16,$M$5:$M$69,$B16) -> 2 | G16: =SUMIFS(R$5:R$69,$L$5:$L$69,$A16,$M$5:$M$69,$B16) -> 8 | H16: =SUMIFS(S$5:S$69,$L$5:$L$69,$A16,$M$5:$M$69,$B16) -> 1 | K16: GOBINDGARH IRON LLP | L16: UTTAR PRADESH | M16: North | N16: =COUNTIFS('FY 26_qualification scenario'!$I:$I,DB!$K16,'FY 26_qualification scenario'!$F:$F,DB!$L16,'FY 26_qualification scenario'!$M:$M,DB!$M16) -> 67 | O16: =COUNTIFS('FY 26_qualification scenario'!$BI:$BI,DB!O$4,'FY 26_qualification scenario'!$I:$I,DB!$K16,'FY 26_qualification scenario'!$F:$F,DB!$L16,'FY 26_qualification scenario'!$M:$M,DB!$M16) -> 1 | P16: =COUNTIFS('FY 26_qualification scenario'!$BI:$BI,DB!P$4,'FY 26_qualification scenario'!$I:$I,DB!$K16,'FY 26_qualification scenario'!$F:$F,DB!$L16,'FY 26_qualification scenario'!$M:$M,DB!$M16) -> 0 | Q16: =COUNTIFS('FY 26_qualification scenario'!$BI:$BI,DB!Q$4,'FY 26_qualification scenario'!$I:$I,DB!$K16,'FY 26_qualification scenario'!$F:$F,DB!$L16,'FY 26_qualification scenario'!$M:$M,DB!$M16) -> 0 | R16: =COUNTIFS('FY 26_qualification scenario'!$BI:$BI,DB!R$4,'FY 26_qualification scenario'!$I:$I,DB!$K16,'FY 26_qualification scenario'!$F:$F,DB!$L16,'FY 26_qualification scenario'!$M:$M,DB!$M16) -> 0 | S16: =COUNTIFS('FY 26_qualification scenario'!$BI:$BI,DB!S$4,'FY 26_qualification scenario'!$I:$I,DB!$K16,'FY 26_qualification scenario'!$F:$F,DB!$L16,'FY 26_qualification scenario'!$M:$M,DB!$M16) -> 0
A17: HARYANA | B17: =IFERROR(VLOOKUP(A17,$L$5:$M$69,2,0),"-") -> North | C17: =SUMIFS(N$5:N$69,$L$5:$L$69,$A17,$M$5:$M$69,$B17) -> 280 | D17: =SUMIFS(O$5:O$69,$L$5:$L$69,$A17,$M$5:$M$69,$B17) -> 8 | E17: =SUMIFS(P$5:P$69,$L$5:$L$69,$A17,$M$5:$M$69,$B17) -> 22 | F17: =SUMIFS(Q$5:Q$69,$L$5:$L$69,$A17,$M$5:$M$69,$B17) -> 13 | G17: =SUMIFS(R$5:R$69,$L$5:$L$69,$A17,$M$5:$M$69,$B17) -> 19 | H17: =SUMIFS(S$5:S$69,$L$5:$L$69,$A17,$M$5:$M$69,$B17) -> 5 | K17: GOLDWIN ISPAT PRIVATE LIMITED | L17: ODISHA | M17: Central | N17: =COUNTIFS('FY 26_qualification scenario'!$I:$I,DB!$K17,'FY 26_qualification scenario'!$F:$F,DB!$L17,'FY 26_qualification scenario'!$M:$M,DB!$M17) -> 6 | O17: =COUNTIFS('FY 26_qualification scenario'!$BI:$BI,DB!O$4,'FY 26_qualification scenario'!$I:$I,DB!$K17,'FY 26_qualification scenario'!$F:$F,DB!$L17,'FY 26_qualification scenario'!$M:$M,DB!$M17) -> 0 | P17: =COUNTIFS('FY 26_qualification scenario'!$BI:$BI,DB!P$4,'FY 26_qualification scenario'!$I:$I,DB!$K17,'FY 26_qualification scenario'!$F:$F,DB!$L17,'FY 26_qualification scenario'!$M:$M,DB!$M17) -> 1 | Q17: =COUNTIFS('FY 26_qualification scenario'!$BI:$BI,DB!Q$4,'FY 26_qualification scenario'!$I:$I,DB!$K17,'FY 26_qualification scenario'!$F:$F,DB!$L17,'FY 26_qualification scenario'!$M:$M,DB!$M17) -> 0 | R17: =COUNTIFS('FY 26_qualification scenario'!$BI:$BI,DB!R$4,'FY 26_qualification scenario'!$I:$I,DB!$K17,'FY 26_qualification scenario'!$F:$F,DB!$L17,'FY 26_qualification scenario'!$M:$M,DB!$M17) -> 0 | S17: =COUNTIFS('FY 26_qualification scenario'!$BI:$BI,DB!S$4,'FY 26_qualification scenario'!$I:$I,DB!$K17,'FY 26_qualification scenario'!$F:$F,DB!$L17,'FY 26_qualification scenario'!$M:$M,DB!$M17) -> 0
A18: PUNJAB | B18: =IFERROR(VLOOKUP(A18,$L$5:$M$69,2,0),"-") -> North | C18: =SUMIFS(N$5:N$69,$L$5:$L$69,$A18,$M$5:$M$69,$B18) -> 111 | D18: =SUMIFS(O$5:O$69,$L$5:$L$69,$A18,$M$5:$M$69,$B18) -> 5 | E18: =SUMIFS(P$5:P$69,$L$5:$L$69,$A18,$M$5:$M$69,$B18) -> 3 | F18: =SUMIFS(Q$5:Q$69,$L$5:$L$69,$A18,$M$5:$M$69,$B18) -> 0 | G18: =SUMIFS(R$5:R$69,$L$5:$L$69,$A18,$M$5:$M$69,$B18) -> 1 | H18: =SUMIFS(S$5:S$69,$L$5:$L$69,$A18,$M$5:$M$69,$B18) -> 1 | K18: J P ALLOYS | L18: RAJASTHAN | M18: North | N18: =COUNTIFS('FY 26_qualification scenario'!$I:$I,DB!$K18,'FY 26_qualification scenario'!$F:$F,DB!$L18,'FY 26_qualification scenario'!$M:$M,DB!$M18) -> 72 | O18: =COUNTIFS('FY 26_qualification scenario'!$BI:$BI,DB!O$4,'FY 26_qualification scenario'!$I:$I,DB!$K18,'FY 26_qualification scenario'!$F:$F,DB!$L18,'FY 26_qualification scenario'!$M:$M,DB!$M18) -> 1 | P18: =COUNTIFS('FY 26_qualification scenario'!$BI:$BI,DB!P$4,'FY 26_qualification scenario'!$I:$I,DB!$K18,'FY 26_qualification scenario'!$F:$F,DB!$L18,'FY 26_qualification scenario'!$M:$M,DB!$M18) -> 6 | Q18: =COUNTIFS('FY 26_qualification scenario'!$BI:$BI,DB!Q$4,'FY 26_qualification scenario'!$I:$I,DB!$K18,'FY 26_qualification scenario'!$F:$F,DB!$L18,'FY 26_qualification scenario'!$M:$M,DB!$M18) -> 1 | R18: =COUNTIFS('FY 26_qualification scenario'!$BI:$BI,DB!R$4,'FY 26_qualification scenario'!$I:$I,DB!$K18,'FY 26_qualification scenario'!$F:$F,DB!$L18,'FY 26_qualification scenario'!$M:$M,DB!$M18) -> 5 | S18: =COUNTIFS('FY 26_qualification scenario'!$BI:$BI,DB!S$4,'FY 26_qualification scenario'!$I:$I,DB!$K18,'FY 26_qualification scenario'!$F:$F,DB!$L18,'FY 26_qualification scenario'!$M:$M,DB!$M18) -> 0
A19: DELHI | B19: =IFERROR(VLOOKUP(A19,$L$5:$M$69,2,0),"-") -> North | C19: =SUMIFS(N$5:N$69,$L$5:$L$69,$A19,$M$5:$M$69,$B19) -> 79 | D19: =SUMIFS(O$5:O$69,$L$5:$L$69,$A19,$M$5:$M$69,$B19) -> 3 | E19: =SUMIFS(P$5:P$69,$L$5:$L$69,$A19,$M$5:$M$69,$B19) -> 2 | F19: =SUMIFS(Q$5:Q$69,$L$5:$L$69,$A19,$M$5:$M$69,$B19) -> 2 | G19: =SUMIFS(R$5:R$69,$L$5:$L$69,$A19,$M$5:$M$69,$B19) -> 1 | H19: =SUMIFS(S$5:S$69,$L$5:$L$69,$A19,$M$5:$M$69,$B19) -> 1 | K19: JAI DURGA STEELS | L19: HARYANA | M19: North | N19: =COUNTIFS('FY 26_qualification scenario'!$I:$I,DB!$K19,'FY 26_qualification scenario'!$F:$F,DB!$L19,'FY 26_qualification scenario'!$M:$M,DB!$M19) -> 45 | O19: =COUNTIFS('FY 26_qualification scenario'!$BI:$BI,DB!O$4,'FY 26_qualification scenario'!$I:$I,DB!$K19,'FY 26_qualification scenario'!$F:$F,DB!$L19,'FY 26_qualification scenario'!$M:$M,DB!$M19) -> 1 | P19: =COUNTIFS('FY 26_qualification scenario'!$BI:$BI,DB!P$4,'FY 26_qualification scenario'!$I:$I,DB!$K19,'FY 26_qualification scenario'!$F:$F,DB!$L19,'FY 26_qualification scenario'!$M:$M,DB!$M19) -> 4 | Q19: =COUNTIFS('FY 26_qualification scenario'!$BI:$BI,DB!Q$4,'FY 26_qualification scenario'!$I:$I,DB!$K19,'FY 26_qualification scenario'!$F:$F,DB!$L19,'FY 26_qualification scenario'!$M:$M,DB!$M19) -> 4 | R19: =COUNTIFS('FY 26_qualification scenario'!$BI:$BI,DB!R$4,'FY 26_qualification scenario'!$I:$I,DB!$K19,'FY 26_qualification scenario'!$F:$F,DB!$L19,'FY 26_qualification scenario'!$M:$M,DB!$M19) -> 9 | S19: =COUNTIFS('FY 26_qualification scenario'!$BI:$BI,DB!S$4,'FY 26_qualification scenario'!$I:$I,DB!$K19,'FY 26_qualification scenario'!$F:$F,DB!$L19,'FY 26_qualification scenario'!$M:$M,DB!$M19) -> 2
A20: HIMACHAL PRADESH | B20: =IFERROR(VLOOKUP(A20,$L$5:$M$69,2,0),"-") -> North | C20: =SUMIFS(N$5:N$69,$L$5:$L$69,$A20,$M$5:$M$69,$B20) -> 19 | D20: =SUMIFS(O$5:O$69,$L$5:$L$69,$A20,$M$5:$M$69,$B20) -> 0 | E20: =SUMIFS(P$5:P$69,$L$5:$L$69,$A20,$M$5:$M$69,$B20) -> 0 | F20: =SUMIFS(Q$5:Q$69,$L$5:$L$69,$A20,$M$5:$M$69,$B20) -> 0 | G20: =SUMIFS(R$5:R$69,$L$5:$L$69,$A20,$M$5:$M$69,$B20) -> 1 | H20: =SUMIFS(S$5:S$69,$L$5:$L$69,$A20,$M$5:$M$69,$B20) -> 0 | K20: JAI MATA DI STEELS | L20: WEST BENGAL | M20: East | N20: =COUNTIFS('FY 26_qualification scenario'!$I:$I,DB!$K20,'FY 26_qualification scenario'!$F:$F,DB!$L20,'FY 26_qualification scenario'!$M:$M,DB!$M20) -> 8 | O20: =COUNTIFS('FY 26_qualification scenario'!$BI:$BI,DB!O$4,'FY 26_qualification scenario'!$I:$I,DB!$K20,'FY 26_qualification scenario'!$F:$F,DB!$L20,'FY 26_qualification scenario'!$M:$M,DB!$M20) -> 0 | P20: =COUNTIFS('FY 26_qualification scenario'!$BI:$BI,DB!P$4,'FY 26_qualification scenario'!$I:$I,DB!$K20,'FY 26_qualification scenario'!$F:$F,DB!$L20,'FY 26_qualification scenario'!$M:$M,DB!$M20) -> 0 | Q20: =COUNTIFS('FY 26_qualification scenario'!$BI:$BI,DB!Q$4,'FY 26_qualification scenario'!$I:$I,DB!$K20,'FY 26_qualification scenario'!$F:$F,DB!$L20,'FY 26_qualification scenario'!$M:$M,DB!$M20) -> 0 | R20: =COUNTIFS('FY 26_qualification scenario'!$BI:$BI,DB!R$4,'FY 26_qualification scenario'!$I:$I,DB!$K20,'FY 26_qualification scenario'!$F:$F,DB!$L20,'FY 26_qualification scenario'!$M:$M,DB!$M20) -> 0 | S20: =COUNTIFS('FY 26_qualification scenario'!$BI:$BI,DB!S$4,'FY 26_qualification scenario'!$I:$I,DB!$K20,'FY 26_qualification scenario'!$F:$F,DB!$L20,'FY 26_qualification scenario'!$M:$M,DB!$M20) -> 0
A21: CHANDIGARH | B21: =IFERROR(VLOOKUP(A21,$L$5:$M$69,2,0),"-") -> North | C21: =SUMIFS(N$5:N$69,$L$5:$L$69,$A21,$M$5:$M$69,$B21) -> 5 | D21: =SUMIFS(O$5:O$69,$L$5:$L$69,$A21,$M$5:$M$69,$B21) -> 0 | E21: =SUMIFS(P$5:P$69,$L$5:$L$69,$A21,$M$5:$M$69,$B21) -> 0 | F21: =SUMIFS(Q$5:Q$69,$L$5:$L$69,$A21,$M$5:$M$69,$B21) -> 0 | G21: =SUMIFS(R$5:R$69,$L$5:$L$69,$A21,$M$5:$M$69,$B21) -> 0 | H21: =SUMIFS(S$5:S$69,$L$5:$L$69,$A21,$M$5:$M$69,$B21) -> 0 | K21: K P ENTERPRISES | L21: UTTAR PRADESH | M21: North | N21: =COUNTIFS('FY 26_qualification scenario'!$I:$I,DB!$K21,'FY 26_qualification scenario'!$F:$F,DB!$L21,'FY 26_qualification scenario'!$M:$M,DB!$M21) -> 4 | O21: =COUNTIFS('FY 26_qualification scenario'!$BI:$BI,DB!O$4,'FY 26_qualification scenario'!$I:$I,DB!$K21,'FY 26_qualification scenario'!$F:$F,DB!$L21,'FY 26_qualification scenario'!$M:$M,DB!$M21) -> 0 | P21: =COUNTIFS('FY 26_qualification scenario'!$BI:$BI,DB!P$4,'FY 26_qualification scenario'!$I:$I,DB!$K21,'FY 26_qualification scenario'!$F:$F,DB!$L21,'FY 26_qualification scenario'!$M:$M,DB!$M21) -> 0 | Q21: =COUNTIFS('FY 26_qualification scenario'!$BI:$BI,DB!Q$4,'FY 26_qualification scenario'!$I:$I,DB!$K21,'FY 26_qualification scenario'!$F:$F,DB!$L21,'FY 26_qualification scenario'!$M:$M,DB!$M21) -> 0 | R21: =COUNTIFS('FY 26_qualification scenario'!$BI:$BI,DB!R$4,'FY 26_qualification scenario'!$I:$I,DB!$K21,'FY 26_qualification scenario'!$F:$F,DB!$L21,'FY 26_qualification scenario'!$M:$M,DB!$M21) -> 0 | S21: =COUNTIFS('FY 26_qualification scenario'!$BI:$BI,DB!S$4,'FY 26_qualification scenario'!$I:$I,DB!$K21,'FY 26_qualification scenario'!$F:$F,DB!$L21,'FY 26_qualification scenario'!$M:$M,DB!$M21) -> 0
A22: UTTARAKHAND | B22: =IFERROR(VLOOKUP(A22,$L$5:$M$69,2,0),"-") -> North | C22: =SUMIFS(N$5:N$69,$L$5:$L$69,$A22,$M$5:$M$69,$B22) -> 74 | D22: =SUMIFS(O$5:O$69,$L$5:$L$69,$A22,$M$5:$M$69,$B22) -> 3 | E22: =SUMIFS(P$5:P$69,$L$5:$L$69,$A22,$M$5:$M$69,$B22) -> 1 | F22: =SUMIFS(Q$5:Q$69,$L$5:$L$69,$A22,$M$5:$M$69,$B22) -> 0 | G22: =SUMIFS(R$5:R$69,$L$5:$L$69,$A22,$M$5:$M$69,$B22) -> 0 | H22: =SUMIFS(S$5:S$69,$L$5:$L$69,$A22,$M$5:$M$69,$B22) -> 0 | K22: KASHMIR IRON TRADER | L22: JAMMU AND KASHMIR | M22: North | N22: =COUNTIFS('FY 26_qualification scenario'!$I:$I,DB!$K22,'FY 26_qualification scenario'!$F:$F,DB!$L22,'FY 26_qualification scenario'!$M:$M,DB!$M22) -> 2 | O22: =COUNTIFS('FY 26_qualification scenario'!$BI:$BI,DB!O$4,'FY 26_qualification scenario'!$I:$I,DB!$K22,'FY 26_qualification scenario'!$F:$F,DB!$L22,'FY 26_qualification scenario'!$M:$M,DB!$M22) -> 0 | P22: =COUNTIFS('FY 26_qualification scenario'!$BI:$BI,DB!P$4,'FY 26_qualification scenario'!$I:$I,DB!$K22,'FY 26_qualification scenario'!$F:$F,DB!$L22,'FY 26_qualification scenario'!$M:$M,DB!$M22) -> 0 | Q22: =COUNTIFS('FY 26_qualification scenario'!$BI:$BI,DB!Q$4,'FY 26_qualification scenario'!$I:$I,DB!$K22,'FY 26_qualification scenario'!$F:$F,DB!$L22,'FY 26_qualification scenario'!$M:$M,DB!$M22) -> 0 | R22: =COUNTIFS('FY 26_qualification scenario'!$BI:$BI,DB!R$4,'FY 26_qualification scenario'!$I:$I,DB!$K22,'FY 26_qualification scenario'!$F:$F,DB!$L22,'FY 26_qualification scenario'!$M:$M,DB!$M22) -> 0 | S22: =COUNTIFS('FY 26_qualification scenario'!$BI:$BI,DB!S$4,'FY 26_qualification scenario'!$I:$I,DB!$K22,'FY 26_qualification scenario'!$F:$F,DB!$L22,'FY 26_qualification scenario'!$M:$M,DB!$M22) -> 0
A23: GUJARAT | B23: =IFERROR(VLOOKUP(A23,$L$5:$M$69,2,0),"-") -> West | C23: =SUMIFS(N$5:N$69,$L$5:$L$69,$A23,$M$5:$M$69,$B23) -> 2 | D23: =SUMIFS(O$5:O$69,$L$5:$L$69,$A23,$M$5:$M$69,$B23) -> 0 | E23: =SUMIFS(P$5:P$69,$L$5:$L$69,$A23,$M$5:$M$69,$B23) -> 0 | F23: =SUMIFS(Q$5:Q$69,$L$5:$L$69,$A23,$M$5:$M$69,$B23) -> 0 | G23: =SUMIFS(R$5:R$69,$L$5:$L$69,$A23,$M$5:$M$69,$B23) -> 0 | H23: =SUMIFS(S$5:S$69,$L$5:$L$69,$A23,$M$5:$M$69,$B23) -> 0 | K23: KEDIA PIPES PRIVATE LMITED | L23: WEST BENGAL | M23: East | N23: =COUNTIFS('FY 26_qualification scenario'!$I:$I,DB!$K23,'FY 26_qualification scenario'!$F:$F,DB!$L23,'FY 26_qualification scenario'!$M:$M,DB!$M23) -> 12 | O23: =COUNTIFS('FY 26_qualification scenario'!$BI:$BI,DB!O$4,'FY 26_qualification scenario'!$I:$I,DB!$K23,'FY 26_qualification scenario'!$F:$F,DB!$L23,'FY 26_qualification scenario'!$M:$M,DB!$M23) -> 0 | P23: =COUNTIFS('FY 26_qualification scenario'!$BI:$BI,DB!P$4,'FY 26_qualification scenario'!$I:$I,DB!$K23,'FY 26_qualification scenario'!$F:$F,DB!$L23,'FY 26_qualification scenario'!$M:$M,DB!$M23) -> 0 | Q23: =COUNTIFS('FY 26_qualification scenario'!$BI:$BI,DB!Q$4,'FY 26_qualification scenario'!$I:$I,DB!$K23,'FY 26_qualification scenario'!$F:$F,DB!$L23,'FY 26_qualification scenario'!$M:$M,DB!$M23) -> 0 | R23: =COUNTIFS('FY 26_qualification scenario'!$BI:$BI,DB!R$4,'FY 26_qualification scenario'!$I:$I,DB!$K23,'FY 26_qualification scenario'!$F:$F,DB!$L23,'FY 26_qualification scenario'!$M:$M,DB!$M23) -> 0 | S23: =COUNTIFS('FY 26_qualification scenario'!$BI:$BI,DB!S$4,'FY 26_qualification scenario'!$I:$I,DB!$K23,'FY 26_qualification scenario'!$F:$F,DB!$L23,'FY 26_qualification scenario'!$M:$M,DB!$M23) -> 0
A24: Total | C24: =SUM(C5:C23) -> 1745 | D24: =SUM(D5:D23) -> 50 | E24: =SUM(E5:E23) -> 59 | F24: =SUM(F5:F23) -> 25 | G24: =SUM(G5:G23) -> 41 | H24: =SUM(H5:H23) -> 9 | K24: Khandelwal Associates | L24: UTTAR PRADESH | M24: North | N24: =COUNTIFS('FY 26_qualification scenario'!$I:$I,DB!$K24,'FY 26_qualification scenario'!$F:$F,DB!$L24,'FY 26_qualification scenario'!$M:$M,DB!$M24) -> 23 | O24: =COUNTIFS('FY 26_qualification scenario'!$BI:$BI,DB!O$4,'FY 26_qualification scenario'!$I:$I,DB!$K24,'FY 26_qualification scenario'!$F:$F,DB!$L24,'FY 26_qualification scenario'!$M:$M,DB!$M24) -> 3 | P24: =COUNTIFS('FY 26_qualification scenario'!$BI:$BI,DB!P$4,'FY 26_qualification scenario'!$I:$I,DB!$K24,'FY 26_qualification scenario'!$F:$F,DB!$L24,'FY 26_qualification scenario'!$M:$M,DB!$M24) -> 1 | Q24: =COUNTIFS('FY 26_qualification scenario'!$BI:$BI,DB!Q$4,'FY 26_qualification scenario'!$I:$I,DB!$K24,'FY 26_qualification scenario'!$F:$F,DB!$L24,'FY 26_qualification scenario'!$M:$M,DB!$M24) -> 0 | R24: =COUNTIFS('FY 26_qualification scenario'!$BI:$BI,DB!R$4,'FY 26_qualification scenario'!$I:$I,DB!$K24,'FY 26_qualification scenario'!$F:$F,DB!$L24,'FY 26_qualification scenario'!$M:$M,DB!$M24) -> 0 | S24: =COUNTIFS('FY 26_qualification scenario'!$BI:$BI,DB!S$4,'FY 26_qualification scenario'!$I:$I,DB!$K24,'FY 26_qualification scenario'!$F:$F,DB!$L24,'FY 26_qualification scenario'!$M:$M,DB!$M24) -> 1
K25: KHARAKIA METALS PRIVATE LIMITED | L25: BIHAR | M25: East | N25: =COUNTIFS('FY 26_qualification scenario'!$I:$I,DB!$K25,'FY 26_qualification scenario'!$F:$F,DB!$L25,'FY 26_qualification scenario'!$M:$M,DB!$M25) -> 23 | O25: =COUNTIFS('FY 26_qualification scenario'!$BI:$BI,DB!O$4,'FY 26_qualification scenario'!$I:$I,DB!$K25,'FY 26_qualification scenario'!$F:$F,DB!$L25,'FY 26_qualification scenario'!$M:$M,DB!$M25) -> 1 | P25: =COUNTIFS('FY 26_qualification scenario'!$BI:$BI,DB!P$4,'FY 26_qualification scenario'!$I:$I,DB!$K25,'FY 26_qualification scenario'!$F:$F,DB!$L25,'FY 26_qualification scenario'!$M:$M,DB!$M25) -> 0 | Q25: =COUNTIFS('FY 26_qualification scenario'!$BI:$BI,DB!Q$4,'FY 26_qualification scenario'!$I:$I,DB!$K25,'FY 26_qualification scenario'!$F:$F,DB!$L25,'FY 26_qualification scenario'!$M:$M,DB!$M25) -> 0 | R25: =COUNTIFS('FY 26_qualification scenario'!$BI:$BI,DB!R$4,'FY 26_qualification scenario'!$I:$I,DB!$K25,'FY 26_qualification scenario'!$F:$F,DB!$L25,'FY 26_qualification scenario'!$M:$M,DB!$M25) -> 0 | S25: =COUNTIFS('FY 26_qualification scenario'!$BI:$BI,DB!S$4,'FY 26_qualification scenario'!$I:$I,DB!$K25,'FY 26_qualification scenario'!$F:$F,DB!$L25,'FY 26_qualification scenario'!$M:$M,DB!$M25) -> 0
K26: KHUNTETA STEELS | L26: RAJASTHAN | M26: North | N26: =COUNTIFS('FY 26_qualification scenario'!$I:$I,DB!$K26,'FY 26_qualification scenario'!$F:$F,DB!$L26,'FY 26_qualification scenario'!$M:$M,DB!$M26) -> 23 | O26: =COUNTIFS('FY 26_qualification scenario'!$BI:$BI,DB!O$4,'FY 26_qualification scenario'!$I:$I,DB!$K26,'FY 26_qualification scenario'!$F:$F,DB!$L26,'FY 26_qualification scenario'!$M:$M,DB!$M26) -> 0 | P26: =COUNTIFS('FY 26_qualification scenario'!$BI:$BI,DB!P$4,'FY 26_qualification scenario'!$I:$I,DB!$K26,'FY 26_qualification scenario'!$F:$F,DB!$L26,'FY 26_qualification scenario'!$M:$M,DB!$M26) -> 0 | Q26: =COUNTIFS('FY 26_qualification scenario'!$BI:$BI,DB!Q$4,'FY 26_qualification scenario'!$I:$I,DB!$K26,'FY 26_qualification scenario'!$F:$F,DB!$L26,'FY 26_qualification scenario'!$M:$M,DB!$M26) -> 0 | R26: =COUNTIFS('FY 26_qualification scenario'!$BI:$BI,DB!R$4,'FY 26_qualification scenario'!$I:$I,DB!$K26,'FY 26_qualification scenario'!$F:$F,DB!$L26,'FY 26_qualification scenario'!$M:$M,DB!$M26) -> 0 | S26: =COUNTIFS('FY 26_qualification scenario'!$BI:$BI,DB!S$4,'FY 26_qualification scenario'!$I:$I,DB!$K26,'FY 26_qualification scenario'!$F:$F,DB!$L26,'FY 26_qualification scenario'!$M:$M,DB!$M26) -> 0
K27: LAXMI ENTERPRISES | L27: CHHATTISGARH | M27: Central | N27: =COUNTIFS('FY 26_qualification scenario'!$I:$I,DB!$K27,'FY 26_qualification scenario'!$F:$F,DB!$L27,'FY 26_qualification scenario'!$M:$M,DB!$M27) -> 4 | O27: =COUNTIFS('FY 26_qualification scenario'!$BI:$BI,DB!O$4,'FY 26_qualification scenario'!$I:$I,DB!$K27,'FY 26_qualification scenario'!$F:$F,DB!$L27,'FY 26_qualification scenario'!$M:$M,DB!$M27) -> 0 | P27: =COUNTIFS('FY 26_qualification scenario'!$BI:$BI,DB!P$4,'FY 26_qualification scenario'!$I:$I,DB!$K27,'FY 26_qualification scenario'!$F:$F,DB!$L27,'FY 26_qualification scenario'!$M:$M,DB!$M27) -> 0 | Q27: =COUNTIFS('FY 26_qualification scenario'!$BI:$BI,DB!Q$4,'FY 26_qualification scenario'!$I:$I,DB!$K27,'FY 26_qualification scenario'!$F:$F,DB!$L27,'FY 26_qualification scenario'!$M:$M,DB!$M27) -> 0 | R27: =COUNTIFS('FY 26_qualification scenario'!$BI:$BI,DB!R$4,'FY 26_qualification scenario'!$I:$I,DB!$K27,'FY 26_qualification scenario'!$F:$F,DB!$L27,'FY 26_qualification scenario'!$M:$M,DB!$M27) -> 0 | S27: =COUNTIFS('FY 26_qualification scenario'!$BI:$BI,DB!S$4,'FY 26_qualification scenario'!$I:$I,DB!$K27,'FY 26_qualification scenario'!$F:$F,DB!$L27,'FY 26_qualification scenario'!$M:$M,DB!$M27) -> 0
K28: M R Associates | L28: RAJASTHAN | M28: North | N28: =COUNTIFS('FY 26_qualification scenario'!$I:$I,DB!$K28,'FY 26_qualification scenario'!$F:$F,DB!$L28,'FY 26_qualification scenario'!$M:$M,DB!$M28) -> 42 | O28: =COUNTIFS('FY 26_qualification scenario'!$BI:$BI,DB!O$4,'FY 26_qualification scenario'!$I:$I,DB!$K28,'FY 26_qualification scenario'!$F:$F,DB!$L28,'FY 26_qualification scenario'!$M:$M,DB!$M28) -> 4 | P28: =COUNTIFS('FY 26_qualification scenario'!$BI:$BI,DB!P$4,'FY 26_qualification scenario'!$I:$I,DB!$K28,'FY 26_qualification scenario'!$F:$F,DB!$L28,'FY 26_qualification scenario'!$M:$M,DB!$M28) -> 4 | Q28: =COUNTIFS('FY 26_qualification scenario'!$BI:$BI,DB!Q$4,'FY 26_qualification scenario'!$I:$I,DB!$K28,'FY 26_qualification scenario'!$F:$F,DB!$L28,'FY 26_qualification scenario'!$M:$M,DB!$M28) -> 1 | R28: =COUNTIFS('FY 26_qualification scenario'!$BI:$BI,DB!R$4,'FY 26_qualification scenario'!$I:$I,DB!$K28,'FY 26_qualification scenario'!$F:$F,DB!$L28,'FY 26_qualification scenario'!$M:$M,DB!$M28) -> 1 | S28: =COUNTIFS('FY 26_qualification scenario'!$BI:$BI,DB!S$4,'FY 26_qualification scenario'!$I:$I,DB!$K28,'FY 26_qualification scenario'!$F:$F,DB!$L28,'FY 26_qualification scenario'!$M:$M,DB!$M28) -> 0
K29: M/S JAI BALAJEE ENTERPRISES | L29: JHARKHAND | M29: East | N29: =COUNTIFS('FY 26_qualification scenario'!$I:$I,DB!$K29,'FY 26_qualification scenario'!$F:$F,DB!$L29,'FY 26_qualification scenario'!$M:$M,DB!$M29) -> 5 | O29: =COUNTIFS('FY 26_qualification scenario'!$BI:$BI,DB!O$4,'FY 26_qualification scenario'!$I:$I,DB!$K29,'FY 26_qualification scenario'!$F:$F,DB!$L29,'FY 26_qualification scenario'!$M:$M,DB!$M29) -> 0 | P29: =COUNTIFS('FY 26_qualification scenario'!$BI:$BI,DB!P$4,'FY 26_qualification scenario'!$I:$I,DB!$K29,'FY 26_qualification scenario'!$F:$F,DB!$L29,'FY 26_qualification scenario'!$M:$M,DB!$M29) -> 0 | Q29: =COUNTIFS('FY 26_qualification scenario'!$BI:$BI,DB!Q$4,'FY 26_qualification scenario'!$I:$I,DB!$K29,'FY 26_qualification scenario'!$F:$F,DB!$L29,'FY 26_qualification scenario'!$M:$M,DB!$M29) -> 0 | R29: =COUNTIFS('FY 26_qualification scenario'!$BI:$BI,DB!R$4,'FY 26_qualification scenario'!$I:$I,DB!$K29,'FY 26_qualification scenario'!$F:$F,DB!$L29,'FY 26_qualification scenario'!$M:$M,DB!$M29) -> 0 | S29: =COUNTIFS('FY 26_qualification scenario'!$BI:$BI,DB!S$4,'FY 26_qualification scenario'!$I:$I,DB!$K29,'FY 26_qualification scenario'!$F:$F,DB!$L29,'FY 26_qualification scenario'!$M:$M,DB!$M29) -> 0
K30: M/s REAL DREAMS ENTERPRISES | L30: JHARKHAND | M30: East | N30: =COUNTIFS('FY 26_qualification scenario'!$I:$I,DB!$K30,'FY 26_qualification scenario'!$F:$F,DB!$L30,'FY 26_qualification scenario'!$M:$M,DB!$M30) -> 25 | O30: =COUNTIFS('FY 26_qualification scenario'!$BI:$BI,DB!O$4,'FY 26_qualification scenario'!$I:$I,DB!$K30,'FY 26_qualification scenario'!$F:$F,DB!$L30,'FY 26_qualification scenario'!$M:$M,DB!$M30) -> 1 | P30: =COUNTIFS('FY 26_qualification scenario'!$BI:$BI,DB!P$4,'FY 26_qualification scenario'!$I:$I,DB!$K30,'FY 26_qualification scenario'!$F:$F,DB!$L30,'FY 26_qualification scenario'!$M:$M,DB!$M30) -> 0 | Q30: =COUNTIFS('FY 26_qualification scenario'!$BI:$BI,DB!Q$4,'FY 26_qualification scenario'!$I:$I,DB!$K30,'FY 26_qualification scenario'!$F:$F,DB!$L30,'FY 26_qualification scenario'!$M:$M,DB!$M30) -> 0 | R30: =COUNTIFS('FY 26_qualification scenario'!$BI:$BI,DB!R$4,'FY 26_qualification scenario'!$I:$I,DB!$K30,'FY 26_qualification scenario'!$F:$F,DB!$L30,'FY 26_qualification scenario'!$M:$M,DB!$M30) -> 0 | S30: =COUNTIFS('FY 26_qualification scenario'!$BI:$BI,DB!S$4,'FY 26_qualification scenario'!$I:$I,DB!$K30,'FY 26_qualification scenario'!$F:$F,DB!$L30,'FY 26_qualification scenario'!$M:$M,DB!$M30) -> 0
K31: M/S TIRUPATI SALES | L31: JHARKHAND | M31: East | N31: =COUNTIFS('FY 26_qualification scenario'!$I:$I,DB!$K31,'FY 26_qualification scenario'!$F:$F,DB!$L31,'FY 26_qualification scenario'!$M:$M,DB!$M31) -> 0 | O31: =COUNTIFS('FY 26_qualification scenario'!$BI:$BI,DB!O$4,'FY 26_qualification scenario'!$I:$I,DB!$K31,'FY 26_qualification scenario'!$F:$F,DB!$L31,'FY 26_qualification scenario'!$M:$M,DB!$M31) -> 0 | P31: =COUNTIFS('FY 26_qualification scenario'!$BI:$BI,DB!P$4,'FY 26_qualification scenario'!$I:$I,DB!$K31,'FY 26_qualification scenario'!$F:$F,DB!$L31,'FY 26_qualification scenario'!$M:$M,DB!$M31) -> 0 | Q31: =COUNTIFS('FY 26_qualification scenario'!$BI:$BI,DB!Q$4,'FY 26_qualification scenario'!$I:$I,DB!$K31,'FY 26_qualification scenario'!$F:$F,DB!$L31,'FY 26_qualification scenario'!$M:$M,DB!$M31) -> 0 | R31: =COUNTIFS('FY 26_qualification scenario'!$BI:$BI,DB!R$4,'FY 26_qualification scenario'!$I:$I,DB!$K31,'FY 26_qualification scenario'!$F:$F,DB!$L31,'FY 26_qualification scenario'!$M:$M,DB!$M31) -> 0 | S31: =COUNTIFS('FY 26_qualification scenario'!$BI:$BI,DB!S$4,'FY 26_qualification scenario'!$I:$I,DB!$K31,'FY 26_qualification scenario'!$F:$F,DB!$L31,'FY 26_qualification scenario'!$M:$M,DB!$M31) -> 0
K32: MADHYA BHARAT ISPAT PRIVATE LIMITED | L32: CHHATTISGARH | M32: Central | N32: =COUNTIFS('FY 26_qualification scenario'!$I:$I,DB!$K32,'FY 26_qualification scenario'!$F:$F,DB!$L32,'FY 26_qualification scenario'!$M:$M,DB!$M32) -> 18 | O32: =COUNTIFS('FY 26_qualification scenario'!$BI:$BI,DB!O$4,'FY 26_qualification scenario'!$I:$I,DB!$K32,'FY 26_qualification scenario'!$F:$F,DB!$L32,'FY 26_qualification scenario'!$M:$M,DB!$M32) -> 0 | P32: =COUNTIFS('FY 26_qualification scenario'!$BI:$BI,DB!P$4,'FY 26_qualification scenario'!$I:$I,DB!$K32,'FY 26_qualification scenario'!$F:$F,DB!$L32,'FY 26_qualification scenario'!$M:$M,DB!$M32) -> 0 | Q32: =COUNTIFS('FY 26_qualification scenario'!$BI:$BI,DB!Q$4,'FY 26_qualification scenario'!$I:$I,DB!$K32,'FY 26_qualification scenario'!$F:$F,DB!$L32,'FY 26_qualification scenario'!$M:$M,DB!$M32) -> 0 | R32: =COUNTIFS('FY 26_qualification scenario'!$BI:$BI,DB!R$4,'FY 26_qualification scenario'!$I:$I,DB!$K32,'FY 26_qualification scenario'!$F:$F,DB!$L32,'FY 26_qualification scenario'!$M:$M,DB!$M32) -> 0 | S32: =COUNTIFS('FY 26_qualification scenario'!$BI:$BI,DB!S$4,'FY 26_qualification scenario'!$I:$I,DB!$K32,'FY 26_qualification scenario'!$F:$F,DB!$L32,'FY 26_qualification scenario'!$M:$M,DB!$M32) -> 0
K33: MAHAVIR STEEL CORPORATION | L33: PUNJAB | M33: North | N33: =COUNTIFS('FY 26_qualification scenario'!$I:$I,DB!$K33,'FY 26_qualification scenario'!$F:$F,DB!$L33,'FY 26_qualification scenario'!$M:$M,DB!$M33) -> 31 | O33: =COUNTIFS('FY 26_qualification scenario'!$BI:$BI,DB!O$4,'FY 26_qualification scenario'!$I:$I,DB!$K33,'FY 26_qualification scenario'!$F:$F,DB!$L33,'FY 26_qualification scenario'!$M:$M,DB!$M33) -> 1 | P33: =COUNTIFS('FY 26_qualification scenario'!$BI:$BI,DB!P$4,'FY 26_qualification scenario'!$I:$I,DB!$K33,'FY 26_qualification scenario'!$F:$F,DB!$L33,'FY 26_qualification scenario'!$M:$M,DB!$M33) -> 1 | Q33: =COUNTIFS('FY 26_qualification scenario'!$BI:$BI,DB!Q$4,'FY 26_qualification scenario'!$I:$I,DB!$K33,'FY 26_qualification scenario'!$F:$F,DB!$L33,'FY 26_qualification scenario'!$M:$M,DB!$M33) -> 0 | R33: =COUNTIFS('FY 26_qualification scenario'!$BI:$BI,DB!R$4,'FY 26_qualification scenario'!$I:$I,DB!$K33,'FY 26_qualification scenario'!$F:$F,DB!$L33,'FY 26_qualification scenario'!$M:$M,DB!$M33) -> 0 | S33: =COUNTIFS('FY 26_qualification scenario'!$BI:$BI,DB!S$4,'FY 26_qualification scenario'!$I:$I,DB!$K33,'FY 26_qualification scenario'!$F:$F,DB!$L33,'FY 26_qualification scenario'!$M:$M,DB!$M33) -> 0
K34: MAHENDRA STEELS | L34: DELHI | M34: North | N34: =COUNTIFS('FY 26_qualification scenario'!$I:$I,DB!$K34,'FY 26_qualification scenario'!$F:$F,DB!$L34,'FY 26_qualification scenario'!$M:$M,DB!$M34) -> 79 | O34: =COUNTIFS('FY 26_qualification scenario'!$BI:$BI,DB!O$4,'FY 26_qualification scenario'!$I:$I,DB!$K34,'FY 26_qualification scenario'!$F:$F,DB!$L34,'FY 26_qualification scenario'!$M:$M,DB!$M34) -> 3 | P34: =COUNTIFS('FY 26_qualification scenario'!$BI:$BI,DB!P$4,'FY 26_qualification scenario'!$I:$I,DB!$K34,'FY 26_qualification scenario'!$F:$F,DB!$L34,'FY 26_qualification scenario'!$M:$M,DB!$M34) -> 2 | Q34: =COUNTIFS('FY 26_qualification scenario'!$BI:$BI,DB!Q$4,'FY 26_qualification scenario'!$I:$I,DB!$K34,'FY 26_qualification scenario'!$F:$F,DB!$L34,'FY 26_qualification scenario'!$M:$M,DB!$M34) -> 2 | R34: =COUNTIFS('FY 26_qualification scenario'!$BI:$BI,DB!R$4,'FY 26_qualification scenario'!$I:$I,DB!$K34,'FY 26_qualification scenario'!$F:$F,DB!$L34,'FY 26_qualification scenario'!$M:$M,DB!$M34) -> 1 | S34: =COUNTIFS('FY 26_qualification scenario'!$BI:$BI,DB!S$4,'FY 26_qualification scenario'!$I:$I,DB!$K34,'FY 26_qualification scenario'!$F:$F,DB!$L34,'FY 26_qualification scenario'!$M:$M,DB!$M34) -> 1
K35: Maheshwari Traders | L35: WEST BENGAL | M35: East | N35: =COUNTIFS('FY 26_qualification scenario'!$I:$I,DB!$K35,'FY 26_qualification scenario'!$F:$F,DB!$L35,'FY 26_qualification scenario'!$M:$M,DB!$M35) -> 18 | O35: =COUNTIFS('FY 26_qualification scenario'!$BI:$BI,DB!O$4,'FY 26_qualification scenario'!$I:$I,DB!$K35,'FY 26_qualification scenario'!$F:$F,DB!$L35,'FY 26_qualification scenario'!$M:$M,DB!$M35) -> 0 | P35: =COUNTIFS('FY 26_qualification scenario'!$BI:$BI,DB!P$4,'FY 26_qualification scenario'!$I:$I,DB!$K35,'FY 26_qualification scenario'!$F:$F,DB!$L35,'FY 26_qualification scenario'!$M:$M,DB!$M35) -> 0 | Q35: =COUNTIFS('FY 26_qualification scenario'!$BI:$BI,DB!Q$4,'FY 26_qualification scenario'!$I:$I,DB!$K35,'FY 26_qualification scenario'!$F:$F,DB!$L35,'FY 26_qualification scenario'!$M:$M,DB!$M35) -> 0 | R35: =COUNTIFS('FY 26_qualification scenario'!$BI:$BI,DB!R$4,'FY 26_qualification scenario'!$I:$I,DB!$K35,'FY 26_qualification scenario'!$F:$F,DB!$L35,'FY 26_qualification scenario'!$M:$M,DB!$M35) -> 0 | S35: =COUNTIFS('FY 26_qualification scenario'!$BI:$BI,DB!S$4,'FY 26_qualification scenario'!$I:$I,DB!$K35,'FY 26_qualification scenario'!$F:$F,DB!$L35,'FY 26_qualification scenario'!$M:$M,DB!$M35) -> 0
K36: MEWARAM MADHUSUDAN PRASAD & SONS | L36: BIHAR | M36: East | N36: =COUNTIFS('FY 26_qualification scenario'!$I:$I,DB!$K36,'FY 26_qualification scenario'!$F:$F,DB!$L36,'FY 26_qualification scenario'!$M:$M,DB!$M36) -> 14 | O36: =COUNTIFS('FY 26_qualification scenario'!$BI:$BI,DB!O$4,'FY 26_qualification scenario'!$I:$I,DB!$K36,'FY 26_qualification scenario'!$F:$F,DB!$L36,'FY 26_qualification scenario'!$M:$M,DB!$M36) -> 0 | P36: =COUNTIFS('FY 26_qualification scenario'!$BI:$BI,DB!P$4,'FY 26_qualification scenario'!$I:$I,DB!$K36,'FY 26_qualification scenario'!$F:$F,DB!$L36,'FY 26_qualification scenario'!$M:$M,DB!$M36) -> 0 | Q36: =COUNTIFS('FY 26_qualification scenario'!$BI:$BI,DB!Q$4,'FY 26_qualification scenario'!$I:$I,DB!$K36,'FY 26_qualification scenario'!$F:$F,DB!$L36,'FY 26_qualification scenario'!$M:$M,DB!$M36) -> 0 | R36: =COUNTIFS('FY 26_qualification scenario'!$BI:$BI,DB!R$4,'FY 26_qualification scenario'!$I:$I,DB!$K36,'FY 26_qualification scenario'!$F:$F,DB!$L36,'FY 26_qualification scenario'!$M:$M,DB!$M36) -> 0 | S36: =COUNTIFS('FY 26_qualification scenario'!$BI:$BI,DB!S$4,'FY 26_qualification scenario'!$I:$I,DB!$K36,'FY 26_qualification scenario'!$F:$F,DB!$L36,'FY 26_qualification scenario'!$M:$M,DB!$M36) -> 0
... K69: Urbanspan Infrastructure Pvt Ltd | L69: MADHYA PRADESH | M69: Central | N69: =COUNTIFS('FY 26_qualification scenario'!$I:$I,DB!$K69,'FY 26_qualification scenario'!$F:$F,DB!$L69,'FY 26_qualification scenario'!$M:$M,DB!$M69) -> 2 | O69: =COUNTIFS('FY 26_qualification scenario'!$BI:$BI,DB!O$4,'FY 26_qualification scenario'!$I:$I,DB!$K69,'FY 26_qualification scenario'!$F:$F,DB!$L69,'FY 26_qualification scenario'!$M:$M,DB!$M69) -> 0 | P69: =COUNTIFS('FY 26_qualification scenario'!$BI:$BI,DB!P$4,'FY 26_qualification scenario'!$I:$I,DB!$K69,'FY 26_qualification scenario'!$F:$F,DB!$L69,'FY 26_qualification scenario'!$M:$M,DB!$M69) -> 0 | Q69: =COUNTIFS('FY 26_qualification scenario'!$BI:$BI,DB!Q$4,'FY 26_qualification scenario'!$I:$I,DB!$K69,'FY 26_qualification scenario'!$F:$F,DB!$L69,'FY 26_qualification scenario'!$M:$M,DB!$M69) -> 0 | R69: =COUNTIFS('FY 26_qualification scenario'!$BI:$BI,DB!R$4,'FY 26_qualification scenario'!$I:$I,DB!$K69,'FY 26_qualification scenario'!$F:$F,DB!$L69,'FY 26_qualification scenario'!$M:$M,DB!$M69) -> 0 | S69: =COUNTIFS('FY 26_qualification scenario'!$BI:$BI,DB!S$4,'FY 26_qualification scenario'!$I:$I,DB!$K69,'FY 26_qualification scenario'!$F:$F,DB!$L69,'FY 26_qualification scenario'!$M:$M,DB!$M69) -> 0
K70: Total | N70: =SUM(N5:N69) -> 1745 | O70: =SUM(O5:O69) -> 50 | P70: =SUM(P5:P69) -> 59 | Q70: =SUM(Q5:Q69) -> 25 | R70: =SUM(R5:R69) -> 41 | S70: =SUM(S5:S69) -> 9

Sheet FY 26_qualification Expected
A1: {='[1]Consol. dealer sales_FY 25 + 26'!$A$2:$AV$1800} -> Sr No. | B1: Year | C1: Retailer Code | D1: Account Sf ID | E1: Name of the Dealer | F1: State | G1: District | H1: Taluka | I1: Distributor Name | J1: Account Owner As per SF | K1: TM | L1: Distributor Code | M1: Zone | N1: Pin code | O1: GST No. | P1: Mobile No. | Q1: Onboarded Dealer Months | R1: Year of Onboarding (FY) | S1: Sales FY24 | T1: Counter Potential / month | U1: Share of Business (%) | V1: Dealer Segmentation | W1: 45292 | X1: 45323 | Y1: 45352 | Z1: 45383 | AA1: 45413 | AB1: 45444 | AC1: 45474 | AD1: 45505 | AE1: 45536 | AF1: 45566 | AG1: 45597 | AH1: 45627 | AI1: 45658 | AJ1: 45689 | AK1: 45717 | AL1: 45748 | AM1: 45778 | AN1: 45809 | AO1: 45839 | AP1: 45870 | AQ1: 45901 | AR1: 45931 | AS1: 45962 | AT1: 45992 | AU1: 46023 | AV1: 46054 | AW1: Actual Apr'25 to Jan'26 | AX1: Recommend Vol. Nov to Mar'26 | AY1: FY 26 total | AZ1: FY 25 vol. | BA1: Sales recommend Vol. FY 26 | BB1: Balance Vol FY 26 | BC1: RR/Month | BD1: Y-o-Y Growth | BE1: Vol. gap (FY 25 - Oct 25 TD) | BF1: Distributor self-counter (Yes/No) | BG1: Avg. monthly vol. | BH1: Applicable for scheme (Yes/No) | BI1: Sales recommended vol. FY 26 | BJ1: Category | BK1: H2 BE | BL1: H1 | BM1: % H2 sales | BN1: % H1 sales | BO1: Sales TD | BP1: Current scheme slab | BQ1: Remarks | BR1: H1 | BS1: H2 | BT1: Total | BU1: FY 25 Qualifier | BV1: Category | BX1: Status | BY1: Changes | BZ1: Recommend Vol. | CB1: Up to Oct-25 | CC1: Nov to Mar | CG1: Bucketing wise | CH1: Category | CI1: Category for Non Qualifier Dealer | CK1: FY 25 Qualifier Domestic | CV1: 45292 | CW1: 45323 | CX1: 45352 | CY1: 45383 | CZ1: 45413 | DA1: 45444 | DB1: 45474 | DC1: 45505 | DD1: 45536 | DE1: 45566 | DF1: 45597 | DG1: 45627 | DH1: 45658 | DI1: 45689 | DJ1: 45717 | DK1: 45748 | DL1: 45778 | DM1: 45809 | DN1: 45839 | DO1: 45870 | DP1: 45901 | DQ1: 45931 | DR1: 45962 | DS1: 45992
A2: 1 | B2: 2023 | C2: PBTMTR211 | D2: 0015g00001UBHkRAAX | E2: M/S SHRI NIRMAL KUMAR JAIN & CO. | F2: UTTAR PRADESH | G2: KANPUR NAGAR | H2: Fazalganj | I2: SHREE LAKSHMAN ROLLING MILL (INDIA) LLP | J2: Ashutosh Shukla | K2: - | L2: C12815 | M2: North | N2: 208012 | O2: 09AAOPJ4618H1ZG | P2: 8808060004 | Q2: Nov'23 | R2: 2024 | S2: 296 | T2: 1500 | U2: 0.19833333 | V2: Super Star | W2: 95 | X2: 96 | Y2: 75 | Z2: 4 | AA2: 263.925 | AB2: 133 | AC2: 0 | AD2: 394 | AE2: 52 | AF2: 189 | AG2: 90 | AH2: 168 | AI2: 107.91 | AJ2: 568.38 | AK2: 596 | AL2: 520 | AM2: 216 | AN2: 137 | AO2: 98.81 | AP2: 182.48 | AQ2: 344.25 | AR2: 110.39 | AS2: 184 | AT2: 270 | AU2: 200 | AV2: 422.5 | AW2: =SUM(AL2:AU2) -> 2262.93 | AX2: 3217.86 | AY2: =AW2+AX2 -> 5480.79 | AZ2: =SUM(Z2:AK2) -> 2566.215 | BA2: 3400 | BB2: =BA2-AW2 -> 1137.07 | BC2: =IFERROR(BB2/4,0) -> 284.2675 | BD2: =AY2-AZ2 -> 2914.575 | BE2: =AZ2-AW2 -> 303.285 | BF2: Yes | BG2: =AVERAGE(AL2:AS2) -> 224.11625 | BH2: No | BI2: =IF(BF2="Yes","", IF(BA2>1250,"E", IF(BA2>750,"D", IF(BA2>=500,"C", IF(BA2>=300,"B", IF(BA2>=200,"A", IF(BA2<200,"<200",""))))))) | BJ2: =IF(BF2="Yes","",IF(AY2>1250,"E",IF(AY2>750,"D", IF(AY2>=500,"C", IF(AY2>=300,"B", IF(AY2>=200,"A", "")))))) | BK2: =SUM(AR2:AX2) -> 6667.68 | BL2: =SUM(AL2:AQ2) -> 1498.54 | BM2: =IFERROR(BK2/$AY2,"") -> 1.2165545 | BN2: =IFERROR(BL2/$AY2,"") -> 0.27341679 | BO2: =SUM(AL2:AS2) -> 1792.93 | BP2: =IF(BF2="Yes","",IF(BO2>1250,"E",IF(BO2>750,"D", IF(BO2>=500,"C", IF(BO2>=300,"B", IF(BO2>=200,"A", "")))))) | BR2: =SUM(Z2:AE2) -> 846.925 | BS2: =SUM(AF2:AK2) -> 1719.29 | BT2: =SUM(BR2:BS2) -> 2566.215 | BU2: =IFERROR(_xlfn.XLOOKUP(D2,Sheet1!B:B,Sheet1!L:L),"") | BV2: =_xlfn.XLOOKUP(BU2,Sheet1!S:S,Sheet1!T:T) -> #N/A | BW2: =_xlfn.XLOOKUP(D2,Sheet1!B:B,Sheet1!M:M) -> #N/A | BZ2: =AY2-AW2 -> 3217.86 | CB2: =AW2/AY2 -> 0.41288391 | CC2: =AX2/AY2 -> 0.58711609 | CE2: =AW2/CB2*CC2 -> 3217.86 | CG2: =IF(BO2<80,"Below 80", IF(BO2<=120,"80-120", IF(BO2<=200,"> 120-200", IF(BO2<=300,">200-300", IF(BO2<=500,">300-500", ">500"))))) -> >500 | CH2: =IFERROR(_xlfn.XLOOKUP(CG2,Scenario!M:M,Scenario!N:N),"") -> E | CI2: =IF(BI2="", IF(BA2>=1, "Yes", "No")) -> Yes | CJ2: 3033.86 | CT2: # | CU2: Rajasthan | CV2: =COUNTIFS($F:$F,$CU2,W:W,">0") -> 15 | CW2: =COUNTIFS($F:$F,$CU2,X:X,">0") -> 14 | CX2: =COUNTIFS($F:$F,$CU2,Y:Y,">0") -> 13 | CY2: =COUNTIFS($F:$F,$CU2,Z:Z,">0") -> 20 | CZ2: =COUNTIFS($F:$F,$CU2,AA:AA,">0") -> 28 | DA2: =COUNTIFS($F:$F,$CU2,AB:AB,">0") -> 11 | DB2: =COUNTIFS($F:$F,$CU2,AC:AC,">0") -> 13 | DC2: =COUNTIFS($F:$F,$CU2,AD:AD,">0") -> 14 | DD2: =COUNTIFS($F:$F,$CU2,AE:AE,">0") -> 14 | DE2: =COUNTIFS($F:$F,$CU2,AF:AF,">0") -> 34 | DF2: =COUNTIFS($F:$F,$CU2,AG:AG,">0") -> 19 | DG2: =COUNTIFS($F:$F,$CU2,AH:AH,">0") -> 42 | DH2: =COUNTIFS($F:$F,$CU2,AI:AI,">0") -> 34 | DI2: =COUNTIFS($F:$F,$CU2,AJ:AJ,">0") -> 36 | DJ2: =COUNTIFS($F:$F,$CU2,AK:AK,">0") -> 38 | DK2: =COUNTIFS($F:$F,$CU2,AL:AL,">0") -> 33 | DL2: =COUNTIFS($F:$F,$CU2,AM:AM,">0") -> 30 | DM2: =COUNTIFS($F:$F,$CU2,AN:AN,">0") -> 25 | DN2: =COUNTIFS($F:$F,$CU2,AO:AO,">0") -> 34 | DO2: =COUNTIFS($F:$F,$CU2,AP:AP,">0") -> 23 | DP2: =COUNTIFS($F:$F,$CU2,AQ:AQ,">0") -> 27 | DQ2: =COUNTIFS($F:$F,$CU2,AR:AR,">0") -> 26 | DY2: Current #
A3: 2 | B3: 2023 | C3: PBTMTR18 | D3: 0015g00001V9fpAAAR | E3: ALLAHABAD IRON AND STEEL COMPANY | F3: UTTAR PRADESH | G3: PRAYAGRAJ | H3: Prayagraj | I3: GLOBAL IRONTRADING PVT. LTD. | J3: Divyansh Dhawal | K3: Varun Arora | L3: C12819 | M3: North | N3: 211008 | O3: 09BDAPS4881H1Z5 | P3: 9956563784 | Q3: Nov'23 | R3: 2024 | S3: 150 | T3: 200 | U3: 0.0416 | V3: Challenger | W3: 30 | X3: 30 | Y3: 30 | Z3: 30 | AA3: 35.04 | AB3: 0 | AC3: 51 | AD3: 0 | AE3: 0 | AF3: 30 | AG3: 0 | AH3: 35 | AI3: 0 | AJ3: 0 | AK3: 0 | AL3: 0 | AM3: 20 | AN3: 15 | AO3: 25.03 | AP3: 0 | AQ3: 24.95 | AR3: 0 | AS3: 25.14 | AT3: 24.96 | AU3: 0 | AV3: 0 | AW3: =SUM(AL3:AU3) -> 135.08 | AX3: 216.02 | AY3: 301 | AZ3: =SUM(Z3:AK3) -> 181.04 | BA3: =AW3+120 -> 255.08 | BB3: =BA3-AW3 -> 120 | BC3: =IFERROR(BB3/4,0) -> 30 | BD3: =AY3-AZ3 -> 119.96 | BE3: =AZ3-AW3 -> 45.96 | BF3: No | BG3: =AVERAGE(AL3:AS3) -> 13.765 | BH3: Yes | BI3: =IF(BF3="Yes","",IF(BA3>1250,"E",IF(BA3>750,"D", IF(BA3>=500,"C", IF(BA3>=300,"B", IF(BA3>=200,"A", "")))))) -> A | BJ3: =IF(BF3="Yes","",IF(AY3>1250,"E",IF(AY3>750,"D", IF(AY3>=500,"C", IF(AY3>=300,"B", IF(AY3>=200,"A", "")))))) -> B | BK3: =SUM(AR3:AX3) -> 401.2 | BL3: =SUM(AL3:AQ3) -> 84.98 | BM3: =IFERROR(BK3/$AY3,"") -> 1.3328904 | BN3: =IFERROR(BL3/$AY3,"") -> 0.28232558 | BO3: =SUM(AL3:AS3) -> 110.12 | BP3: =IF(BF3="Yes","",IF(BO3>1250,"E",IF(BO3>750,"D", IF(BO3>=500,"C", IF(BO3>=300,"B", IF(BO3>=200,"A", "")))))) | BR3: =SUM(Z3:AE3) -> 116.04 | BS3: =SUM(AF3:AK3) -> 65 | BT3: =SUM(BR3:BS3) -> 181.04 | BU3: =IFERROR(_xlfn.XLOOKUP(D3,Sheet1!B:B,Sheet1!L:L),"") | BV3: =_xlfn.XLOOKUP(BU3,Sheet1!S:S,Sheet1!T:T) -> #N/A | BW3: =_xlfn.XLOOKUP(D3,Sheet1!B:B,Sheet1!M:M) -> #N/A | BX3: New | BY3: 301 | BZ3: =AY3-AW3 -> 165.92 | CB3: =AW3/AY3 -> 0.44877076 | CC3: =AX3/AY3 -> 0.71767442 | CE3: =AW3/CB3*CC3 -> 216.02 | CG3: =IF(BO3<80,"Below 80", IF(BO3<=120,"80-120", IF(BO3<=200,"> 120-200", IF(BO3<=300,">200-300", IF(BO3<=500,">300-500", ">500"))))) -> 80-120 | CH3: =IFERROR(_xlfn.XLOOKUP(CG3,Scenario!M:M,Scenario!N:N),"") -> A | CI3: =IF(BI3="", IF(BA3>=1, "Yes", "No")) -> FALSE | CJ3: 190.88 | CT3: Volume | CU3: Rajasthan | CV3: =SUMIFS(W:W,$F:$F,$CU3) -> 311 | CW3: =SUMIFS(X:X,$F:$F,$CU3) -> 308 | CX3: =SUMIFS(Y:Y,$F:$F,$CU3) -> 361 | CY3: =SUMIFS(Z:Z,$F:$F,$CU3) -> 423 | CZ3: =SUMIFS(AA:AA,$F:$F,$CU3) -> 782.34 | DA3: =SUMIFS(AB:AB,$F:$F,$CU3) -> 381 | DB3: =SUMIFS(AC:AC,$F:$F,$CU3) -> 422.05 | DC3: =SUMIFS(AD:AD,$F:$F,$CU3) -> 437.54 | DD3: =SUMIFS(AE:AE,$F:$F,$CU3) -> 805.29 | DE3: =SUMIFS(AF:AF,$F:$F,$CU3) -> 1261.12 | DF3: =SUMIFS(AG:AG,$F:$F,$CU3) -> 767 | DG3: =SUMIFS(AH:AH,$F:$F,$CU3) -> 1456.99 | DH3: =SUMIFS(AI:AI,$F:$F,$CU3) -> 1279.3 | DI3: =SUMIFS(AJ:AJ,$F:$F,$CU3) -> 1553.05 | DJ3: =SUMIFS(AK:AK,$F:$F,$CU3) -> 1609.49 | DK3: =SUMIFS(AL:AL,$F:$F,$CU3) -> 1728.83 | DL3: =SUMIFS(AM:AM,$F:$F,$CU3) -> 1349.04 | DM3: =SUMIFS(AN:AN,$F:$F,$CU3) -> 1134.6 | DN3: =SUMIFS(AO:AO,$F:$F,$CU3) -> 1279.92 | DO3: =SUMIFS(AP:AP,$F:$F,$CU3) -> 1064.37 | DP3: =SUMIFS(AQ:AQ,$F:$F,$CU3) -> 885.12 | DQ3: =SUMIFS(AR:AR,$F:$F,$CU3) -> 624.22 | DY3: # Qualified dealers | DZ3: Qualified volume | EA3: Avg. lifting/dealer/slab | EB3: Amount
A4: 3 | B4: 2023 | C4: PBTMTR01 | D4: 0015g00001W4TWFAA3 | E4: JAI DURGA IRON & STEEL COMPANY | F4: UTTAR PRADESH | G4: MATHURA | H4: Mathura | I4: DINESH STEEL PRIVATE LIMITED | J4: Pankaj Garg | K4: - | L4: C12820 | M4: North | N4: 281004 | O4: 09AAAFJ8956E1Z4 | P4: 9412280141 | Q4: Nov'23 | R4: 2024 | S4: 206 | T4: 350 | U4: 0.23718095 | V4: Super Star | W4: 34 | X4: 77 | Y4: 85 | Z4: 126 | AA4: 62 | AB4: 36 | AC4: 50 | AD4: 0 | AE4: 60 | AF4: 25 | AG4: 58 | AH4: 75 | AI4: 58 | AJ4: 86 | AK4: 135 | AL4: 20 | AM4: 76 | AN4: 55 | AO4: 56.95 | AP4: 42.13 | AQ4: 39.79 | AR4: 31.99 | AS4: 37.96 | AT4: 65.03 | AU4: 100 | AV4: 84.01 | AW4: =SUM(AL4:AU4) -> 524.85 | AX4: 929.14 | AY4: =BW4 -> 1251 | AZ4: =SUM(Z4:AK4) -> 771 | BA4: 750 | BB4: =BA4-AW4 -> 225.15 | BC4: =IFERROR(BB4/4,0) -> 56.2875 | BD4: =AY4-AZ4 -> 480 | BE4: =AZ4-AW4 -> 246.15 | BF4: No | BG4: =AVERAGE(AL4:AS4) -> 44.9775 | BH4: Yes | BI4: =IF(BF4="Yes","",IF(BA4>1250,"E",IF(BA4>750,"D", IF(BA4>=500,"C", IF(BA4>=300,"B", IF(BA4>=200,"A", "")))))) -> C | BJ4: =IF(BF4="Yes","",IF(AY4>1250,"E",IF(AY4>750,"D", IF(AY4>=500,"C", IF(AY4>=300,"B", IF(AY4>=200,"A", "")))))) -> E | BK4: =SUM(AR4:AX4) -> 1772.98 | BL4: =SUM(AL4:AQ4) -> 289.87 | BM4: =IFERROR(BK4/$AY4,"") -> 1.4172502 | BN4: =IFERROR(BL4/$AY4,"") -> 0.23171063 | BO4: =SUM(AL4:AS4) -> 359.82 | BP4: =IF(BF4="Yes","",IF(BO4>1250,"E",IF(BO4>750,"D", IF(BO4>=500,"C", IF(BO4>=300,"B", IF(BO4>=200,"A", "")))))) -> B | BR4: =SUM(Z4:AE4) -> 334 | BS4: =SUM(AF4:AK4) -> 437 | BT4: =SUM(BR4:BS4) -> 771 | BU4: =IFERROR(_xlfn.XLOOKUP(D4,Sheet1!B:B,Sheet1!L:L),"") -> Luxury International Trip (2 pax Dubai) 3N-4D | BV4: =_xlfn.XLOOKUP(BU4,Sheet1!S:S,Sheet1!T:T) -> E | BW4: =_xlfn.XLOOKUP(D4,Sheet1!B:B,Sheet1!M:M) -> 1251 | BX4: Qualified in Tour Scheme FY25 | BY4: 1251 | BZ4: =AY4-AW4 -> 726.15 | CB4: =AW4/AY4 -> 0.41954436 | CC4: =AX4/AY4 -> 0.74271783 | CD4: =AW4*1 -> 524.85 | CE4: =AW4/CB4*CC4 -> 929.14 | CF4: =CD4+AW4 -> 1049.7 | CG4: =IF(BO4<80,"Below 80", IF(BO4<=120,"80-120", IF(BO4<=200,"> 120-200", IF(BO4<=300,">200-300", IF(BO4<=500,">300-500", ">500"))))) -> >300-500 | CH4: =IFERROR(_xlfn.XLOOKUP(CG4,Scenario!M:M,Scenario!N:N),"") -> D | CI4: =IF(BI4="", IF(BA4>=1, "Yes", "No")) -> FALSE | CJ4: 891.18 | CU4: Dealer throughput | CV4: =CV3/CV2 -> 20.733333 | CW4: =CW3/CW2 -> 22 | CX4: =CX3/CX2 -> 27.769231 | CY4: =CY3/CY2 -> 21.15 | CZ4: =CZ3/CZ2 -> 27.940714 | DA4: =DA3/DA2 -> 34.636364 | DB4: =DB3/DB2 -> 32.465385 | DC4: =DC3/DC2 -> 31.252857 | ... DQ4: =DQ3/DQ2 -> 24.008462 | DY4: 30 | DZ4: 7317.485 | EA4: 243.91617 | EB4: 1650000
A5: 4 | B5: 2023 | C5: PBTMTR02 | D5: 0015g00001ZV4gAAAT | E5: CHAUDHARY DAU DAYAL SURESH CHANDRA | F5: Uttar Pradesh | G5: Mathura | H5: Mathura | I5: DINESH STEEL PRIVATE LIMITED | J5: Pankaj Garg | K5: - | L5: C12820 | M5: North | N5: 281002 | O5: 09AHGPG3615C1ZS | P5: 9837094361 | Q5: Nov'23 | R5: 2024 | S5: 139 | T5: 250 | U5: 0.02 | V5: Alien | W5: 10 | X5: 0 | Y5: 78 | Z5: 10 | AA5: 10 | AB5: 2 | AC5: 0 | AD5: 0 | AE5: 5 | AF5: 5 | AG5: 5 | AH5: 5 | AI5: 8 | AJ5: 0 | AK5: 0 | AL5: 0 | AM5: 5 | AN5: 0 | AO5: 0 | AP5: 4 | AQ5: 2 | AR5: 5 | AS5: 5 | AT5: 10 | AU5: 5 | AV5: 0 | AW5: =SUM(AL5:AU5) -> 36 | AX5: 32 | AY5: =AW5+AX5 -> 68 | AZ5: =SUM(Z5:AK5) -> 50 | BA5: 50 | BB5: =BA5-AW5 -> 14 | BC5: =IFERROR(BB5/4,0) -> 3.5 | BD5: =AY5-AZ5 -> 18 | BE5: =AZ5-AW5 -> 14 | BF5: No | BG5: =AVERAGE(AL5:AS5) -> 2.625 | BH5: Yes | BI5: =IF(BF5="Yes","",IF(BA5>1250,"E",IF(BA5>750,"D", IF(BA5>=500,"C", IF(BA5>=300,"B", IF(BA5>=200,"A", "")))))) | BJ5: =IF(BF5="Yes","",IF(AY5>1250,"E",IF(AY5>750,"D", IF(AY5>=500,"C", IF(AY5>=300,"B", IF(AY5>=200,"A", "")))))) | BK5: =SUM(AR5:AX5) -> 93 | BL5: =SUM(AL5:AQ5) -> 11 | BM5: =IFERROR(BK5/$AY5,"") -> 1.3676471 | BN5: =IFERROR(BL5/$AY5,"") -> 0.16176471 | BO5: =SUM(AL5:AS5) -> 21 | BP5: =IF(BF5="Yes","",IF(BO5>1250,"E",IF(BO5>750,"D", IF(BO5>=500,"C", IF(BO5>=300,"B", IF(BO5>=200,"A", "")))))) | BR5: =SUM(Z5:AE5) -> 27 | BS5: =SUM(AF5:AK5) -> 23 | BT5: =SUM(BR5:BS5) -> 50 | BU5: =IFERROR(_xlfn.XLOOKUP(D5,Sheet1!B:B,Sheet1!L:L),"") | BV5: =_xlfn.XLOOKUP(BU5,Sheet1!S:S,Sheet1!T:T) -> #N/A | BW5: =_xlfn.XLOOKUP(D5,Sheet1!B:B,Sheet1!M:M) -> #N/A | BZ5: =AY5-AW5 -> 32 | CB5: =AW5/AY5 -> 0.52941176 | CC5: =AX5/AY5 -> 0.47058824 | CG5: =IF(BO5<80,"Below 80", IF(BO5<=120,"80-120", IF(BO5<=200,"> 120-200", IF(BO5<=300,">200-300", IF(BO5<=500,">300-500", ">500"))))) -> Below 80 | CH5: =IFERROR(_xlfn.XLOOKUP(CG5,Scenario!M:M,Scenario!N:N),"") | CI5: =IF(BI5="", IF(BA5>=1, "Yes", "No")) -> Yes | CJ5: 27 | DY5: 39 | DZ5: 14900.07 | EA5: 382.05308 | EB5: 3003000
A6: 5 | B6: 2023 | C6: PBTMTR03 | D6: 0015g00001YOMCMAA5 | E6: M/S AAR DEE DISTRIBUTORS | F6: UTTAR PRADESH | G6: AGRA | H6: Agra | I6: DINESH STEEL PRIVATE LIMITED | J6: Pankaj Garg | K6: - | L6: C12820 | M6: North | N6: 282002 | O6: 09ABHPA0980F1ZX | P6: 8171374107 | Q6: Nov'23 | R6: 2024 | S6: 337 | T6: 450 | U6: 0.10022222 | V6: Super Star | W6: 40 | X6: 116 | Y6: 111 | Z6: 134 | AA6: 55 | AB6: 158 | AC6: 82 | AD6: 60 | AE6: 100 | AF6: 204 | AG6: 77 | AH6: 87 | AI6: 113 | AJ6: 98 | AK6: 125 | AL6: 245 | AM6: 88 | AN6: 61 | AO6: 54.91 | AP6: 82.68 | AQ6: 202.14 | AR6: 39.95 | AS6: 30.05 | AT6: 44.65 | AU6: 50 | AV6: 40.65 | AW6: =SUM(AL6:AU6) -> 898.38 | AX6: 1547.36 | AY6: =AW6+AX6 -> 2445.74 | AZ6: =SUM(Z6:AK6) -> 1293 | BA6: 1250 | BB6: =BA6-AW6 -> 351.62 | BC6: =IFERROR(BB6/4,0) -> 87.905 | BD6: =AY6-AZ6 -> 1152.74 | BE6: =AZ6-AW6 -> 394.62 | BF6: Yes | BG6: =AVERAGE(AL6:AS6) -> 100.46625 | BH6: No | BI6: =IF(BF6="Yes","",IF(BA6>1250,"E",IF(BA6>750,"D", IF(BA6>=500,"C", IF(BA6>=300,"B", IF(BA6>=200,"A", "")))))) | BJ6: =IF(BF6="Yes","",IF(AY6>1250,"E",IF(AY6>750,"D", IF(AY6>=500,"C", IF(AY6>=300,"B", IF(AY6>=200,"A", "")))))) | BK6: =SUM(AR6:AX6) -> 2651.04 | BL6: =SUM(AL6:AQ6) -> 733.73 | BM6: =IFERROR(BK6/$AY6,"") -> 1.0839419 | BN6: =IFERROR(BL6/$AY6,"") -> 0.30000327 | BO6: =SUM(AL6:AS6) -> 803.73 | BP6: =IF(BF6="Yes","",IF(BO6>1250,"E",IF(BO6>750,"D", IF(BO6>=500,"C", IF(BO6>=300,"B", IF(BO6>=200,"A", "")))))) | BQ6: Distributor self-counter; Wants annual tour for pushing sales | BR6: =SUM(Z6:AE6) -> 589 | BS6: =SUM(AF6:AK6) -> 704 | BT6: =SUM(BR6:BS6) -> 1293 | BU6: =IFERROR(_xlfn.XLOOKUP(D6,Sheet1!B:B,Sheet1!L:L),"") | BV6: =_xlfn.XLOOKUP(BU6,Sheet1!S:S,Sheet1!T:T) -> #N/A | BW6: =_xlfn.XLOOKUP(D6,Sheet1!B:B,Sheet1!M:M) -> #N/A | BZ6: =AY6-AW6 -> 1547.36 | CB6: =AW6/AY6 -> 0.36732441 | CC6: =AX6/AY6 -> 0.63267559 | CG6: =IF(BO6<80,"Below 80", IF(BO6<=120,"80-120", IF(BO6<=200,"> 120-200", IF(BO6<=300,">200-300", IF(BO6<=500,">300-500", ">500"))))) -> >500 | CH6: =IFERROR(_xlfn.XLOOKUP(CG6,Scenario!M:M,Scenario!N:N),"") -> E | CI6: =IF(BI6="", IF(BA6>=1, "Yes", "No")) -> Yes | CJ6: 1517.31 | DY6: 11 | DZ6: 6424.195 | EA6: 584.01773 | EB6: 1210000
A7: 6 | B7: 2023 | C7: PBTMTR234 | D7: 0015g00001UBHi0AAH | E7: RAJ RAJESHWERI IRON & TIMBAR STORE | F7: RAJASTHAN | G7: KARAULI | H7: Karauli | I7: Swastik Tradevision Pvt. Ltd. | J7: Ravi Kumar Kulmi | K7: Ravi Kumar Kulmi | L7: C12822 | M7: North | N7: 322241 | O7: 08AQNPB6135A1Z8 | P7: 9887982022 | Q7: Nov'23 | R7: 2024 | S7: 50 | T7: 270 | U7: 0 | V7: Alien | W7: 20 | X7: 0 | Y7: 0 | Z7: 0 | AA7: 0 | AB7: 0 | AC7: 0 | AD7: 0 | AE7: 0 | AF7: 0 | AG7: 0 | AH7: 0 | AI7: 0 | AJ7: 0 | AK7: 0 | AL7: 0 | AM7: 0 | AN7: 0 | AO7: 0 | AP7: 0 | AQ7: 0 | AR7: 0 | AS7: 0 | AT7: 0 | AU7: 0 | AV7: 0 | AW7: =SUM(AL7:AU7) -> 0 | AX7: 0 | AY7: =AW7+AX7 -> 0 | AZ7: =SUM(Z7:AK7) -> 0 | BB7: =BA7-AW7 -> 0 | BC7: =IFERROR(BB7/4,0) -> 0 | BD7: =AY7-AZ7 -> 0 | BE7: =AZ7-AW7 -> 0 | BF7: No | BG7: =AVERAGE(AL7:AS7) -> 0 | BH7: Yes | BI7: =IF(BF7="Yes","",IF(BA7>1250,"E",IF(BA7>750,"D", IF(BA7>=500,"C", IF(BA7>=300,"B", IF(BA7>=200,"A", "")))))) | BJ7: =IF(BF7="Yes","",IF(AY7>1250,"E",IF(AY7>750,"D", IF(AY7>=500,"C", IF(AY7>=300,"B", IF(AY7>=200,"A", "")))))) | BK7: =SUM(AR7:AX7) -> 0 | BL7: =SUM(AL7:AQ7) -> 0 | BM7: =IFERROR(BK7/$AY7,"") | BN7: =IFERROR(BL7/$AY7,"") | BO7: =SUM(AL7:AS7) -> 0 | BP7: =IF(BF7="Yes","",IF(BO7>1250,"E",IF(BO7>750,"D", IF(BO7>=500,"C", IF(BO7>=300,"B", IF(BO7>=200,"A", "")))))) | BR7: =SUM(Z7:AE7) -> 0 | BS7: =SUM(AF7:AK7) -> 0 | BT7: =SUM(BR7:BS7) -> 0 | BU7: =IFERROR(_xlfn.XLOOKUP(D7,Sheet1!B:B,Sheet1!L:L),"") | BV7: =_xlfn.XLOOKUP(BU7,Sheet1!S:S,Sheet1!T:T) -> #N/A | BW7: =_xlfn.XLOOKUP(D7,Sheet1!B:B,Sheet1!M:M) -> #N/A | BZ7: =AY7-AW7 -> 0 | CG7: =IF(BO7<80,"Below 80", IF(BO7<=120,"80-120", IF(BO7<=200,"> 120-200", IF(BO7<=300,">200-300", IF(BO7<=500,">300-500", ">500"))))) -> Below 80 | CH7: =IFERROR(_xlfn.XLOOKUP(CG7,Scenario!M:M,Scenario!N:N),"") | CI7: =IF(BI7="", IF(BA7>=1, "Yes", "No")) -> No | CJ7: 0 | CT7: # | CU7: Odisha | CV7: =COUNTIFS($F:$F,$CU7,W:W,">0") -> 3 | CW7: =COUNTIFS($F:$F,$CU7,X:X,">0") -> 11 | CX7: =COUNTIFS($F:$F,$CU7,Y:Y,">0") -> 12 | CY7: =COUNTIFS($F:$F,$CU7,Z:Z,">0") -> 16 | CZ7: =COUNTIFS($F:$F,$CU7,AA:AA,">0") -> 26 | DA7: =COUNTIFS($F:$F,$CU7,AB:AB,">0") -> 19 | DB7: =COUNTIFS($F:$F,$CU7,AC:AC,">0") -> 12 | DC7: =COUNTIFS($F:$F,$CU7,AD:AD,">0") -> 10 | DD7: =COUNTIFS($F:$F,$CU7,AE:AE,">0") -> 15 | DE7: =COUNTIFS($F:$F,$CU7,AF:AF,">0") -> 16 | DF7: =COUNTIFS($F:$F,$CU7,AG:AG,">0") -> 13 | DG7: =COUNTIFS($F:$F,$CU7,AH:AH,">0") -> 14 | DH7: =COUNTIFS($F:$F,$CU7,AI:AI,">0") -> 14 | DI7: =COUNTIFS($F:$F,$CU7,AJ:AJ,">0") -> 13 | DJ7: =COUNTIFS($F:$F,$CU7,AK:AK,">0") -> 17 | DK7: =COUNTIFS($F:$F,$CU7,AL:AL,">0") -> 19 | DL7: =COUNTIFS($F:$F,$CU7,AM:AM,">0") -> 15 | DM7: =COUNTIFS($F:$F,$CU7,AN:AN,">0") -> 9 | DN7: =COUNTIFS($F:$F,$CU7,AO:AO,">0") -> 13 | DO7: =COUNTIFS($F:$F,$CU7,AP:AP,">0") -> 21 | DP7: =COUNTIFS($F:$F,$CU7,AQ:AQ,">0") -> 19 | DQ7: =COUNTIFS($F:$F,$CU7,AR:AR,">0") -> 26 | DY7: 7 | DZ7: 6049.3 | EA7: 864.18571 | EB7: 1694000
A8: 7 | B8: 2023 | C8: PBTMTR235 | D8: 0015g00001c4Q9rAAE | E8: UMA STEEL | F8: RAJASTHAN | G8: ALWAR | H8: Rajgarh | I8: Swastik Tradevision Pvt. Ltd. | J8: Ravi Kumar Kulmi | K8: Ravi Kumar Kulmi | L8: C12822 | M8: North | N8: 301408 | O8: 08ABRPD8244K1Z6 | P8: 9664100259 | Q8: Nov'23 | R8: 2024 | S8: 55 | T8: 1400 | U8: 0 | V8: Alien | W8: 0 | X8: 0 | Y8: 0 | Z8: 0 | AA8: 20 | AB8: 0 | AC8: 0 | AD8: 0 | AE8: 0 | AF8: 0 | AG8: 0 | AH8: 0 | AI8: 0 | AJ8: 0 | AK8: 0 | AL8: 0 | AM8: 0 | AN8: 0 | AO8: 0 | AP8: 0 | AQ8: 0 | AR8: 0 | AS8: 0 | AT8: 0 | AU8: 0 | AV8: 0 | AW8: =SUM(AL8:AU8) -> 0 | AX8: 0 | AY8: =AW8+AX8 -> 0 | AZ8: =SUM(Z8:AK8) -> 20 | BB8: =BA8-AW8 -> 0 | BC8: =IFERROR(BB8/4,0) -> 0 | BD8: =AY8-AZ8 -> -20 | BE8: =AZ8-AW8 -> 20 | BF8: No | BG8: =AVERAGE(AL8:AS8) -> 0 | BH8: Yes | BI8: =IF(BF8="Yes","",IF(BA8>1250,"E",IF(BA8>750,"D", IF(BA8>=500,"C", IF(BA8>=300,"B", IF(BA8>=200,"A", "")))))) | BJ8: =IF(BF8="Yes","",IF(AY8>1250,"E",IF(AY8>750,"D", IF(AY8>=500,"C", IF(AY8>=300,"B", IF(AY8>=200,"A", "")))))) | BK8: =SUM(AR8:AX8) -> 0 | BL8: =SUM(AL8:AQ8) -> 0 | BM8: =IFERROR(BK8/$AY8,"") | BN8: =IFERROR(BL8/$AY8,"") | BO8: =SUM(AL8:AS8) -> 0 | BP8: =IF(BF8="Yes","",IF(BO8>1250,"E",IF(BO8>750,"D", IF(BO8>=500,"C", IF(BO8>=300,"B", IF(BO8>=200,"A", "")))))) | BR8: =SUM(Z8:AE8) -> 20 | BS8: =SUM(AF8:AK8) -> 0 | BT8: =SUM(BR8:BS8) -> 20 | BU8: =IFERROR(_xlfn.XLOOKUP(D8,Sheet1!B:B,Sheet1!L:L),"") | BV8: =_xlfn.XLOOKUP(BU8,Sheet1!S:S,Sheet1!T:T) -> #N/A | BW8: =_xlfn.XLOOKUP(D8,Sheet1!B:B,Sheet1!M:M) -> #N/A | BZ8: =AY8-AW8 -> 0 | CG8: =IF(BO8<80,"Below 80", IF(BO8<=120,"80-120", IF(BO8<=200,"> 120-200", IF(BO8<=300,">200-300", IF(BO8<=500,">300-500", ">500"))))) -> Below 80 | CH8: =IFERROR(_xlfn.XLOOKUP(CG8,Scenario!M:M,Scenario!N:N),"") | CI8: =IF(BI8="", IF(BA8>=1, "Yes", "No")) -> No | CJ8: 0 | CT8: Volume | CU8: Odisha | CV8: =SUMIFS(W:W,$F:$F,$CU8) -> 52 | CW8: =SUMIFS(X:X,$F:$F,$CU8) -> 131 | CX8: =SUMIFS(Y:Y,$F:$F,$CU8) -> 187 | CY8: =SUMIFS(Z:Z,$F:$F,$CU8) -> 494.15 | CZ8: =SUMIFS(AA:AA,$F:$F,$CU8) -> 507.23 | DA8: =SUMIFS(AB:AB,$F:$F,$CU8) -> 469.397 | DB8: =SUMIFS(AC:AC,$F:$F,$CU8) -> 192.03 | DC8: =SUMIFS(AD:AD,$F:$F,$CU8) -> 297.376 | DD8: =SUMIFS(AE:AE,$F:$F,$CU8) -> 507.55 | DE8: =SUMIFS(AF:AF,$F:$F,$CU8) -> 431.97 | DF8: =SUMIFS(AG:AG,$F:$F,$CU8) -> 753 | DG8: =SUMIFS(AH:AH,$F:$F,$CU8) -> 238.64 | DH8: =SUMIFS(AI:AI,$F:$F,$CU8) -> 373.5 | DI8: =SUMIFS(AJ:AJ,$F:$F,$CU8) -> 374.2 | DJ8: =SUMIFS(AK:AK,$F:$F,$CU8) -> 614.07 | DK8: =SUMIFS(AL:AL,$F:$F,$CU8) -> 508.35 | DL8: =SUMIFS(AM:AM,$F:$F,$CU8) -> 365.5 | DM8: =SUMIFS(AN:AN,$F:$F,$CU8) -> 432.8 | DN8: =SUMIFS(AO:AO,$F:$F,$CU8) -> 294.07 | DO8: =SUMIFS(AP:AP,$F:$F,$CU8) -> 649.99 | DP8: =SUMIFS(AQ:AQ,$F:$F,$CU8) -> 230.6 | DQ8: =SUMIFS(AR:AR,$F:$F,$CU8) -> 306.15 | DY8: 0 | DZ8: 0 | EB8: 0
A9: 8 | B9: 2023 | C9: PBTMTR236 | D9: 0015g00001UBHaEAAX | E9: SHRI MAHAVEER STEELS | F9: RAJASTHAN | G9: BHARATPUR | H9: Bharatpur | I9: Swastik Tradevision Pvt. Ltd. | J9: Amit Kumar Sharma | K9: Ravi Kumar Kulmi | L9: C12822 | M9: North | N9: 321001 | O9: 08ABFPJ0052R1ZG | P9: 9413012103 | Q9: Nov'23 | R9: 2024 | S9: 30 | T9: 800 | U9: 0 | V9: Alien | W9: 0 | X9: 0 | Y9: 0 | Z9: 0 | AA9: 20.14 | AB9: 0 | AC9: 0 | AD9: 0 | AE9: 0 | AF9: 0 | AG9: 0 | AH9: 0 | AI9: 0 | AJ9: 0 | AK9: 0 | AL9: 0 | AM9: 0 | AN9: 0 | AO9: 0 | AP9: 0 | AQ9: 0 | AR9: 0 | AS9: 0 | AT9: 0 | AU9: 0 | AV9: 0 | AW9: =SUM(AL9:AU9) -> 0 | AX9: 0 | AY9: =AW9+AX9 -> 0 | AZ9: =SUM(Z9:AK9) -> 20.14 | BB9: =BA9-AW9 -> 0 | BC9: =IFERROR(BB9/4,0) -> 0 | BD9: =AY9-AZ9 -> -20.14 | BE9: =AZ9-AW9 -> 20.14 | BF9: No | BG9: =AVERAGE(AL9:AS9) -> 0 | BH9: Yes | BI9: =IF(BF9="Yes","",IF(BA9>1250,"E",IF(BA9>750,"D", IF(BA9>=500,"C", IF(BA9>=300,"B", IF(BA9>=200,"A", "")))))) | BJ9: =IF(BF9="Yes","",IF(AY9>1250,"E",IF(AY9>750,"D", IF(AY9>=500,"C", IF(AY9>=300,"B", IF(AY9>=200,"A", "")))))) | BK9: =SUM(AR9:AX9) -> 0 | BL9: =SUM(AL9:AQ9) -> 0 | BM9: =IFERROR(BK9/$AY9,"") | BN9: =IFERROR(BL9/$AY9,"") | BO9: =SUM(AL9:AS9) -> 0 | BP9: =IF(BF9="Yes","",IF(BO9>1250,"E",IF(BO9>750,"D", IF(BO9>=500,"C", IF(BO9>=300,"B", IF(BO9>=200,"A", "")))))) | BR9: =SUM(Z9:AE9) -> 20.14 | BS9: =SUM(AF9:AK9) -> 0 | BT9: =SUM(BR9:BS9) -> 20.14 | BU9: =IFERROR(_xlfn.XLOOKUP(D9,Sheet1!B:B,Sheet1!L:L),"") | BV9: =_xlfn.XLOOKUP(BU9,Sheet1!S:S,Sheet1!T:T) -> #N/A | BW9: =_xlfn.XLOOKUP(D9,Sheet1!B:B,Sheet1!M:M) -> #N/A | BZ9: =AY9-AW9 -> 0 | CG9: =IF(BO9<80,"Below 80", IF(BO9<=120,"80-120", IF(BO9<=200,"> 120-200", IF(BO9<=300,">200-300", IF(BO9<=500,">300-500", ">500"))))) -> Below 80 | CH9: =IFERROR(_xlfn.XLOOKUP(CG9,Scenario!M:M,Scenario!N:N),"") | CI9: =IF(BI9="", IF(BA9>=1, "Yes", "No")) -> No | CJ9: 0 | CU9: Dealer throughput | CV9: =CV8/CV7 -> 17.333333 | CW9: =CW8/CW7 -> 11.909091 | CX9: =CX8/CX7 -> 15.583333 | CY9: =CY8/CY7 -> 30.884375 | CZ9: =CZ8/CZ7 -> 19.508846 | DA9: =DA8/DA7 -> 24.705105 | DB9: =DB8/DB7 -> 16.0025 | DC9: =DC8/DC7 -> 29.7376 | ... DQ9: =DQ8/DQ7 -> 11.775 | DY9: 87 | DZ9: 34691.05 | EA9: 398.7477 | EB9: 7557000
A10: 9 | B10: 2023 | C10: PBTMTR226 | D10: 0015g00001XIsNwAAL | E10: B R TRADERS | F10: CHHATTISGARH | G10: BILASPUR | H10: Bilaspur | I10: Shree Resources | J10: Saurav Nath | K10: Sudhir Tiwari | M10: Central | N10: 495001 | O10: 0 | P10: 9826133304 | Q10: Nov'23 | R10: 2024 | S10: 103 | T10: 400 | U10: 0 | V10: Alien | W10: 0 | X10: 48 | Y10: 30 | Z10: 9.58 | AA10: 0 | AB10: 0 | AC10: 22 | AD10: 0 | AE10: 0 | AF10: 0 | AG10: 0 | AH10: 0 | AI10: 0 | AJ10: 0 | AK10: 0 | AL10: 0 | AM10: 0 | AN10: 0 | AO10: 0 | AP10: 0 | AQ10: 0 | AR10: 0 | AS10: 0 | AT10: 0 | AU10: 0 | AV10: 0 | AW10: =SUM(AL10:AU10) -> 0 | AX10: 0 | AY10: =AW10+AX10 -> 0 | AZ10: =SUM(Z10:AK10) -> 31.58 | BB10: =BA10-AW10 -> 0 | BC10: =IFERROR(BB10/4,0) -> 0 | BD10: =AY10-AZ10 -> -31.58 | BE10: =AZ10-AW10 -> 31.58 | BF10: No | BG10: =AVERAGE(AL10:AS10) -> 0 | BH10: Yes | BI10: =IF(BF10="Yes","",IF(BA10>1250,"E",IF(BA10>750,"D", IF(BA10>=500,"C", IF(BA10>=300,"B", IF(BA10>=200,"A", "")))))) | BJ10: =IF(BF10="Yes","",IF(AY10>1250,"E",IF(AY10>750,"D", IF(AY10>=500,"C", IF(AY10>=300,"B", IF(AY10>=200,"A", "")))))) | BK10: =SUM(AR10:AX10) -> 0 | BL10: =SUM(AL10:AQ10) -> 0 | BM10: =IFERROR(BK10/$AY10,"") | BN10: =IFERROR(BL10/$AY10,"") | BO10: =SUM(AL10:AS10) -> 0 | BP10: =IF(BF10="Yes","",IF(BO10>1250,"E",IF(BO10>750,"D", IF(BO10>=500,"C", IF(BO10>=300,"B", IF(BO10>=200,"A", "")))))) | BR10: =SUM(Z10:AE10) -> 31.58 | BS10: =SUM(AF10:AK10) -> 0 | BT10: =SUM(BR10:BS10) -> 31.58 | BU10: =IFERROR(_xlfn.XLOOKUP(D10,Sheet1!B:B,Sheet1!L:L),"") | BV10: =_xlfn.XLOOKUP(BU10,Sheet1!S:S,Sheet1!T:T) -> #N/A | BW10: =_xlfn.XLOOKUP(D10,Sheet1!B:B,Sheet1!M:M) -> #N/A | BZ10: =AY10-AW10 -> 0 | CG10: =IF(BO10<80,"Below 80", IF(BO10<=120,"80-120", IF(BO10<=200,"> 120-200", IF(BO10<=300,">200-300", IF(BO10<=500,">300-500", ">500"))))) -> Below 80 | CH10: =IFERROR(_xlfn.XLOOKUP(CG10,Scenario!M:M,Scenario!N:N),"") | CI10: =IF(BI10="", IF(BA10>=1, "Yes", "No")) -> No | CJ10: 0
A11: 10 | B11: 2023 | C11: PBTMTR92 | D11: 0015g00001X3D2eAAF | E11: Kunal hardware | F11: CHHATTISGARH | G11: SUKMA | H11: Sukma | I11: MADHYA BHARAT ISPAT PRIVATE LIMITED | J11: Saurav Nath | K11: Vikash Kumar | L11: C12834 | M11: Central | N11: 494111 | O11: 0 | P11: 0 | Q11: Dec'23 | R11: 2024 | S11: 22 | T11: 50 | U11: 0 | V11: Minor | W11: 0 | X11: 0 | Y11: 0 | Z11: 0 | AA11: 0 | AB11: 0 | AC11: 0 | AD11: 0 | AE11: 8.205 | AF11: 0 | AG11: 0 | AH11: 0 | AI11: 0 | AJ11: 0 | AK11: 0 | AL11: 0 | AM11: 0 | AN11: 0 | AO11: 0 | AP11: 0 | AQ11: 0 | AR11: 0 | AS11: 0 | AT11: 0 | AU11: 0 | AV11: 0 | AW11: =SUM(AL11:AU11) -> 0 | AX11: 0 | AY11: =AW11+AX11 -> 0 | AZ11: =SUM(Z11:AK11) -> 8.205 | BB11: =BA11-AW11 -> 0 | BC11: =IFERROR(BB11/4,0) -> 0 | BD11: =AY11-AZ11 -> -8.205 | BE11: =AZ11-AW11 -> 8.205 | BF11: No | BG11: =AVERAGE(AL11:AS11) -> 0 | BH11: Yes | BI11: =IF(BF11="Yes","",IF(BA11>1250,"E",IF(BA11>750,"D", IF(BA11>=500,"C", IF(BA11>=300,"B", IF(BA11>=200,"A", "")))))) | BJ11: =IF(BF11="Yes","",IF(AY11>1250,"E",IF(AY11>750,"D", IF(AY11>=500,"C", IF(AY11>=300,"B", IF(AY11>=200,"A", "")))))) | BK11: =SUM(AR11:AX11) -> 0 | BL11: =SUM(AL11:AQ11) -> 0 | BM11: =IFERROR(BK11/$AY11,"") | BN11: =IFERROR(BL11/$AY11,"") | BO11: =SUM(AL11:AS11) -> 0 | BP11: =IF(BF11="Yes","",IF(BO11>1250,"E",IF(BO11>750,"D", IF(BO11>=500,"C", IF(BO11>=300,"B", IF(BO11>=200,"A", "")))))) | BR11: =SUM(Z11:AE11) -> 8.205 | BS11: =SUM(AF11:AK11) -> 0 | BT11: =SUM(BR11:BS11) -> 8.205 | BU11: =IFERROR(_xlfn.XLOOKUP(D11,Sheet1!B:B,Sheet1!L:L),"") | BV11: =_xlfn.XLOOKUP(BU11,Sheet1!S:S,Sheet1!T:T) -> #N/A | BW11: =_xlfn.XLOOKUP(D11,Sheet1!B:B,Sheet1!M:M) -> #N/A | BZ11: =AY11-AW11 -> 0 | CG11: =IF(BO11<80,"Below 80", IF(BO11<=120,"80-120", IF(BO11<=200,"> 120-200", IF(BO11<=300,">200-300", IF(BO11<=500,">300-500", ">500"))))) -> Below 80 | CH11: =IFERROR(_xlfn.XLOOKUP(CG11,Scenario!M:M,Scenario!N:N),"") | CI11: =IF(BI11="", IF(BA11>=1, "Yes", "No")) -> No | CJ11: 0
A12: 11 | B12: 2023 | C12: PBTMTR175 | D12: 0015g00001YPk0yAAD | E12: M/s, OMMSHA TILES | F12: ODISHA | G12: DEOGARH | H12: Deogarh | I12: SACHDEVA ISPAT PVT LTD | J12: Papun Padhan | K12: Papun Pradhan | L12: C12823 | M12: Central | N12: 768110 | O12: 21EQYPS7066C2ZB | P12: 9937723811 | Q12: Nov'23 | R12: 2024 | S12: 11 | T12: 50 | U12: 0.01 | V12: Minor | W12: 5 | X12: 0 | Y12: 4 | Z12: 0 | AA12: 3.5 | AB12: 0 | AC12: 0 | AD12: 0 | AE12: 2 | AF12: 0 | AG12: 0 | AH12: 0 | AI12: 0 | AJ12: 1 | AK12: 0 | AL12: 1 | AM12: 0 | AN12: 0 | AO12: 0 | AP12: 0 | AQ12: 4.5 | AR12: 0 | AS12: 5.5 | AT12: 0.5 | AU12: 1 | AV12: 0 | AW12: =SUM(AL12:AU12) -> 12.5 | AX12: 11 | AY12: =AW12+AX12 -> 23.5 | AZ12: =SUM(Z12:AK12) -> 6.5 | BA12: 50 | BB12: =BA12-AW12 -> 37.5 | BC12: =IFERROR(BB12/4,0) -> 9.375 | BD12: =AY12-AZ12 -> 17 | BE12: =AZ12-AW12 -> -6 | BF12: No | BG12: =AVERAGE(AL12:AS12) -> 1.375 | BH12: Yes | BI12: =IF(BF12="Yes","",IF(BA12>1250,"E",IF(BA12>750,"D", IF(BA12>=500,"C", IF(BA12>=300,"B", IF(BA12>=200,"A", "")))))) | BJ12: =IF(BF12="Yes","",IF(AY12>1250,"E",IF(AY12>750,"D", IF(AY12>=500,"C", IF(AY12>=300,"B", IF(AY12>=200,"A", "")))))) | BK12: =SUM(AR12:AX12) -> 30.5 | BL12: =SUM(AL12:AQ12) -> 5.5 | BM12: =IFERROR(BK12/$AY12,"") -> 1.2978723 | BN12: =IFERROR(BL12/$AY12,"") -> 0.23404255 | BO12: =SUM(AL12:AS12) -> 11 | BP12: =IF(BF12="Yes","",IF(BO12>1250,"E",IF(BO12>750,"D", IF(BO12>=500,"C", IF(BO12>=300,"B", IF(BO12>=200,"A", "")))))) | BR12: =SUM(Z12:AE12) -> 5.5 | BS12: =SUM(AF12:AK12) -> 1 | BT12: =SUM(BR12:BS12) -> 6.5 | BU12: =IFERROR(_xlfn.XLOOKUP(D12,Sheet1!B:B,Sheet1!L:L),"") | BV12: =_xlfn.XLOOKUP(BU12,Sheet1!S:S,Sheet1!T:T) -> #N/A | BW12: =_xlfn.XLOOKUP(D12,Sheet1!B:B,Sheet1!M:M) -> #N/A | BZ12: =AY12-AW12 -> 11 | CB12: =AW12/AY12 -> 0.53191489 | CC12: =AX12/AY12 -> 0.46808511 | CG12: =IF(BO12<80,"Below 80", IF(BO12<=120,"80-120", IF(BO12<=200,"> 120-200", IF(BO12<=300,">200-300", IF(BO12<=500,">300-500", ">500"))))) -> Below 80 | CH12: =IFERROR(_xlfn.XLOOKUP(CG12,Scenario!M:M,Scenario!N:N),"") | CI12: =IF(BI12="", IF(BA12>=1, "Yes", "No")) -> Yes | CJ12: 5.5 | DY12: Sec. sales | DZ12: 34691.05
A13: 12 | B13: 2023 | C13: PBTMTR176 | D13: 0015g00001e9DuKAAU | E13: M/S. BISWAKARMA HARDWARE | F13: ODISHA | G13: KENDUJHAR | H13: Kendujhar | I13: SACHDEVA ISPAT PVT LTD | J13: Sourav Kumar Rana | K13: Papun Pradhan | L13: C12823 | M13: Central | N13: 758035 | O13: 21AXHPS5043D1ZS | P13: 9937687238 | Q13: Dec'23 | R13: 2024 | S13: 10 | T13: 60 | U13: 0 | V13: Challenger | W13: 0 | X13: 4 | Y13: 0 | Z13: 0 | AA13: 10.98 | AB13: 0 | AC13: 0 | AD13: 10 | AE13: 0 | AF13: 0 | AG13: 0 | AH13: 0 | AI13: 6 | AJ13: 0 | AK13: 0 | AL13: 7 | AM13: 0 | AN13: 0 | AO13: 0 | AP13: 0 | AQ13: 4.2 | AR13: 0 | AS13: 9 | AT13: 0 | AU13: 0 | AV13: 0 | AW13: =SUM(AL13:AU13) -> 20.2 | AX13: 22.4 | AY13: =AW13+AX13 -> 42.6 | AZ13: =SUM(Z13:AK13) -> 26.98 | BA13: =AW13 -> 20.2 | BB13: =BA13-AW13 -> 0 | BC13: =IFERROR(BB13/4,0) -> 0 | BD13: =AY13-AZ13 -> 15.62 | BE13: =AZ13-AW13 -> 6.78 | BF13: No | BG13: =AVERAGE(AL13:AS13) -> 2.525 | BH13: Yes | BI13: =IF(BF13="Yes","",IF(BA13>1250,"E",IF(BA13>750,"D", IF(BA13>=500,"C", IF(BA13>=300,"B", IF(BA13>=200,"A", "")))))) | BJ13: =IF(BF13="Yes","",IF(AY13>1250,"E",IF(AY13>750,"D", IF(AY13>=500,"C", IF(AY13>=300,"B", IF(AY13>=200,"A", "")))))) | BK13: =SUM(AR13:AX13) -> 51.6 | BL13: =SUM(AL13:AQ13) -> 11.2 | BM13: =IFERROR(BK13/$AY13,"") -> 1.2112676 | BN13: =IFERROR(BL13/$AY13,"") -> 0.2629108 | BO13: =SUM(AL13:AS13) -> 20.2 | BP13: =IF(BF13="Yes","",IF(BO13>1250,"E",IF(BO13>750,"D", IF(BO13>=500,"C", IF(BO13>=300,"B", IF(BO13>=200,"A", "")))))) | BR13: =SUM(Z13:AE13) -> 20.98 | BS13: =SUM(AF13:AK13) -> 6 | BT13: =SUM(BR13:BS13) -> 26.98 | BU13: =IFERROR(_xlfn.XLOOKUP(D13,Sheet1!B:B,Sheet1!L:L),"") | BV13: =_xlfn.XLOOKUP(BU13,Sheet1!S:S,Sheet1!T:T) -> #N/A | BW13: =_xlfn.XLOOKUP(D13,Sheet1!B:B,Sheet1!M:M) -> #N/A | BZ13: =AY13-AW13 -> 22.4 | CB13: =AW13/AY13 -> 0.4741784 | CC13: =AX13/AY13 -> 0.5258216 | CG13: =IF(BO13<80,"Below 80", IF(BO13<=120,"80-120", IF(BO13<=200,"> 120-200", IF(BO13<=300,">200-300", IF(BO13<=500,">300-500", ">500"))))) -> Below 80 | CH13: =IFERROR(_xlfn.XLOOKUP(CG13,Scenario!M:M,Scenario!N:N),"") | CI13: =IF(BI13="", IF(BA13>=1, "Yes", "No")) -> Yes | CJ13: 13.4 | DY13: % sec. sales | DZ13: 1
A14: 13 | B14: 2023 | C14: PBTMTR177 | D14: 0015g00001XKXuDAAX | E14: Chandra Steel | F14: ODISHA | G14: SUNDARGARH | H14: Sundarpahari | I14: SACHDEVA ISPAT PVT LTD | J14: Papun Padhan | K14: Papun Pradhan | L14: C12823 | M14: Central | N14: 769004 | O14: 21AADCC2469D1Z6 | P14: 9437048292 | Q14: Dec'23 | R14: 2024 | S14: 32 | T14: 50 | U14: 0 | V14: Minor | W14: 7 | X14: 3 | Y14: 9 | Z14: 6.45 | AA14: 0 | AB14: 0 | AC14: 0 | AD14: 0 | AE14: 0 | AF14: 21 | AG14: 0 | AH14: 32 | AI14: 0 | AJ14: 0 | AK14: 15.7 | AL14: 0 | AM14: 3 | AN14: 0 | AO14: 6.2 | AP14: 0 | AQ14: 0 | AR14: 0 | AS14: 0 | AT14: 0 | AU14: 0 | AV14: 0 | AW14: =SUM(AL14:AU14) -> 9.2 | AX14: 18.4 | AY14: =AW14+AX14 -> 27.6 | AZ14: =SUM(Z14:AK14) -> 75.15 | BA14: 50 | BB14: =BA14-AW14 -> 40.8 | BC14: =IFERROR(BB14/4,0) -> 10.2 | BD14: =AY14-AZ14 -> -47.55 | BE14: =AZ14-AW14 -> 65.95 | BF14: No | BG14: =AVERAGE(AL14:AS14) -> 1.15 | BH14: Yes | BI14: =IF(BF14="Yes","",IF(BA14>1250,"E",IF(BA14>750,"D", IF(BA14>=500,"C", IF(BA14>=300,"B", IF(BA14>=200,"A", "")))))) | BJ14: =IF(BF14="Yes","",IF(AY14>1250,"E",IF(AY14>750,"D", IF(AY14>=500,"C", IF(AY14>=300,"B", IF(AY14>=200,"A", "")))))) | BK14: =SUM(AR14:AX14) -> 27.6 | BL14: =SUM(AL14:AQ14) -> 9.2 | BM14: =IFERROR(BK14/$AY14,"") -> 1 | BN14: =IFERROR(BL14/$AY14,"") -> 0.33333333 | BO14: =SUM(AL14:AS14) -> 9.2 | BP14: =IF(BF14="Yes","",IF(BO14>1250,"E",IF(BO14>750,"D", IF(BO14>=500,"C", IF(BO14>=300,"B", IF(BO14>=200,"A", "")))))) | BR14: =SUM(Z14:AE14) -> 6.45 | BS14: =SUM(AF14:AK14) -> 68.7 | BT14: =SUM(BR14:BS14) -> 75.15 | BU14: =IFERROR(_xlfn.XLOOKUP(D14,Sheet1!B:B,Sheet1!L:L),"") | BV14: =_xlfn.XLOOKUP(BU14,Sheet1!S:S,Sheet1!T:T) -> #N/A | BW14: =_xlfn.XLOOKUP(D14,Sheet1!B:B,Sheet1!M:M) -> #N/A | BZ14: =AY14-AW14 -> 18.4 | CB14: =AW14/AY14 -> 0.33333333 | CC14: =AX14/AY14 -> 0.66666667 | CG14: =IF(BO14<80,"Below 80", IF(BO14<=120,"80-120", IF(BO14<=200,"> 120-200", IF(BO14<=300,">200-300", IF(BO14<=500,">300-500", ">500"))))) -> Below 80 | CH14: =IFERROR(_xlfn.XLOOKUP(CG14,Scenario!M:M,Scenario!N:N),"") | CI14: =IF(BI14="", IF(BA14>=1, "Yes", "No")) -> Yes | CJ14: 18.4 | DY14: Overall retail sales | DZ14: 83000
A15: 14 | B15: 2023 | C15: PBTMTR178 | D15: 001J1000002in9QIAQ | E15: GLOBAL STEEL | F15: ODISHA | G15: SAMBALPUR | H15: 0 | I15: SACHDEVA ISPAT PVT LTD | J15: Papun Padhan | K15: Papun Pradhan | L15: C12823 | M15: Central | N15: 768228 | O15: 21AWRPT5068N2ZO | P15: 7077774769 | Q15: Dec'23 | R15: 2024 | S15: 100 | U15: 0 | V15: Potential Not updated | W15: 40 | X15: 0 | Y15: 0 | Z15: 50.05 | AA15: 50.25 | AB15: 51 | AC15: 30 | AD15: 0 | AE15: 0 | AF15: 0 | AG15: 0 | AH15: 0 | AI15: 0 | AJ15: 0 | AK15: 0 | AL15: 0 | AM15: 0 | AN15: 0 | AO15: 0 | AP15: 0 | AQ15: 0 | AR15: 0 | AS15: 0 | AT15: 0 | AU15: 0 | AV15: 0 | AW15: =SUM(AL15:AU15) -> 0 | AX15: 0 | AY15: =AW15+AX15 -> 0 | AZ15: =SUM(Z15:AK15) -> 181.3 | BA15: 0 | BB15: =BA15-AW15 -> 0 | BC15: =IFERROR(BB15/4,0) -> 0 | BD15: =AY15-AZ15 -> -181.3 | BE15: =AZ15-AW15 -> 181.3 | BF15: Yes | BG15: =AVERAGE(AL15:AS15) -> 0 | BH15: No | BI15: =IF(BF15="Yes","",IF(BA15>1250,"E",IF(BA15>750,"D", IF(BA15>=500,"C", IF(BA15>=300,"B", IF(BA15>=200,"A", "")))))) | BJ15: =IF(BF15="Yes","",IF(AY15>1250,"E",IF(AY15>750,"D", IF(AY15>=500,"C", IF(AY15>=300,"B", IF(AY15>=200,"A", "")))))) | BK15: =SUM(AR15:AX15) -> 0 | BL15: =SUM(AL15:AQ15) -> 0 | BM15: =IFERROR(BK15/$AY15,"") | BN15: =IFERROR(BL15/$AY15,"") | BO15: =SUM(AL15:AS15) -> 0 | BP15: =IF(BF15="Yes","",IF(BO15>1250,"E",IF(BO15>750,"D", IF(BO15>=500,"C", IF(BO15>=300,"B", IF(BO15>=200,"A", "")))))) | BR15: =SUM(Z15:AE15) -> 181.3 | BS15: =SUM(AF15:AK15) -> 0 | BT15: =SUM(BR15:BS15) -> 181.3 | BU15: =IFERROR(_xlfn.XLOOKUP(D15,Sheet1!B:B,Sheet1!L:L),"") | BV15: =_xlfn.XLOOKUP(BU15,Sheet1!S:S,Sheet1!T:T) -> #N/A | BW15: =_xlfn.XLOOKUP(D15,Sheet1!B:B,Sheet1!M:M) -> #N/A | BZ15: =AY15-AW15 -> 0 | CG15: =IF(BO15<80,"Below 80", IF(BO15<=120,"80-120", IF(BO15<=200,"> 120-200", IF(BO15<=300,">200-300", IF(BO15<=500,">300-500", ">500"))))) -> Below 80 | CH15: =IFERROR(_xlfn.XLOOKUP(CG15,Scenario!M:M,Scenario!N:N),"") | CI15: =IF(BI15="", IF(BA15>=1, "Yes", "No")) -> No | CJ15: 0 | DY15: Per MT | DZ15: 91.048193
A16: 15 | B16: 2023 | C16: PBTMTR04 | D16: 0015g00001Y3x1EAAR | E16: M/S MEENA STEELS | F16: UTTAR PRADESH | G16: AGRA | H16: Agra | I16: DINESH STEEL PRIVATE LIMITED | J16: Pankaj Garg | K16: - | L16: C12820 | M16: North | N16: 282007 | O16: 09AEAPJ9199R1ZF | P16: 9837021446 | Q16: Dec'23 | R16: 2024 | S16: 108 | T16: 100 | U16: 0.77 | V16: Star | W16: 11 | X16: 25 | Y16: 52 | Z16: 12 | AA16: 17 | AB16: 22 | AC16: 50 | AD16: 25 | AE16: 12 | AF16: 17 | AG16: 16 | AH16: 25 | AI16: 20 | AJ16: 25 | AK16: 61 | AL16: 30 | AM16: 18 | AN16: 17 | AO16: 12.1 | AP16: 28.12 | AQ16: 42.11 | AR16: 14.96 | AS16: 15.01 | AT16: 32.02 | AU16: 32 | AV16: 166.98 | AW16: =SUM(AL16:AU16) -> 241.32 | AX16: 338.71 | AY16: =BW16 -> 501 | AZ16: =SUM(Z16:AK16) -> 302 | BA16: 300 | BB16: =BA16-AW16 -> 58.68 | BC16: =IFERROR(BB16/4,0) -> 14.67 | BD16: =AY16-AZ16 -> 199 | BE16: =AZ16-AW16 -> 60.68 | BF16: No | BG16: =AVERAGE(AL16:AS16) -> 22.1625 | BH16: Yes | BI16: =IF(BF16="Yes","",IF(BA16>1250,"E",IF(BA16>750,"D", IF(BA16>=500,"C", IF(BA16>=300,"B", IF(BA16>=200,"A", "")))))) -> B | BJ16: =IF(BF16="Yes","",IF(AY16>1250,"E",IF(AY16>750,"D", IF(AY16>=500,"C", IF(AY16>=300,"B", IF(AY16>=200,"A", "")))))) -> C | BK16: =SUM(AR16:AX16) -> 841 | BL16: =SUM(AL16:AQ16) -> 147.33 | BM16: =IFERROR(BK16/$AY16,"") -> 1.6786427 | BN16: =IFERROR(BL16/$AY16,"") -> 0.29407186 | BO16: =SUM(AL16:AS16) -> 177.3 | BP16: =IF(BF16="Yes","",IF(BO16>1250,"E",IF(BO16>750,"D", IF(BO16>=500,"C", IF(BO16>=300,"B", IF(BO16>=200,"A", "")))))) | BR16: =SUM(Z16:AE16) -> 138 | BS16: =SUM(AF16:AK16) -> 164 | BT16: =SUM(BR16:BS16) -> 302 | BU16: =IFERROR(_xlfn.XLOOKUP(D16,Sheet1!B:B,Sheet1!L:L),"") -> International trip (1 pax Almaty) 3N-4D | BV16: =_xlfn.XLOOKUP(BU16,Sheet1!S:S,Sheet1!T:T) -> #N/A | BW16: =_xlfn.XLOOKUP(D16,Sheet1!B:B,Sheet1!M:M) -> 501 | BX16: Qualified in Tour Scheme FY25 | BY16: 501 | BZ16: =AY16-AW16 -> 259.68 | CB16: =AW16/AY16 -> 0.48167665 | CC16: =AX16/AY16 -> 0.67606786 | CG16: =IF(BO16<80,"Below 80", IF(BO16<=120,"80-120", IF(BO16<=200,"> 120-200", IF(BO16<=300,">200-300", IF(BO16<=500,">300-500", ">500"))))) -> > 120-200 | CH16: =IFERROR(_xlfn.XLOOKUP(CG16,Scenario!M:M,Scenario!N:N),"") -> B | CI16: =IF(BI16="", IF(BA16>=1, "Yes", "No")) -> FALSE | CJ16: 323.7
A17: 16 | B17: 2023 | C17: PBTMTR05 | D17: 0015g00001ehWMuAAM | E17: M/S MITTAL STEELS | F17: UTTAR PRADESH | G17: AGRA | H17: Etmadpur | I17: DINESH STEEL PRIVATE LIMITED | J17: Pankaj Garg | K17: - | L17: C12820 | M17: North | N17: 282005 | O17: 09AFYPM6727P1Z6 | P17: 9837163079 | Q17: Dec'23 | R17: 2024 | S17: 53 | T17: 50 | U17: 0 | V17: Minor | W17: 11 | X17: 0 | Y17: 30 | Z17: 10 | AA17: 15 | AB17: 3 | AC17: 4 | AD17: 5 | AE17: 5 | AF17: 10 | AG17: 10 | AH17: 5 | AI17: 8 | AJ17: 10 | AK17: 10 | AL17: 10 | AM17: 10 | AN17: 8 | AO17: 0 | AP17: 0 | AQ17: 0 | AR17: 0 | AS17: 0 | AT17: 0 | AU17: 0 | AV17: 0 | AW17: =SUM(AL17:AU17) -> 28 | AX17: 56 | AY17: =AW17+AX17 -> 84 | AZ17: =SUM(Z17:AK17) -> 95 | BA17: 100 | BB17: =BA17-AW17 -> 72 | BC17: =IFERROR(BB17/4,0) -> 18 | BD17: =AY17-AZ17 -> -11 | BE17: =AZ17-AW17 -> 67 | BF17: No | BG17: =AVERAGE(AL17:AS17) -> 3.5 | BH17: Yes | BI17: =IF(BF17="Yes","",IF(BA17>1250,"E",IF(BA17>750,"D", IF(BA17>=500,"C", IF(BA17>=300,"B", IF(BA17>=200,"A", "")))))) | BJ17: =IF(BF17="Yes","",IF(AY17>1250,"E",IF(AY17>750,"D", IF(AY17>=500,"C", IF(AY17>=300,"B", IF(AY17>=200,"A", "")))))) | BK17: =SUM(AR17:AX17) -> 84 | BL17: =SUM(AL17:AQ17) -> 28 | BM17: =IFERROR(BK17/$AY17,"") -> 1 | BN17: =IFERROR(BL17/$AY17,"") -> 0.33333333 | BO17: =SUM(AL17:AS17) -> 28 | BP17: =IF(BF17="Yes","",IF(BO17>1250,"E",IF(BO17>750,"D", IF(BO17>=500,"C", IF(BO17>=300,"B", IF(BO17>=200,"A", "")))))) | BQ17: Neosteel dealer; Has project specific demand - can push since Neosteel will have shortage of material | BR17: =SUM(Z17:AE17) -> 42 | BS17: =SUM(AF17:AK17) -> 53 | BT17: =SUM(BR17:BS17) -> 95 | BU17: =IFERROR(_xlfn.XLOOKUP(D17,Sheet1!B:B,Sheet1!L:L),"") | BV17: =_xlfn.XLOOKUP(BU17,Sheet1!S:S,Sheet1!T:T) -> #N/A | BW17: =_xlfn.XLOOKUP(D17,Sheet1!B:B,Sheet1!M:M) -> #N/A | BZ17: =AY17-AW17 -> 56 | CB17: =AW17/AY17 -> 0.33333333 | CC17: =AX17/AY17 -> 0.66666667 | CG17: =IF(BO17<80,"Below 80", IF(BO17<=120,"80-120", IF(BO17<=200,"> 120-200", IF(BO17<=300,">200-300", IF(BO17<=500,">300-500", ">500"))))) -> Below 80 | CH17: =IFERROR(_xlfn.XLOOKUP(CG17,Scenario!M:M,Scenario!N:N),"") | CI17: =IF(BI17="", IF(BA17>=1, "Yes", "No")) -> Yes | CJ17: 56
A18: 17 | B18: 2023 | C18: PBTMTR06 | D18: 0015g00001XbzInAAJ | E18: Dinesh Steel PVT LTD | F18: UTTAR PRADESH | G18: AGRA | H18: Sadar | I18: DINESH STEEL PRIVATE LIMITED | J18: Pankaj Garg | K18: - | L18: C12820 | M18: North | N18: 282002 | O18: 0 | P18: 0 | Q18: Dec'23 | R18: 2024 | S18: 339 | T18: 400 | U18: 0 | V18: Alien | W18: 87 | X18: 64 | Y18: 125 | Z18: 26 | AA18: 47 | AB18: 15 | AC18: 30 | AD18: 31 | AE18: 15 | AF18: 25 | AG18: 300 | AH18: 165 | AI18: 350 | AJ18: 482 | AK18: 500 | AL18: 11 | AM18: 15 | AN18: 0 | AO18: 0 | AP18: 0 | AQ18: 0 | AR18: 0 | AS18: 0 | AT18: 0 | AU18: 0 | AV18: 0 | AW18: =SUM(AL18:AU18) -> 26 | AX18: 52 | AY18: =AW18+AX18 -> 78 | AZ18: =SUM(Z18:AK18) -> 1986 | BA18: 26 | BB18: =BA18-AW18 -> 0 | BC18: =IFERROR(BB18/4,0) -> 0 | BD18: =AY18-AZ18 -> -1908 | BE18: =AZ18-AW18 -> 1960 | BF18: Yes | BG18: =AVERAGE(AL18:AS18) -> 3.25 | BH18: No | BI18: =IF(BF18="Yes","",IF(BA18>1250,"E",IF(BA18>750,"D", IF(BA18>=500,"C", IF(BA18>=300,"B", IF(BA18>=200,"A", "")))))) | BJ18: =IF(BF18="Yes","",IF(AY18>1250,"E",IF(AY18>750,"D", IF(AY18>=500,"C", IF(AY18>=300,"B", IF(AY18>=200,"A", "")))))) | BK18: =SUM(AR18:AX18) -> 78 | BL18: =SUM(AL18:AQ18) -> 26 | BM18: =IFERROR(BK18/$AY18,"") -> 1 | BN18: =IFERROR(BL18/$AY18,"") -> 0.33333333 | BO18: =SUM(AL18:AS18) -> 26 | BP18: =IF(BF18="Yes","",IF(BO18>1250,"E",IF(BO18>750,"D", IF(BO18>=500,"C", IF(BO18>=300,"B", IF(BO18>=200,"A", "")))))) | BQ18: Distributor self-counter | BR18: =SUM(Z18:AE18) -> 164 | BS18: =SUM(AF18:AK18) -> 1822 | BT18: =SUM(BR18:BS18) -> 1986 | BU18: =IFERROR(_xlfn.XLOOKUP(D18,Sheet1!B:B,Sheet1!L:L),"") | BV18: =_xlfn.XLOOKUP(BU18,Sheet1!S:S,Sheet1!T:T) -> #N/A | BW18: =_xlfn.XLOOKUP(D18,Sheet1!B:B,Sheet1!M:M) -> #N/A | BZ18: =AY18-AW18 -> 52 | CB18: =AW18/AY18 -> 0.33333333 | CC18: =AX18/AY18 -> 0.66666667 | CG18: =IF(BO18<80,"Below 80", IF(BO18<=120,"80-120", IF(BO18<=200,"> 120-200", IF(BO18<=300,">200-300", IF(BO18<=500,">300-500", ">500"))))) -> Below 80 | CH18: =IFERROR(_xlfn.XLOOKUP(CG18,Scenario!M:M,Scenario!N:N),"") | CI18: =IF(BI18="", IF(BA18>=1, "Yes", "No")) -> Yes | CJ18: 52
A19: 18 | B19: 2023 | C19: PBTMTR76 | D19: 0015g00001ZWw5CAAT | E19: M/S J T STEEL TRADERS | F19: UTTAR PRADESH | G19: SHAHJAHANPUR | H19: Shahjahanpur | I19: Khandelwal Associates | J19: SHIV KUMAR | K19: Ashutosh Shukla | L19: C12818 | M19: North | N19: 242001 | O19: 09AYMPS5514P1ZI | P19: 9648071400 | Q19: Dec'23 | R19: 2024 | S19: 18 | T19: 200 | U19: 0 | V19: Challenger | W19: 0 | X19: 0 | Y19: 0 | Z19: 0 | AA19: 0 | AB19: 0 | AC19: 0 | AD19: 0 | AE19: 0 | AF19: 0 | AG19: 0 | AH19: 0 | AI19: 0 | AJ19: 0 | AK19: 0 | AL19: 0 | AM19: 0 | AN19: 0 | AO19: 0 | AP19: 0 | AQ19: 0 | AR19: 0 | AS19: 0 | AT19: 0 | AU19: 0 | AV19: 0 | AW19: =SUM(AL19:AU19) -> 0 | AX19: 0 | AY19: =AW19+AX19 -> 0 | AZ19: =SUM(Z19:AK19) -> 0 | BB19: =BA19-AW19 -> 0 | BC19: =IFERROR(BB19/4,0) -> 0 | BD19: =AY19-AZ19 -> 0 | BE19: =AZ19-AW19 -> 0 | BF19: No | BG19: =AVERAGE(AL19:AS19) -> 0 | BH19: Yes | BI19: =IF(BF19="Yes","",IF(BA19>1250,"E",IF(BA19>750,"D", IF(BA19>=500,"C", IF(BA19>=300,"B", IF(BA19>=200,"A", "")))))) | BJ19: =IF(BF19="Yes","",IF(AY19>1250,"E",IF(AY19>750,"D", IF(AY19>=500,"C", IF(AY19>=300,"B", IF(AY19>=200,"A", "")))))) | BK19: =SUM(AR19:AX19) -> 0 | BL19: =SUM(AL19:AQ19) -> 0 | BM19: =IFERROR(BK19/$AY19,"") | BN19: =IFERROR(BL19/$AY19,"") | BO19: =SUM(AL19:AS19) -> 0 | BP19: =IF(BF19="Yes","",IF(BO19>1250,"E",IF(BO19>750,"D", IF(BO19>=500,"C", IF(BO19>=300,"B", IF(BO19>=200,"A", "")))))) | BR19: =SUM(Z19:AE19) -> 0 | BS19: =SUM(AF19:AK19) -> 0 | BT19: =SUM(BR19:BS19) -> 0 | BU19: =IFERROR(_xlfn.XLOOKUP(D19,Sheet1!B:B,Sheet1!L:L),"") | BV19: =_xlfn.XLOOKUP(BU19,Sheet1!S:S,Sheet1!T:T) -> #N/A | BW19: =_xlfn.XLOOKUP(D19,Sheet1!B:B,Sheet1!M:M) -> #N/A | BZ19: =AY19-AW19 -> 0 | CG19: =IF(BO19<80,"Below 80", IF(BO19<=120,"80-120", IF(BO19<=200,"> 120-200", IF(BO19<=300,">200-300", IF(BO19<=500,">300-500", ">500"))))) -> Below 80 | CH19: =IFERROR(_xlfn.XLOOKUP(CG19,Scenario!M:M,Scenario!N:N),"") | CI19: =IF(BI19="", IF(BA19>=1, "Yes", "No")) -> No | CJ19: 0
A20: 19 | B20: 2023 | C20: PBTMTR19 | D20: 0015g00001VBhGCAA1 | E20: LAKSHMI TRADING COMPANY | F20: UTTAR PRADESH | G20: PRAYAGRAJ | H20: Prayagraj | I20: GLOBAL IRONTRADING PVT. LTD. | J20: Divyansh Dhawal | K20: Varun Arora | L20: C12819 | M20: North | N20: 211002 | O20: 09AAVHA0822P1ZS | P20: 9415032051 | Q20: Dec'23 | R20: 2024 | S20: 100 | T20: 600 | U20: 0 | V20: Alien | W20: 30 | X20: 0 | Y20: 40 | Z20: 32 | AA20: 0 | AB20: 0 | AC20: 0 | AD20: 0 | AE20: 0 | AF20: 0 | AG20: 0 | AH20: 0 | AI20: 0 | AJ20: 0 | AK20: 0 | AL20: 0 | AM20: 0 | AN20: 0 | AO20: 0 | AP20: 0 | AQ20: 0 | AR20: 0 | AS20: 0 | AT20: 0 | AU20: 0 | AV20: 0 | AW20: =SUM(AL20:AU20) -> 0 | AX20: 0 | AY20: =AW20+AX20 -> 0 | AZ20: =SUM(Z20:AK20) -> 32 | BA20: 0 | BB20: =BA20-AW20 -> 0 | BC20: =IFERROR(BB20/4,0) -> 0 | BD20: =AY20-AZ20 -> -32 | BE20: =AZ20-AW20 -> 32 | BF20: No | BG20: =AVERAGE(AL20:AS20) -> 0 | BH20: Yes | BI20: =IF(BF20="Yes","",IF(BA20>1250,"E",IF(BA20>750,"D", IF(BA20>=500,"C", IF(BA20>=300,"B", IF(BA20>=200,"A", "")))))) | BJ20: =IF(BF20="Yes","",IF(AY20>1250,"E",IF(AY20>750,"D", IF(AY20>=500,"C", IF(AY20>=300,"B", IF(AY20>=200,"A", "")))))) | BK20: =SUM(AR20:AX20) -> 0 | BL20: =SUM(AL20:AQ20) -> 0 | BM20: =IFERROR(BK20/$AY20,"") | BN20: =IFERROR(BL20/$AY20,"") | BO20: =SUM(AL20:AS20) -> 0 | BP20: =IF(BF20="Yes","",IF(BO20>1250,"E",IF(BO20>750,"D", IF(BO20>=500,"C", IF(BO20>=300,"B", IF(BO20>=200,"A", "")))))) | BR20: =SUM(Z20:AE20) -> 32 | BS20: =SUM(AF20:AK20) -> 0 | BT20: =SUM(BR20:BS20) -> 32 | BU20: =IFERROR(_xlfn.XLOOKUP(D20,Sheet1!B:B,Sheet1!L:L),"") | BV20: =_xlfn.XLOOKUP(BU20,Sheet1!S:S,Sheet1!T:T) -> #N/A | BW20: =_xlfn.XLOOKUP(D20,Sheet1!B:B,Sheet1!M:M) -> #N/A | BZ20: =AY20-AW20 -> 0 | CG20: =IF(BO20<80,"Below 80", IF(BO20<=120,"80-120", IF(BO20<=200,"> 120-200", IF(BO20<=300,">200-300", IF(BO20<=500,">300-500", ">500"))))) -> Below 80 | CH20: =IFERROR(_xlfn.XLOOKUP(CG20,Scenario!M:M,Scenario!N:N),"") | CI20: =IF(BI20="", IF(BA20>=1, "Yes", "No")) -> No | CJ20: 0
A21: 20 | B21: 2023 | C21: PBTMTR20 | D21: 0015g00001V9dtGAAR | E21: SAMRAT CONSTRUCTION COMPANY | F21: UTTAR PRADESH | G21: PRAYAGRAJ | H21: Phulpur | I21: GLOBAL IRONTRADING PVT. LTD. | J21: Divyansh Dhawal | K21: Varun Arora | L21: C12819 | M21: North | N21: 211019 | O21: 09ANKPK2750N1Z1 | P21: 9651676023 | Q21: Dec'23 | R21: 2024 | S21: 100 | T21: 200 | U21: 0 | V21: Challenger | W21: 0 | X21: 30 | Y21: 40 | Z21: 40 | AA21: 0 | AB21: 0 | AC21: 0 | AD21: 49.97 | AE21: 0 | AF21: 0 | AG21: 0 | AH21: 0 | AI21: 0 | AJ21: 0 | AK21: 0 | AL21: 0 | AM21: 0 | AN21: 0 | AO21: 0 | AP21: 0 | AQ21: 0 | AR21: 0 | AS21: 0 | AT21: 0 | AU21: 0 | AV21: 0 | AW21: =SUM(AL21:AU21) -> 0 | AX21: 0 | AY21: =AW21+AX21 -> 0 | AZ21: =SUM(Z21:AK21) -> 89.97 | BA21: 0 | BB21: =BA21-AW21 -> 0 | BC21: =IFERROR(BB21/4,0) -> 0 | BD21: =AY21-AZ21 -> -89.97 | BE21: =AZ21-AW21 -> 89.97 | BF21: No | BG21: =AVERAGE(AL21:AS21) -> 0 | BH21: Yes | BI21: =IF(BF21="Yes","",IF(BA21>1250,"E",IF(BA21>750,"D", IF(BA21>=500,"C", IF(BA21>=300,"B", IF(BA21>=200,"A", "")))))) | BJ21: =IF(BF21="Yes","",IF(AY21>1250,"E",IF(AY21>750,"D", IF(AY21>=500,"C", IF(AY21>=300,"B", IF(AY21>=200,"A", "")))))) | BK21: =SUM(AR21:AX21) -> 0 | BL21: =SUM(AL21:AQ21) -> 0 | BM21: =IFERROR(BK21/$AY21,"") | BN21: =IFERROR(BL21/$AY21,"") | BO21: =SUM(AL21:AS21) -> 0 | BP21: =IF(BF21="Yes","",IF(BO21>1250,"E",IF(BO21>750,"D", IF(BO21>=500,"C", IF(BO21>=300,"B", IF(BO21>=200,"A", "")))))) | BR21: =SUM(Z21:AE21) -> 89.97 | BS21: =SUM(AF21:AK21) -> 0 | BT21: =SUM(BR21:BS21) -> 89.97 | BU21: =IFERROR(_xlfn.XLOOKUP(D21,Sheet1!B:B,Sheet1!L:L),"") | BV21: =_xlfn.XLOOKUP(BU21,Sheet1!S:S,Sheet1!T:T) -> #N/A | BW21: =_xlfn.XLOOKUP(D21,Sheet1!B:B,Sheet1!M:M) -> #N/A | BZ21: =AY21-AW21 -> 0 | CG21: =IF(BO21<80,"Below 80", IF(BO21<=120,"80-120", IF(BO21<=200,"> 120-200", IF(BO21<=300,">200-300", IF(BO21<=500,">300-500", ">500"))))) -> Below 80 | CH21: =IFERROR(_xlfn.XLOOKUP(CG21,Scenario!M:M,Scenario!N:N),"") | CI21: =IF(BI21="", IF(BA21>=1, "Yes", "No")) -> No | CJ21: 0
A22: 21 | B22: 2023 | C22: PBTMTR21 | D22: 0015g00001fuCAzAAM | E22: M/S SHIV SHAKTI STEEL | F22: UTTAR PRADESH | G22: SONBHADRA | H22: Robertsganj | I22: GLOBAL IRONTRADING PVT. LTD. | J22: Divyansh Dhawal | K22: Varun Arora | L22: C12819 | M22: North | N22: 231216 | O22: 09AFNPJ4598N1ZF | P22: 9935161777 | Q22: Dec'23 | R22: 2024 | S22: 45 | T22: 140 | U22: 0 | V22: Challenger | W22: 0 | X22: 15 | Y22: 0 | Z22: 15 | AA22: 0 | AB22: 0 | AC22: 0 | AD22: 0 | AE22: 5 | AF22: 0 | AG22: 0 | AH22: 0 | AI22: 0 | AJ22: 0 | AK22: 0 | AL22: 0 | AM22: 0 | AN22: 0 | AO22: 0 | AP22: 0 | AQ22: 0 | AR22: 0 | AS22: 0 | AT22: 0 | AU22: 0 | AV22: 0 | AW22: =SUM(AL22:AU22) -> 0 | AX22: 0 | AY22: =AW22+AX22 -> 0 | AZ22: =SUM(Z22:AK22) -> 20 | BA22: 0 | BB22: =BA22-AW22 -> 0 | BC22: =IFERROR(BB22/4,0) -> 0 | BD22: =AY22-AZ22 -> -20 | BE22: =AZ22-AW22 -> 20 | BF22: No | BG22: =AVERAGE(AL22:AS22) -> 0 | BH22: Yes | BI22: =IF(BF22="Yes","",IF(BA22>1250,"E",IF(BA22>750,"D", IF(BA22>=500,"C", IF(BA22>=300,"B", IF(BA22>=200,"A", "")))))) | BJ22: =IF(BF22="Yes","",IF(AY22>1250,"E",IF(AY22>750,"D", IF(AY22>=500,"C", IF(AY22>=300,"B", IF(AY22>=200,"A", "")))))) | BK22: =SUM(AR22:AX22) -> 0 | BL22: =SUM(AL22:AQ22) -> 0 | BM22: =IFERROR(BK22/$AY22,"") | BN22: =IFERROR(BL22/$AY22,"") | BO22: =SUM(AL22:AS22) -> 0 | BP22: =IF(BF22="Yes","",IF(BO22>1250,"E",IF(BO22>750,"D", IF(BO22>=500,"C", IF(BO22>=300,"B", IF(BO22>=200,"A", "")))))) | BR22: =SUM(Z22:AE22) -> 20 | BS22: =SUM(AF22:AK22) -> 0 | BT22: =SUM(BR22:BS22) -> 20 | BU22: =IFERROR(_xlfn.XLOOKUP(D22,Sheet1!B:B,Sheet1!L:L),"") | BV22: =_xlfn.XLOOKUP(BU22,Sheet1!S:S,Sheet1!T:T) -> #N/A | BW22: =_xlfn.XLOOKUP(D22,Sheet1!B:B,Sheet1!M:M) -> #N/A | BZ22: =AY22-AW22 -> 0 | CG22: =IF(BO22<80,"Below 80", IF(BO22<=120,"80-120", IF(BO22<=200,"> 120-200", IF(BO22<=300,">200-300", IF(BO22<=500,">300-500", ">500"))))) -> Below 80 | CH22: =IFERROR(_xlfn.XLOOKUP(CG22,Scenario!M:M,Scenario!N:N),"") | CI22: =IF(BI22="", IF(BA22>=1, "Yes", "No")) -> No | CJ22: 0
A23: 22 | B23: 2023 | C23: PBTMTR22 | D23: 0015g00001caT4XAAU | E23: M/S TIRUPATI INFRA DEVLOPERS | F23: UTTAR PRADESH | G23: VARANASI | H23: Rajatalab | I23: GLOBAL IRONTRADING PVT. LTD. | J23: Divyansh Dhawal | K23: Varun Arora | L23: C12819 | M23: North | N23: 221311 | O23: 09FAUPS8239A1Z1 | P23: 9918357444 | Q23: Dec'23 | R23: 2024 | S23: 343 | T23: 150 | U23: 0 | V23: Challenger | W23: 55 | X23: 30 | Y23: 56 | Z23: 35 | AA23: 0 | AB23: 30 | AC23: 0 | AD23: 50 | AE23: 60 | AF23: 35 | AG23: 0 | AH23: 71 | AI23: 65 | AJ23: 147 | AK23: 131.12 | AL23: 131 | AM23: 71 | AN23: 120 | AO23: 59.83 | AP23: 94.67 | AQ23: 47.93 | AR23: 30.24 | AS23: 30.15 | AT23: 0 | AU23: 0 | AV23: 0 | AW23: =SUM(AL23:AU23) -> 584.82 | AX23: 696.33 | AY23: =BW23 -> 1251 | AZ23: =SUM(Z23:AK23) -> 624.12 | BA23: 1251 | BB23: =BA23-AW23 -> 666.18 | BC23: =IFERROR(BB23/4,0) -> 166.545 | BD23: =AY23-AZ23 -> 626.88 | BE23: =AZ23-AW23 -> 39.3 | BF23: No | BG23: =AVERAGE(AL23:AS23) -> 73.1025 | BH23: Yes | BI23: =IF(BF23="Yes","",IF(BA23>1250,"E",IF(BA23>750,"D", IF(BA23>=500,"C", IF(BA23>=300,"B", IF(BA23>=200,"A", "")))))) -> E | BJ23: =IF(BF23="Yes","",IF(AY23>1250,"E",IF(AY23>750,"D", IF(AY23>=500,"C", IF(AY23>=300,"B", IF(AY23>=200,"A", "")))))) -> E | BK23: =SUM(AR23:AX23) -> 1341.54 | BL23: =SUM(AL23:AQ23) -> 524.43 | BM23: =IFERROR(BK23/$AY23,"") -> 1.0723741 | BN23: =IFERROR(BL23/$AY23,"") -> 0.41920863 | BO23: =SUM(AL23:AS23) -> 584.82 | BP23: =IF(BF23="Yes","",IF(BO23>1250,"E",IF(BO23>750,"D", IF(BO23>=500,"C", IF(BO23>=300,"B", IF(BO23>=200,"A", "")))))) -> C | BR23: =SUM(Z23:AE23) -> 175 | BS23: =SUM(AF23:AK23) -> 449.12 | BT23: =SUM(BR23:BS23) -> 624.12 | BU23: =IFERROR(_xlfn.XLOOKUP(D23,Sheet1!B:B,Sheet1!L:L),"") -> Luxury International Trip (2 pax Dubai) 3N-4D | BV23: =_xlfn.XLOOKUP(BU23,Sheet1!S:S,Sheet1!T:T) -> E | BW23: =_xlfn.XLOOKUP(D23,Sheet1!B:B,Sheet1!M:M) -> 1251 | BX23: Qualified in Tour Scheme FY25 | BY23: 1251 | BZ23: =AY23-AW23 -> 666.18 | CB23: =AW23/AY23 -> 0.46748201 | CC23: =AX23/AY23 -> 0.55661871 | CD23: =AW23*1 -> 584.82 | CF23: =CD23+AW23 -> 1169.64 | CG23: =IF(BO23<80,"Below 80", IF(BO23<=120,"80-120", IF(BO23<=200,"> 120-200", IF(BO23<=300,">200-300", IF(BO23<=500,">300-500", ">500"))))) -> >500 | CH23: =IFERROR(_xlfn.XLOOKUP(CG23,Scenario!M:M,Scenario!N:N),"") -> E | CI23: =IF(BI23="", IF(BA23>=1, "Yes", "No")) -> FALSE | CJ23: 666.18
A24: 23 | B24: 2023 | C24: PBTMTR30 | D24: 0015g00001VA0tkAAD | E24: MAA SHARDA ENTERPRISES | F24: UTTAR PRADESH | G24: MAHARAJGANJ | H24: Anandapur | I24: GOBINDGARH IRON LLP | J24: Mohd Ansari | K24: - | L24: C12817 | M24: North | N24: 273303 | O24: 09AGWSA3180D1ZE | P24: 9839468611 | Q24: Dec'23 | R24: 2024 | S24: 30 | T24: 100 | U24: 0 | V24: Challenger | W24: 20 | X24: 0 | Y24: 0 | Z24: 33 | AA24: 0 | AB24: 0 | AC24: 0 | AD24: 0 | AE24: 0 | AF24: 0 | AG24: 0 | AH24: 0 | AI24: 0 | AJ24: 0 | AK24: 0 | AL24: 0 | AM24: 0 | AN24: 0 | AO24: 0 | AP24: 0 | AQ24: 0 | AR24: 0 | AS24: 0 | AT24: 0 | AU24: 0 | AV24: 0 | AW24: =SUM(AL24:AU24) -> 0 | AX24: 0 | AY24: =AW24+AX24 -> 0 | AZ24: =SUM(Z24:AK24) -> 33 | BA24: 0 | BB24: =BA24-AW24 -> 0 | BC24: =IFERROR(BB24/4,0) -> 0 | BD24: =AY24-AZ24 -> -33 | BE24: =AZ24-AW24 -> 33 | BF24: No | BG24: =AVERAGE(AL24:AS24) -> 0 | BH24: Yes | BI24: =IF(BF24="Yes","",IF(BA24>1250,"E",IF(BA24>750,"D", IF(BA24>=500,"C", IF(BA24>=300,"B", IF(BA24>=200,"A", "")))))) | BJ24: =IF(BF24="Yes","",IF(AY24>1250,"E",IF(AY24>750,"D", IF(AY24>=500,"C", IF(AY24>=300,"B", IF(AY24>=200,"A", "")))))) | BK24: =SUM(AR24:AX24) -> 0 | BL24: =SUM(AL24:AQ24) -> 0 | BM24: =IFERROR(BK24/$AY24,"") | BN24: =IFERROR(BL24/$AY24,"") | BO24: =SUM(AL24:AS24) -> 0 | BP24: =IF(BF24="Yes","",IF(BO24>1250,"E",IF(BO24>750,"D", IF(BO24>=500,"C", IF(BO24>=300,"B", IF(BO24>=200,"A", "")))))) | BR24: =SUM(Z24:AE24) -> 33 | BS24: =SUM(AF24:AK24) -> 0 | BT24: =SUM(BR24:BS24) -> 33 | BU24: =IFERROR(_xlfn.XLOOKUP(D24,Sheet1!B:B,Sheet1!L:L),"") | BV24: =_xlfn.XLOOKUP(BU24,Sheet1!S:S,Sheet1!T:T) -> #N/A | BW24: =_xlfn.XLOOKUP(D24,Sheet1!B:B,Sheet1!M:M) -> #N/A | BZ24: =AY24-AW24 -> 0 | CG24: =IF(BO24<80,"Below 80", IF(BO24<=120,"80-120", IF(BO24<=200,"> 120-200", IF(BO24<=300,">200-300", IF(BO24<=500,">300-500", ">500"))))) -> Below 80 | CH24: =IFERROR(_xlfn.XLOOKUP(CG24,Scenario!M:M,Scenario!N:N),"") | CI24: =IF(BI24="", IF(BA24>=1, "Yes", "No")) -> No | CJ24: 0
A25: 24 | B25: 2023 | C25: PBTMTR31 | D25: 0015g00001dYmj7AAC | E25: M/s ANKUR BUILDING MATERIAL | F25: UTTAR PRADESH | G25: 0 | H25: Khalilabad | I25: GOBINDGARH IRON LLP | J25: Mohd Ansari | K25: - | L25: C12817 | M25: North | N25: 273307 | O25: 09BEDPA3068J1ZK | P25: 9794413130 | Q25: Dec'23 | R25: 2024 | S25: 33 | T25: 40 | U25: 0 | V25: Minor | W25: 14 | X25: 5 | Y25: 9 | Z25: 7 | AA25: 5 | AB25: 0 | AC25: 0 | AD25: 5 | AE25: 5 | AF25: 5 | AG25: 5 | AH25: 0 | AI25: 0 | AJ25: 0 | AK25: 0 | AL25: 0 | AM25: 0 | AN25: 0 | AO25: 0 | AP25: 0 | AQ25: 0 | AR25: 0 | AS25: 0 | AT25: 0 | AU25: 0 | AV25: 0 | AW25: =SUM(AL25:AU25) -> 0 | AX25: 0 | AY25: =AW25+AX25 -> 0 | AZ25: =SUM(Z25:AK25) -> 32 | BA25: 0 | BB25: =BA25-AW25 -> 0 | BC25: =IFERROR(BB25/4,0) -> 0 | BD25: =AY25-AZ25 -> -32 | BE25: =AZ25-AW25 -> 32 | BF25: No | BG25: =AVERAGE(AL25:AS25) -> 0 | BH25: Yes | BI25: =IF(BF25="Yes","",IF(BA25>1250,"E",IF(BA25>750,"D", IF(BA25>=500,"C", IF(BA25>=300,"B", IF(BA25>=200,"A", "")))))) | BJ25: =IF(BF25="Yes","",IF(AY25>1250,"E",IF(AY25>750,"D", IF(AY25>=500,"C", IF(AY25>=300,"B", IF(AY25>=200,"A", "")))))) | BK25: =SUM(AR25:AX25) -> 0 | BL25: =SUM(AL25:AQ25) -> 0 | BM25: =IFERROR(BK25/$AY25,"") | BN25: =IFERROR(BL25/$AY25,"") | BO25: =SUM(AL25:AS25) -> 0 | BP25: =IF(BF25="Yes","",IF(BO25>1250,"E",IF(BO25>750,"D", IF(BO25>=500,"C", IF(BO25>=300,"B", IF(BO25>=200,"A", "")))))) | BR25: =SUM(Z25:AE25) -> 22 | BS25: =SUM(AF25:AK25) -> 10 | BT25: =SUM(BR25:BS25) -> 32 | BU25: =IFERROR(_xlfn.XLOOKUP(D25,Sheet1!B:B,Sheet1!L:L),"") | BV25: =_xlfn.XLOOKUP(BU25,Sheet1!S:S,Sheet1!T:T) -> #N/A | BW25: =_xlfn.XLOOKUP(D25,Sheet1!B:B,Sheet1!M:M) -> #N/A | BZ25: =AY25-AW25 -> 0 | CG25: =IF(BO25<80,"Below 80", IF(BO25<=120,"80-120", IF(BO25<=200,"> 120-200", IF(BO25<=300,">200-300", IF(BO25<=500,">300-500", ">500"))))) -> Below 80 | CH25: =IFERROR(_xlfn.XLOOKUP(CG25,Scenario!M:M,Scenario!N:N),"") | CI25: =IF(BI25="", IF(BA25>=1, "Yes", "No")) -> No | CJ25: 0
A26: 25 | B26: 2023 | C26: PBTMTR32 | D26: 0015g00001cc8IbAAI | E26: AKBUILDERS | F26: UTTAR PRADESH | G26: SANT KABEER NAGAR | H26: Khalilabad | I26: GOBINDGARH IRON LLP | J26: Mohd Ansari | K26: - | L26: C12817 | M26: North | N26: 272175 | O26: 09AK1PN9621Z1 | P26: 0 | Q26: Dec'23 | R26: 2024 | S26: 51 | T26: 45 | U26: 0 | V26: Minor | W26: 15 | X26: 15 | Y26: 10 | Z26: 0 | AA26: 0 | AB26: 5 | AC26: 9 | AD26: 10 | AE26: 5 | AF26: 7 | AG26: 5 | AH26: 5 | AI26: 5 | AJ26: 5 | AK26: 0 | AL26: 0 | AM26: 0 | AN26: 0 | AO26: 0 | AP26: 0 | AQ26: 0 | AR26: 0 | AS26: 0 | AT26: 0 | AU26: 0 | AV26: 0 | AW26: =SUM(AL26:AU26) -> 0 | AX26: 0 | AY26: =AW26+AX26 -> 0 | AZ26: =SUM(Z26:AK26) -> 56 | BA26: 0 | BB26: =BA26-AW26 -> 0 | BC26: =IFERROR(BB26/4,0) -> 0 | BD26: =AY26-AZ26 -> -56 | BE26: =AZ26-AW26 -> 56 | BF26: No | BG26: =AVERAGE(AL26:AS26) -> 0 | BH26: Yes | BI26: =IF(BF26="Yes","",IF(BA26>1250,"E",IF(BA26>750,"D", IF(BA26>=500,"C", IF(BA26>=300,"B", IF(BA26>=200,"A", "")))))) | BJ26: =IF(BF26="Yes","",IF(AY26>1250,"E",IF(AY26>750,"D", IF(AY26>=500,"C", IF(AY26>=300,"B", IF(AY26>=200,"A", "")))))) | BK26: =SUM(AR26:AX26) -> 0 | BL26: =SUM(AL26:AQ26) -> 0 | BM26: =IFERROR(BK26/$AY26,"") | BN26: =IFERROR(BL26/$AY26,"") | BO26: =SUM(AL26:AS26) -> 0 | BP26: =IF(BF26="Yes","",IF(BO26>1250,"E",IF(BO26>750,"D", IF(BO26>=500,"C", IF(BO26>=300,"B", IF(BO26>=200,"A", "")))))) | BR26: =SUM(Z26:AE26) -> 29 | BS26: =SUM(AF26:AK26) -> 27 | BT26: =SUM(BR26:BS26) -> 56 | BU26: =IFERROR(_xlfn.XLOOKUP(D26,Sheet1!B:B,Sheet1!L:L),"") | BV26: =_xlfn.XLOOKUP(BU26,Sheet1!S:S,Sheet1!T:T) -> #N/A | BW26: =_xlfn.XLOOKUP(D26,Sheet1!B:B,Sheet1!M:M) -> #N/A | BZ26: =AY26-AW26 -> 0 | CG26: =IF(BO26<80,"Below 80", IF(BO26<=120,"80-120", IF(BO26<=200,"> 120-200", IF(BO26<=300,">200-300", IF(BO26<=500,">300-500", ">500"))))) -> Below 80 | CH26: =IFERROR(_xlfn.XLOOKUP(CG26,Scenario!M:M,Scenario!N:N),"") | CI26: =IF(BI26="", IF(BA26>=1, "Yes", "No")) -> No | CJ26: 0
A27: 26 | B27: 2023 | C27: PBTMTR33 | D27: 0015g00001VAzKvAAL | E27: AASHIRWAD BUILDING MATERIAL | F27: UTTAR PRADESH | G27: VARANASI | H27: Deoria | I27: GOBINDGARH IRON LLP | J27: Mohd Ansari | K27: - | L27: C12817 | M27: North | N27: 221001 | O27: 09ALHPK842181ZA | P27: 0 | Q27: Dec'23 | R27: 2024 | S27: 52 | T27: 70 | U27: 0 | V27: Challenger | W27: 9 | X27: 10 | Y27: 10 | Z27: 5 | AA27: 20 | AB27: 20 | AC27: 0 | AD27: 5 | AE27: 5 | AF27: 5 | AG27: 5 | AH27: 5 | AI27: 0 | AJ27: 0 | AK27: 0 | AL27: 0 | AM27: 0 | AN27: 0 | AO27: 0 | AP27: 0 | AQ27: 0 | AR27: 0 | AS27: 0 | AT27: 0 | AU27: 0 | AV27: 0 | AW27: =SUM(AL27:AU27) -> 0 | AX27: 0 | AY27: =AW27+AX27 -> 0 | AZ27: =SUM(Z27:AK27) -> 70 | BA27: 0 | BB27: =BA27-AW27 -> 0 | BC27: =IFERROR(BB27/4,0) -> 0 | BD27: =AY27-AZ27 -> -70 | BE27: =AZ27-AW27 -> 70 | BF27: No | BG27: =AVERAGE(AL27:AS27) -> 0 | BH27: Yes | BI27: =IF(BF27="Yes","",IF(BA27>1250,"E",IF(BA27>750,"D", IF(BA27>=500,"C", IF(BA27>=300,"B", IF(BA27>=200,"A", "")))))) | BJ27: =IF(BF27="Yes","",IF(AY27>1250,"E",IF(AY27>750,"D", IF(AY27>=500,"C", IF(AY27>=300,"B", IF(AY27>=200,"A", "")))))) | BK27: =SUM(AR27:AX27) -> 0 | BL27: =SUM(AL27:AQ27) -> 0 | BM27: =IFERROR(BK27/$AY27,"") | BN27: =IFERROR(BL27/$AY27,"") | BO27: =SUM(AL27:AS27) -> 0 | BP27: =IF(BF27="Yes","",IF(BO27>1250,"E",IF(BO27>750,"D", IF(BO27>=500,"C", IF(BO27>=300,"B", IF(BO27>=200,"A", "")))))) | BR27: =SUM(Z27:AE27) -> 55 | BS27: =SUM(AF27:AK27) -> 15 | BT27: =SUM(BR27:BS27) -> 70 | BU27: =IFERROR(_xlfn.XLOOKUP(D27,Sheet1!B:B,Sheet1!L:L),"") | BV27: =_xlfn.XLOOKUP(BU27,Sheet1!S:S,Sheet1!T:T) -> #N/A | BW27: =_xlfn.XLOOKUP(D27,Sheet1!B:B,Sheet1!M:M) -> #N/A | BZ27: =AY27-AW27 -> 0 | CG27: =IF(BO27<80,"Below 80", IF(BO27<=120,"80-120", IF(BO27<=200,"> 120-200", IF(BO27<=300,">200-300", IF(BO27<=500,">300-500", ">500"))))) -> Below 80 | CH27: =IFERROR(_xlfn.XLOOKUP(CG27,Scenario!M:M,Scenario!N:N),"") | CI27: =IF(BI27="", IF(BA27>=1, "Yes", "No")) -> No | CJ27: 0
A28: 27 | B28: 2023 | C28: PBTMTR34 | D28: 001J1000006UavzIAC | E28: GOBIND GARG STEEL | F28: UTTAR PRADESH | G28: JAUNPUR | H28: Gorakhpur | I28: GOBINDGARH IRON LLP | J28: Mohd Ansari | K28: - | L28: C12817 | M28: North | N28: 222139 | O28: 0 | P28: 0 | Q28: Dec'23 | R28: 2024 | S28: 108 | T28: 100 | U28: 0 | V28: Challenger | W28: 20 | X28: 30 | Y28: 38 | Z28: 20 | AA28: 30 | AB28: 6 | AC28: 10 | AD28: 40 | AE28: 10 | AF28: 9 | AG28: 10 | AH28: 30 | AI28: 64 | AJ28: 65 | AK28: 170 | AL28: 0 | AM28: 0 | AN28: 0 | AO28: 0 | AP28: 0 | AQ28: 0 | AR28: 0 | AS28: 0 | AT28: 0 | AU28: 0 | AV28: 0 | AW28: =SUM(AL28:AU28) -> 0 | AX28: 0 | AY28: =AW28+AX28 -> 0 | AZ28: =SUM(Z28:AK28) -> 464 | BA28: 0 | BB28: =BA28-AW28 -> 0 | BC28: =IFERROR(BB28/4,0) -> 0 | BD28: =AY28-AZ28 -> -464 | BE28: =AZ28-AW28 -> 464 | BF28: Yes | BG28: =AVERAGE(AL28:AS28) -> 0 | BH28: No | BI28: =IF(BF28="Yes","",IF(BA28>1250,"E",IF(BA28>750,"D", IF(BA28>=500,"C", IF(BA28>=300,"B", IF(BA28>=200,"A", "")))))) | BJ28: =IF(BF28="Yes","",IF(AY28>1250,"E",IF(AY28>750,"D", IF(AY28>=500,"C", IF(AY28>=300,"B", IF(AY28>=200,"A", "")))))) | BK28: =SUM(AR28:AX28) -> 0 | BL28: =SUM(AL28:AQ28) -> 0 | BM28: =IFERROR(BK28/$AY28,"") | BN28: =IFERROR(BL28/$AY28,"") | BO28: =SUM(AL28:AS28) -> 0 | BP28: =IF(BF28="Yes","",IF(BO28>1250,"E",IF(BO28>750,"D", IF(BO28>=500,"C", IF(BO28>=300,"B", IF(BO28>=200,"A", "")))))) | BR28: =SUM(Z28:AE28) -> 116 | BS28: =SUM(AF28:AK28) -> 348 | BT28: =SUM(BR28:BS28) -> 464 | BU28: =IFERROR(_xlfn.XLOOKUP(D28,Sheet1!B:B,Sheet1!L:L),"") | BV28: =_xlfn.XLOOKUP(BU28,Sheet1!S:S,Sheet1!T:T) -> #N/A | BW28: =_xlfn.XLOOKUP(D28,Sheet1!B:B,Sheet1!M:M) -> #N/A | BZ28: =AY28-AW28 -> 0 | CG28: =IF(BO28<80,"Below 80", IF(BO28<=120,"80-120", IF(BO28<=200,"> 120-200", IF(BO28<=300,">200-300", IF(BO28<=500,">300-500", ">500"))))) -> Below 80 | CH28: =IFERROR(_xlfn.XLOOKUP(CG28,Scenario!M:M,Scenario!N:N),"") | CI28: =IF(BI28="", IF(BA28>=1, "Yes", "No")) -> No | CJ28: 0
A29: 28 | B29: 2023 | C29: PBTMTR190 | D29: 0015g00001UBHh0AAH | E29: P.S Enterprises | F29: UTTAR PRADESH | G29: GHAZIABAD | H29: 0 | I29: SHASHI STEELS CORPORATION | J29: Abhijeet Biswas | K29: Abhijeet Biswas | L29: C12816 | M29: North | N29: 201002 | O29: 09DZYPK438F1ZQ | P29: 9871942109 | Q29: Dec'23 | R29: 2024 | S29: 266 | T29: 450 | U29: 0 | V29: Alien | W29: 82 | X29: 82 | Y29: 40 | Z29: 0 | AA29: 0 | AB29: 0 | AC29: 0 | AD29: 0 | AE29: 0 | AF29: 0 | AG29: 0 | AH29: 0 | AI29: 0 | AJ29: 0 | AK29: 0 | AL29: 0 | AM29: 0 | AN29: 0 | AO29: 0 | AP29: 0 | AQ29: 0 | AR29: 0 | AS29: 0 | AT29: 0 | AU29: 0 | AV29: 0 | AW29: =SUM(AL29:AU29) -> 0 | AX29: 0 | AY29: =AW29+AX29 -> 0 | AZ29: =SUM(Z29:AK29) -> 0 | BB29: =BA29-AW29 -> 0 | BC29: =IFERROR(BB29/4,0) -> 0 | BD29: =AY29-AZ29 -> 0 | BE29: =AZ29-AW29 -> 0 | BF29: No | BG29: =AVERAGE(AL29:AS29) -> 0 | BH29: Yes | BI29: =IF(BF29="Yes","",IF(BA29>1250,"E",IF(BA29>750,"D", IF(BA29>=500,"C", IF(BA29>=300,"B", IF(BA29>=200,"A", "")))))) | BJ29: =IF(BF29="Yes","",IF(AY29>1250,"E",IF(AY29>750,"D", IF(AY29>=500,"C", IF(AY29>=300,"B", IF(AY29>=200,"A", "")))))) | BK29: =SUM(AR29:AX29) -> 0 | BL29: =SUM(AL29:AQ29) -> 0 | BM29: =IFERROR(BK29/$AY29,"") | BN29: =IFERROR(BL29/$AY29,"") | BO29: =SUM(AL29:AS29) -> 0 | BP29: =IF(BF29="Yes","",IF(BO29>1250,"E",IF(BO29>750,"D", IF(BO29>=500,"C", IF(BO29>=300,"B", IF(BO29>=200,"A", "")))))) | BR29: =SUM(Z29:AE29) -> 0 | BS29: =SUM(AF29:AK29) -> 0 | BT29: =SUM(BR29:BS29) -> 0 | BU29: =IFERROR(_xlfn.XLOOKUP(D29,Sheet1!B:B,Sheet1!L:L),"") | BV29: =_xlfn.XLOOKUP(BU29,Sheet1!S:S,Sheet1!T:T) -> #N/A | BW29: =_xlfn.XLOOKUP(D29,Sheet1!B:B,Sheet1!M:M) -> #N/A | BZ29: =AY29-AW29 -> 0 | CG29: =IF(BO29<80,"Below 80", IF(BO29<=120,"80-120", IF(BO29<=200,"> 120-200", IF(BO29<=300,">200-300", IF(BO29<=500,">300-500", ">500"))))) -> Below 80 | CH29: =IFERROR(_xlfn.XLOOKUP(CG29,Scenario!M:M,Scenario!N:N),"") | CI29: =IF(BI29="", IF(BA29>=1, "Yes", "No")) -> No | CJ29: 0
A30: 29 | B30: 2023 | C30: PBTMTR192 | D30: 0015g00001UBHbSAAX | E30: KVA Trading Company | F30: UTTAR PRADESH | G30: GAUTAM BUDDHA NAGAR | H30: Ghaziabad | I30: SHASHI STEELS CORPORATION | J30: Abhijeet Biswas | K30: Abhijeet Biswas | L30: C12816 | M30: North | N30: 201009 | O30: 09DFGH6029LZ1 | P30: 8882424494 | Q30: Dec'23 | R30: 2024 | S30: 217 | T30: 450 | U30: 0.051851852 | V30: Alien | W30: 6 | X30: 30 | Y30: 104 | Z30: 0 | AA30: 0 | AB30: 0 | AC30: 0 | AD30: 0 | AE30: 0 | AF30: 0 | AG30: 0 | AH30: 0 | AI30: 0 | AJ30: 0 | AK30: 0 | AL30: 0 | AM30: 51 | AN30: 68.355 | AO30: 62.38 | AP30: 3.65 | AQ30: 0 | AR30: 10 | AS30: 36.47 | AT30: 0 | AU30: 0 | AV30: 70 | AW30: =SUM(AL30:AU30) -> 231.855 | AX30: =AW30*2 -> 463.71 | AY30: =AW30+AX30 -> 695.565 | AZ30: =SUM(Z30:AK30) -> 0 | BA30: 586.2 | BB30: =BA30-AW30 -> 354.345 | BC30: =IFERROR(BB30/4,0) -> 88.58625 | BD30: =AY30-AZ30 -> 695.565 | BE30: =AZ30-AW30 -> -231.855 | BF30: No | BG30: =AVERAGE(AL30:AS30) -> 28.981875 | BH30: Yes | BI30: =IF(BF30="Yes","",IF(BA30>1250,"E",IF(BA30>750,"D", IF(BA30>=500,"C", IF(BA30>=300,"B", IF(BA30>=200,"A", "")))))) -> C | BJ30: =IF(BF30="Yes","",IF(AY30>1250,"E",IF(AY30>750,"D", IF(AY30>=500,"C", IF(AY30>=300,"B", IF(AY30>=200,"A", "")))))) -> C | BK30: =SUM(AR30:AX30) -> 812.035 | BL30: =SUM(AL30:AQ30) -> 185.385 | BM30: =IFERROR(BK30/$AY30,"") -> 1.1674466 | BN30: =IFERROR(BL30/$AY30,"") -> 0.26652434 | BO30: =SUM(AL30:AS30) -> 231.855 | BP30: =IF(BF30="Yes","",IF(BO30>1250,"E",IF(BO30>750,"D", IF(BO30>=500,"C", IF(BO30>=300,"B", IF(BO30>=200,"A", "")))))) -> A | BR30: =SUM(Z30:AE30) -> 0 | BS30: =SUM(AF30:AK30) -> 0 | BT30: =SUM(BR30:BS30) -> 0 | BU30: =IFERROR(_xlfn.XLOOKUP(D30,Sheet1!B:B,Sheet1!L:L),"") | BV30: =_xlfn.XLOOKUP(BU30,Sheet1!S:S,Sheet1!T:T) -> #N/A | BW30: =_xlfn.XLOOKUP(D30,Sheet1!B:B,Sheet1!M:M) -> #N/A | BX30: New | BZ30: =AY30-AW30 -> 463.71 | CB30: =AW30/AY30 -> 0.33333333 | CC30: =AX30/AY30 -> 0.66666667 | CG30: =IF(BO30<80,"Below 80", IF(BO30<=120,"80-120", IF(BO30<=200,"> 120-200", IF(BO30<=300,">200-300", IF(BO30<=500,">300-500", ">500"))))) -> >200-300 | CH30: =IFERROR(_xlfn.XLOOKUP(CG30,Scenario!M:M,Scenario!N:N),"") -> C | CI30: =IF(BI30="", IF(BA30>=1, "Yes", "No")) -> FALSE | CJ30: 427.24
A31: 30 | B31: 2023 | C31: PBTMTR200 | D31: 0015g00001UBHltAAH | E31: M/S TARUN TRADERS | F31: UTTARAKHAND | G31: DEHRADUN | H31: Dehradun | I31: SHIVA SALES INDIA CORPORATION | J31: Ravi Kumar | K31: - | L31: C12821 | M31: North | N31: 248003 | O31: 05ANLPS6308R1Z7 | P31: 9412054577 | Q31: Dec'23 | R31: 2024 | S31: 135 | T31: 200 | U31: 0.053333333 | V31: Challenger | W31: 16 | X31: 71 | Y31: 32 | Z31: 16 | AA31: 22 | AB31: 31 | AC31: 49 | AD31: 40 | AE31: 40 | AF31: 20 | AG31: 9 | AH31: 17 | AI31: 15 | AJ31: 41 | AK31: 45 | AL31: 30 | AM31: 57 | AN31: 0 | AO31: 0 | AP31: 0 | AQ31: 0 | AR31: 0 | AS31: 0 | AT31: 0 | AU31: 10 | AV31: 22 | AW31: =SUM(AL31:AU31) -> 97 | AX31: 214 | AY31: 301 | AZ31: =SUM(Z31:AK31) -> 345 | BB31: =BA31-AW31 -> -97 | BC31: =IFERROR(BB31/4,0) -> -24.25 | BD31: =AY31-AZ31 -> -44 | BE31: =AZ31-AW31 -> 248 | BF31: No | BG31: =AVERAGE(AL31:AS31) -> 10.875 | BH31: Yes | BI31: =IF(BF31="Yes","",IF(BA31>1250,"E",IF(BA31>750,"D", IF(BA31>=500,"C", IF(BA31>=300,"B", IF(BA31>=200,"A", "")))))) | BJ31: =IF(BF31="Yes","",IF(AY31>1250,"E",IF(AY31>750,"D", IF(AY31>=500,"C", IF(AY31>=300,"B", IF(AY31>=200,"A", "")))))) -> B | BK31: =SUM(AR31:AX31) -> 343 | BL31: =SUM(AL31:AQ31) -> 87 | BM31: =IFERROR(BK31/$AY31,"") -> 1.1395349 | BN31: =IFERROR(BL31/$AY31,"") -> 0.28903654 | BO31: =SUM(AL31:AS31) -> 87 | BP31: =IF(BF31="Yes","",IF(BO31>1250,"E",IF(BO31>750,"D", IF(BO31>=500,"C", IF(BO31>=300,"B", IF(BO31>=200,"A", "")))))) | BR31: =SUM(Z31:AE31) -> 198 | BS31: =SUM(AF31:AK31) -> 147 | BT31: =SUM(BR31:BS31) -> 345 | BU31: =IFERROR(_xlfn.XLOOKUP(D31,Sheet1!B:B,Sheet1!L:L),"") -> 0 | BV31: =_xlfn.XLOOKUP(BU31,Sheet1!S:S,Sheet1!T:T) -> #N/A | BW31: =_xlfn.XLOOKUP(D31,Sheet1!B:B,Sheet1!M:M) -> 0 | BX31: New | BY31: 301 | BZ31: =AY31-AW31 -> 204 | CB31: =AW31/AY31 -> 0.32225914 | CC31: =AX31/AY31 -> 0.71096346 | CG31: =IF(BO31<80,"Below 80", IF(BO31<=120,"80-120", IF(BO31<=200,"> 120-200", IF(BO31<=300,">200-300", IF(BO31<=500,">300-500", ">500"))))) -> 80-120 | CH31: =IFERROR(_xlfn.XLOOKUP(CG31,Scenario!M:M,Scenario!N:N),"") -> A | CI31: =IF(BI31="", IF(BA31>=1, "Yes", "No")) -> No | CJ31: 214
A32: 31 | B32: 2023 | C32: PBTMTR109 | D32: 0015g00001UBHaiAAH | E32: SHARMA STEELS AND PIPES | F32: HARYANA | G32: REWARI | H32: Rewari | I32: NIKUNJ UDYOG | J32: Shiv Shankar Sharma | K32: Shiv Shankar Sharma | L32: C12828 | M32: North | N32: 123106 | O32: 06ACBPS4043G1ZT | P32: 9812024665 | Q32: Dec'23 | R32: 2024 | S32: 66 | T32: 450 | U32: 0.065866667 | V32: Alien | W32: 0 | X32: 22 | Y32: 24 | Z32: 26 | AA32: 23.14 | AB32: 32 | AC32: 23.11 | AD32: 20 | AE32: 139.5 | AF32: 230.84 | AG32: 109 | AH32: 115 | AI32: 125 | AJ32: 159 | AK32: 296 | AL32: 204 | AM32: 122 | AN32: 101 | AO32: 103.36 | AP32: 52.36 | AQ32: 34.12 | AR32: 102.24 | AS32: 125.94 | AT32: 20.03 | AU32: 36 | AV32: 32.89 | AW32: =SUM(AL32:AU32) -> 901.05 | AX32: 680.92 | AY32: =BW32 -> 1400 | AZ32: =SUM(Z32:AK32) -> 1298.59 | BA32: 1300 | BB32: =BA32-AW32 -> 398.95 | BC32: =IFERROR(BB32/4,0) -> 99.7375 | BD32: =AY32-AZ32 -> 101.41 | BE32: =AZ32-AW32 -> 397.54 | BF32: No | BG32: =AVERAGE(AL32:AS32) -> 105.6275 | BH32: Yes | BI32: =IF(BF32="Yes","",IF(BA32>1250,"E",IF(BA32>750,"D", IF(BA32>=500,"C", IF(BA32>=300,"B", IF(BA32>=200,"A", "")))))) -> E | BJ32: =IF(BF32="Yes","",IF(AY32>1250,"E",IF(AY32>750,"D", IF(AY32>=500,"C", IF(AY32>=300,"B", IF(AY32>=200,"A", "")))))) -> E | BK32: =SUM(AR32:AX32) -> 1899.07 | BL32: =SUM(AL32:AQ32) -> 616.84 | BM32: =IFERROR(BK32/$AY32,"") -> 1.3564786 | BN32: =IFERROR(BL32/$AY32,"") -> 0.4406 | BO32: =SUM(AL32:AS32) -> 845.02 | BP32: =IF(BF32="Yes","",IF(BO32>1250,"E",IF(BO32>750,"D", IF(BO32>=500,"C", IF(BO32>=300,"B", IF(BO32>=200,"A", "")))))) -> D | BQ32: Dealer wants to go for domestic tour despite qualifying for International tour; Is also okay for CN | BR32: =SUM(Z32:AE32) -> 263.75 | BS32: =SUM(AF32:AK32) -> 1034.84 | BT32: =SUM(BR32:BS32) -> 1298.59 | BU32: =IFERROR(_xlfn.XLOOKUP(D32,Sheet1!B:B,Sheet1!L:L),"") -> Luxury International Trip (2 pax Dubai) 3N-4D | BV32: =_xlfn.XLOOKUP(BU32,Sheet1!S:S,Sheet1!T:T) -> E | BW32: =_xlfn.XLOOKUP(D32,Sheet1!B:B,Sheet1!M:M) -> 1400 | BX32: Qualified in Tour Scheme FY25 | BZ32: =AY32-AW32 -> 498.95 | CB32: =AW32/AY32 -> 0.64360714 | CC32: =AX32/AY32 -> 0.48637143 | CG32: =IF(BO32<80,"Below 80", IF(BO32<=120,"80-120", IF(BO32<=200,"> 120-200", IF(BO32<=300,">200-300", IF(BO32<=500,">300-500", ">500"))))) -> >500 | CH32: =IFERROR(_xlfn.XLOOKUP(CG32,Scenario!M:M,Scenario!N:N),"") -> E | CI32: =IF(BI32="", IF(BA32>=1, "Yes", "No")) -> FALSE | CJ32: 554.98
A33: 32 | B33: 2023 | C33: PBTMTR110 | D33: 0015g00001UBHaFAAX | E33: DELHI STEEL & CEMENT | F33: HARYANA | G33: GURUGRAM | H33: Gurugram | I33: NIKUNJ UDYOG | J33: Shiv Shankar Sharma | K33: Shiv Shankar Sharma | L33: C12828 | M33: North | N33: 122001 | O33: 06AAEPK2761J1ZQ | P33: 9810137969 | Q33: Dec'23 | R33: 2024 | S33: 50 | T33: 500 | U33: 0.055753333 | V33: Alien | W33: 0 | X33: 0 | Y33: 20 | Z33: 12 | AA33: 14.98 | AB33: 24 | AC33: 26.02 | AD33: 25 | AE33: 40.5 | AF33: 55.79 | AG33: 52 | AH33: 59.7 | AI33: 51 | AJ33: 58 | AK33: 83 | AL33: 9 | AM33: 51 | AN33: 50 | AO33: 45.95 | AP33: 60.4 | AQ33: 35.31 | AR33: 25.76 | AS33: 42.78 | AT33: 20.49 | AU33: 12 | AV33: 51.14 | AW33: =SUM(AL33:AU33) -> 352.69 | AX33: 222.58 | AY33: =BW33 -> 500 | AZ33: =SUM(Z33:AK33) -> 501.99 | BA33: 500 | BB33: =BA33-AW33 -> 147.31 | BC33: =IFERROR(BB33/4,0) -> 36.8275 | BD33: =AY33-AZ33 -> -1.99 | BE33: =AZ33-AW33 -> 149.3 | BF33: No | BG33: =AVERAGE(AL33:AS33) -> 40.025 | BH33: Yes | BI33: =IF(BF33="Yes","",IF(BA33>1250,"E",IF(BA33>750,"D", IF(BA33>=500,"C", IF(BA33>=300,"B", IF(BA33>=200,"A", "")))))) -> C | BJ33: =IF(BF33="Yes","",IF(AY33>1250,"E",IF(AY33>750,"D", IF(AY33>=500,"C", IF(AY33>=300,"B", IF(AY33>=200,"A", "")))))) -> C | BK33: =SUM(AR33:AX33) -> 727.44 | BL33: =SUM(AL33:AQ33) -> 251.66 | BM33: =IFERROR(BK33/$AY33,"") -> 1.45488 | BN33: =IFERROR(BL33/$AY33,"") -> 0.50332 | BO33: =SUM(AL33:AS33) -> 320.2 | BP33: =IF(BF33="Yes","",IF(BO33>1250,"E",IF(BO33>750,"D", IF(BO33>=500,"C", IF(BO33>=300,"B", IF(BO33>=200,"A", "")))))) -> B | BQ33: Multi-brand [Kamdhenu, Panther, Rathi, JSW One] dealer, dia. difference is an issue | BR33: =SUM(Z33:AE33) -> 142.5 | BS33: =SUM(AF33:AK33) -> 359.49 | BT33: =SUM(BR33:BS33) -> 501.99 | BU33: =IFERROR(_xlfn.XLOOKUP(D33,Sheet1!B:B,Sheet1!L:L),"") -> International trip (1 pax Almaty) 3N-4D | BV33: =_xlfn.XLOOKUP(BU33,Sheet1!S:S,Sheet1!T:T) -> #N/A | BW33: =_xlfn.XLOOKUP(D33,Sheet1!B:B,Sheet1!M:M) -> 500 | BX33: Qualified in Tour Scheme FY25 | BY33: 501 | BZ33: =AY33-AW33 -> 147.31 | CB33: =AW33/AY33 -> 0.70538 | CC33: =AX33/AY33 -> 0.44516 | CG33: =IF(BO33<80,"Below 80", IF(BO33<=120,"80-120", IF(BO33<=200,"> 120-200", IF(BO33<=300,">200-300", IF(BO33<=500,">300-500", ">500"))))) -> >300-500 | CH33: =IFERROR(_xlfn.XLOOKUP(CG33,Scenario!M:M,Scenario!N:N),"") -> D | CI33: =IF(BI33="", IF(BA33>=1, "Yes", "No")) -> FALSE | CJ33: 179.8
A34: 33 | B34: 2023 | C34: PBTMTR111 | D34: 0015g00001V9NnOAAV | E34: BHARAT STEEL | F34: HARYANA | G34: PALWAL | H34: Ballabgarh | I34: NIKUNJ UDYOG | J34: Rahul Chauhan | K34: Shiv Shankar Sharma | L34: C12828 | M34: North | N34: 121004 | O34: 06ANYPK6930C1ZR | P34: 9810802551 | Q34: Dec'23 | R34: 2024 | S34: 11 | T34: 150 | U34: 0 | V34: Challenger | W34: 0 | X34: 0 | Y34: 0 | Z34: 0 | AA34: 0 | AB34: 0 | AC34: 0 | AD34: 0 | AE34: 0 | AF34: 0 | AG34: 0 | AH34: 0 | AI34: 0 | AJ34: 0 | AK34: 0 | AL34: 0 | AM34: 0 | AN34: 0 | AO34: 0 | AP34: 0 | AQ34: 0 | AR34: 0 | AS34: 0 | AT34: 0 | AU34: 0 | AV34: 0 | AW34: =SUM(AL34:AU34) -> 0 | AX34: 0 | AY34: =AW34+AX34 -> 0 | AZ34: =SUM(Z34:AK34) -> 0 | BA34: 0 | BB34: =BA34-AW34 -> 0 | BC34: =IFERROR(BB34/4,0) -> 0 | BD34: =AY34-AZ34 -> 0 | BE34: =AZ34-AW34 -> 0 | BF34: No | BG34: =AVERAGE(AL34:AS34) -> 0 | BH34: Yes | BI34: =IF(BF34="Yes","",IF(BA34>1250,"E",IF(BA34>750,"D", IF(BA34>=500,"C", IF(BA34>=300,"B", IF(BA34>=200,"A", "")))))) | BJ34: =IF(BF34="Yes","",IF(AY34>1250,"E",IF(AY34>750,"D", IF(AY34>=500,"C", IF(AY34>=300,"B", IF(AY34>=200,"A", "")))))) | BK34: =SUM(AR34:AX34) -> 0 | BL34: =SUM(AL34:AQ34) -> 0 | BM34: =IFERROR(BK34/$AY34,"") | BN34: =IFERROR(BL34/$AY34,"") | BO34: =SUM(AL34:AS34) -> 0 | BP34: =IF(BF34="Yes","",IF(BO34>1250,"E",IF(BO34>750,"D", IF(BO34>=500,"C", IF(BO34>=300,"B", IF(BO34>=200,"A", "")))))) | BR34: =SUM(Z34:AE34) -> 0 | BS34: =SUM(AF34:AK34) -> 0 | BT34: =SUM(BR34:BS34) -> 0 | BU34: =IFERROR(_xlfn.XLOOKUP(D34,Sheet1!B:B,Sheet1!L:L),"") | BV34: =_xlfn.XLOOKUP(BU34,Sheet1!S:S,Sheet1!T:T) -> #N/A | BW34: =_xlfn.XLOOKUP(D34,Sheet1!B:B,Sheet1!M:M) -> #N/A | BZ34: =AY34-AW34 -> 0 | CG34: =IF(BO34<80,"Below 80", IF(BO34<=120,"80-120", IF(BO34<=200,"> 120-200", IF(BO34<=300,">200-300", IF(BO34<=500,">300-500", ">500"))))) -> Below 80 | CH34: =IFERROR(_xlfn.XLOOKUP(CG34,Scenario!M:M,Scenario!N:N),"") | CI34: =IF(BI34="", IF(BA34>=1, "Yes", "No")) -> No | CJ34: 0
A35: 34 | B35: 2023 | C35: PBTMTR112 | D35: 0015g00001cZty1AAC | E35: BHARDWAJ STEELS | F35: HARYANA | G35: PALWAL | H35: Ballabgarh | I35: NIKUNJ UDYOG | J35: Rahul Chauhan | K35: Shiv Shankar Sharma | L35: C12828 | M35: North | N35: 121004 | O35: 06BOSPS4571K1Z4 | P35: 9999371931 | Q35: Dec'23 | R35: 2024 | S35: 101 | T35: 300 | U35: 0 | V35: Alien | W35: 21 | X35: 27 | Y35: 35 | Z35: 10 | AA35: 12.15 | AB35: 33 | AC35: 0 | AD35: 0 | AE35: 52 | AF35: 0 | AG35: 45 | AH35: 12 | AI35: 45 | AJ35: 12 | AK35: 0 | AL35: 0 | AM35: 23 | AN35: 0 | AO35: 0 | AP35: 3.39 | AQ35: 0 | AR35: 0 | AS35: 0 | AT35: 0 | AU35: 0 | AV35: 0 | AW35: =SUM(AL35:AU35) -> 26.39 | AX35: 52.78 | AY35: =AW35+AX35 -> 79.17 | AZ35: =SUM(Z35:AK35) -> 221.15 | BA35: 26 | BB35: =BA35-AW35 -> -0.39 | BC35: =IFERROR(BB35/4,0) -> -0.0975 | BD35: =AY35-AZ35 -> -141.98 | BE35: =AZ35-AW35 -> 194.76 | BF35: No | BG35: =AVERAGE(AL35:AS35) -> 3.29875 | BH35: Yes | BI35: =IF(BF35="Yes","",IF(BA35>1250,"E",IF(BA35>750,"D", IF(BA35>=500,"C", IF(BA35>=300,"B", IF(BA35>=200,"A", "")))))) | BJ35: =IF(BF35="Yes","",IF(AY35>1250,"E",IF(AY35>750,"D", IF(AY35>=500,"C", IF(AY35>=300,"B", IF(AY35>=200,"A", "")))))) | BK35: =SUM(AR35:AX35) -> 79.17 | BL35: =SUM(AL35:AQ35) -> 26.39 | BM35: =IFERROR(BK35/$AY35,"") -> 1 | BN35: =IFERROR(BL35/$AY35,"") -> 0.33333333 | BO35: =SUM(AL35:AS35) -> 26.39 | BP35: =IF(BF35="Yes","",IF(BO35>1250,"E",IF(BO35>750,"D", IF(BO35>=500,"C", IF(BO35>=300,"B", IF(BO35>=200,"A", "")))))) | BQ35: Credit issue - will not work until that is resolved. Works with other Durgapur brands | BR35: =SUM(Z35:AE35) -> 107.15 | BS35: =SUM(AF35:AK35) -> 114 | BT35: =SUM(BR35:BS35) -> 221.15 | BU35: =IFERROR(_xlfn.XLOOKUP(D35,Sheet1!B:B,Sheet1!L:L),"") | BV35: =_xlfn.XLOOKUP(BU35,Sheet1!S:S,Sheet1!T:T) -> #N/A | BW35: =_xlfn.XLOOKUP(D35,Sheet1!B:B,Sheet1!M:M) -> #N/A | BZ35: =AY35-AW35 -> 52.78 | CB35: =AW35/AY35 -> 0.33333333 | CC35: =AX35/AY35 -> 0.66666667 | CG35: =IF(BO35<80,"Below 80", IF(BO35<=120,"80-120", IF(BO35<=200,"> 120-200", IF(BO35<=300,">200-300", IF(BO35<=500,">300-500", ">500"))))) -> Below 80 | CH35: =IFERROR(_xlfn.XLOOKUP(CG35,Scenario!M:M,Scenario!N:N),"") | CI35: =IF(BI35="", IF(BA35>=1, "Yes", "No")) -> Yes | CJ35: 52.78 | CK35: Yes
A36: 35 | B36: 2023 | C36: PBTMTR113 | D36: 0015g00001UBHadAAH | E36: KAKKAR TRADING CO. | F36: HARYANA | G36: FARIDABAD | H36: Faridabad | I36: NIKUNJ UDYOG | J36: Rahul Chauhan | K36: Shiv Shankar Sharma | L36: C12828 | M36: North | N36: 121008 | O36: 06ABGPK3198N1Z5 | P36: 9313900248 | Q36: Dec'23 | R36: 2024 | S36: 10 | T36: 400 | U36: 0 | V36: Alien | W36: 0 | X36: 0 | Y36: 0 | Z36: 0 | AA36: 0 | AB36: 0 | AC36: 0 | AD36: 0 | AE36: 0 | AF36: 0 | AG36: 0 | AH36: 0 | AI36: 0 | AJ36: 0 | AK36: 0 | AL36: 0 | AM36: 0 | AN36: 0 | AO36: 0 | AP36: 0 | AQ36: 0 | AR36: 0 | AS36: 0 | AT36: 0 | AU36: 0 | AV36: 0 | AW36: =SUM(AL36:AU36) -> 0 | AX36: 0 | AY36: =AW36+AX36 -> 0 | AZ36: =SUM(Z36:AK36) -> 0 | BA36: 0 | BB36: =BA36-AW36 -> 0 | BC36: =IFERROR(BB36/4,0) -> 0 | BD36: =AY36-AZ36 -> 0 | BE36: =AZ36-AW36 -> 0 | BF36: No | BG36: =AVERAGE(AL36:AS36) -> 0 | BH36: Yes | BI36: =IF(BF36="Yes","",IF(BA36>1250,"E",IF(BA36>750,"D", IF(BA36>=500,"C", IF(BA36>=300,"B", IF(BA36>=200,"A", "")))))) | BJ36: =IF(BF36="Yes","",IF(AY36>1250,"E",IF(AY36>750,"D", IF(AY36>=500,"C", IF(AY36>=300,"B", IF(AY36>=200,"A", "")))))) | BK36: =SUM(AR36:AX36) -> 0 | BL36: =SUM(AL36:AQ36) -> 0 | BM36: =IFERROR(BK36/$AY36,"") | BN36: =IFERROR(BL36/$AY36,"") | BO36: =SUM(AL36:AS36) -> 0 | BP36: =IF(BF36="Yes","",IF(BO36>1250,"E",IF(BO36>750,"D", IF(BO36>=500,"C", IF(BO36>=300,"B", IF(BO36>=200,"A", "")))))) | BR36: =SUM(Z36:AE36) -> 0 | BS36: =SUM(AF36:AK36) -> 0 | BT36: =SUM(BR36:BS36) -> 0 | BU36: =IFERROR(_xlfn.XLOOKUP(D36,Sheet1!B:B,Sheet1!L:L),"") | BV36: =_xlfn.XLOOKUP(BU36,Sheet1!S:S,Sheet1!T:T) -> #N/A | BW36: =_xlfn.XLOOKUP(D36,Sheet1!B:B,Sheet1!M:M) -> #N/A | BZ36: =AY36-AW36 -> 0 | CG36: =IF(BO36<80,"Below 80", IF(BO36<=120,"80-120", IF(BO36<=200,"> 120-200", IF(BO36<=300,">200-300", IF(BO36<=500,">300-500", ">500"))))) -> Below 80 | CH36: =IFERROR(_xlfn.XLOOKUP(CG36,Scenario!M:M,Scenario!N:N),"") | CI36: =IF(BI36="", IF(BA36>=1, "Yes", "No")) -> No | CJ36: 0
A37: 36 | B37: 2023 | C37: PBTMTR114 | D37: 0015g00001UBHjbAAH | E37: Yadav Iron Store | F37: HARYANA | G37: REWARI | H37: Rewari | I37: NIKUNJ UDYOG | J37: Shiv Shankar Sharma | K37: Shiv Shankar Sharma | L37: C12828 | M37: North | N37: 123401 | O37: 06ANBPK0034AZZ | P37: 9999614635 | Q37: Dec'23 | R37: 2024 | S37: 101 | T37: 650 | U37: 0.15468718 | V37: Super Star | W37: 15 | X37: 24 | Y37: 50 | Z37: 30 | AA37: 15.23 | AB37: 12 | AC37: 0 | AD37: 12 | AE37: 18 | AF37: 27 | AG37: 10 | AH37: 52.5 | AI37: 63 | AJ37: 42 | AK37: 90 | AL37: 50 | AM37: 50 | AN37: 71 | AO37: 30.02 | AP37: 126.62 | AQ37: 13.98 | AR37: 28.01 | AS37: 15.12 | AT37: 54 | AU37: 99 | AV37: 148.64 | AW37: =SUM(AL37:AU37) -> 537.75 | AX37: 381.37 | AY37: 751 | AZ37: =SUM(Z37:AK37) -> 371.73 | BA37: 600 | BB37: =BA37-AW37 -> 62.25 | BC37: =IFERROR(BB37/4,0) -> 15.5625 | BD37: =AY37-AZ37 -> 379.27 | BE37: =AZ37-AW37 -> -166.02 | BF37: No | BG37: =AVERAGE(AL37:AS37) -> 48.09375 | BH37: Yes | BI37: =IF(BF37="Yes","",IF(BA37>1250,"E",IF(BA37>750,"D", IF(BA37>=500,"C", IF(BA37>=300,"B", IF(BA37>=200,"A", "")))))) -> C | BJ37: =IF(BF37="Yes","",IF(AY37>1250,"E",IF(AY37>750,"D", IF(AY37>=500,"C", IF(AY37>=300,"B", IF(AY37>=200,"A", "")))))) -> D | BK37: =SUM(AR37:AX37) -> 1263.89 | BL37: =SUM(AL37:AQ37) -> 341.62 | BM37: =IFERROR(BK37/$AY37,"") -> 1.6829427 | BN37: =IFERROR(BL37/$AY37,"") -> 0.45488682 | BO37: =SUM(AL37:AS37) -> 384.75 | BP37: =IF(BF37="Yes","",IF(BO37>1250,"E",IF(BO37>750,"D", IF(BO37>=500,"C", IF(BO37>=300,"B", IF(BO37>=200,"A", "")))))) -> B | BR37: =SUM(Z37:AE37) -> 87.23 | BS37: =SUM(AF37:AK37) -> 284.5 | BT37: =SUM(BR37:BS37) -> 371.73 | BU37: =IFERROR(_xlfn.XLOOKUP(D37,Sheet1!B:B,Sheet1!L:L),"") -> International trip (1 pax Almaty) 3N-4D | BV37: =_xlfn.XLOOKUP(BU37,Sheet1!S:S,Sheet1!T:T) -> #N/A | BW37: =_xlfn.XLOOKUP(D37,Sheet1!B:B,Sheet1!M:M) -> 600 | BX37: Qualified in Tour Scheme FY25 | BY37: 751 | BZ37: =AY37-AW37 -> 213.25 | CB37: =AW37/AY37 -> 0.71604527 | CC37: =AX37/AY37 -> 0.50781625 | CG37: =IF(BO37<80,"Below 80", IF(BO37<=120,"80-120", IF(BO37<=200,"> 120-200", IF(BO37<=300,">200-300", IF(BO37<=500,">300-500", ">500"))))) -> >300-500 | CH37: =IFERROR(_xlfn.XLOOKUP(CG37,Scenario!M:M,Scenario!N:N),"") -> D | CI37: =IF(BI37="", IF(BA37>=1, "Yes", "No")) -> FALSE | CJ37: 366.25
A38: 37 | B38: 2023 | C38: PBTMTR115 | D38: 0015g00001UBHaHAAX | E38: SUDHIR STEEL AND CEMENT | F38: HARYANA | G38: GURUGRAM | H38: Gurugram | I38: NIKUNJ UDYOG | J38: Shiv Shankar Sharma | K38: Shiv Shankar Sharma | L38: C12828 | M38: North | N38: 122001 | O38: 0 | P38: 0 | Q38: Dec'23 | R38: 2024 | S38: 54 | T38: 300 | U38: 0 | V38: Alien | W38: 0 | X38: 0 | Y38: 42 | Z38: 0 | AA38: 30.21 | AB38: 0 | AC38: 0 | AD38: 0 | AE38: 0 | AF38: 15 | AG38: 0 | AH38: 0 | AI38: 0 | AJ38: 65.7 | AK38: 27 | AL38: 11 | AM38: 0 | AN38: 0 | AO38: 0 | AP38: 0 | AQ38: 0 | AR38: 0 | AS38: 0 | AT38: 0 | AU38: 0 | AV38: 0 | AW38: =SUM(AL38:AU38) -> 11 | AX38: 22 | AY38: =AW38+AX38 -> 33 | AZ38: =SUM(Z38:AK38) -> 137.91 | BA38: 50 | BB38: =BA38-AW38 -> 39 | BC38: =IFERROR(BB38/4,0) -> 9.75 | BD38: =AY38-AZ38 -> -104.91 | BE38: =AZ38-AW38 -> 126.91 | BF38: No | BG38: =AVERAGE(AL38:AS38) -> 1.375 | BH38: Yes | BI38: =IF(BF38="Yes","",IF(BA38>1250,"E",IF(BA38>750,"D", IF(BA38>=500,"C", IF(BA38>=300,"B", IF(BA38>=200,"A", "")))))) | BJ38: =IF(BF38="Yes","",IF(AY38>1250,"E",IF(AY38>750,"D", IF(AY38>=500,"C", IF(AY38>=300,"B", IF(AY38>=200,"A", "")))))) | BK38: =SUM(AR38:AX38) -> 33 | BL38: =SUM(AL38:AQ38) -> 11 | BM38: =IFERROR(BK38/$AY38,"") -> 1 | BN38: =IFERROR(BL38/$AY38,"") -> 0.33333333 | BO38: =SUM(AL38:AS38) -> 11 | BP38: =IF(BF38="Yes","",IF(BO38>1250,"E",IF(BO38>750,"D", IF(BO38>=500,"C", IF(BO38>=300,"B", IF(BO38>=200,"A", "")))))) | BR38: =SUM(Z38:AE38) -> 30.21 | BS38: =SUM(AF38:AK38) -> 107.7 | BT38: =SUM(BR38:BS38) -> 137.91 | BU38: =IFERROR(_xlfn.XLOOKUP(D38,Sheet1!B:B,Sheet1!L:L),"") | BV38: =_xlfn.XLOOKUP(BU38,Sheet1!S:S,Sheet1!T:T) -> #N/A | BW38: =_xlfn.XLOOKUP(D38,Sheet1!B:B,Sheet1!M:M) -> #N/A | BZ38: =AY38-AW38 -> 22 | CB38: =AW38/AY38 -> 0.33333333 | CC38: =AX38/AY38 -> 0.66666667 | CG38: =IF(BO38<80,"Below 80", IF(BO38<=120,"80-120", IF(BO38<=200,"> 120-200", IF(BO38<=300,">200-300", IF(BO38<=500,">300-500", ">500"))))) -> Below 80 | CH38: =IFERROR(_xlfn.XLOOKUP(CG38,Scenario!M:M,Scenario!N:N),"") | CI38: =IF(BI38="", IF(BA38>=1, "Yes", "No")) -> Yes | CJ38: 22
A39: 38 | B39: 2023 | C39: PBTMTR116 | D39: 0015g00001UBHajAAH | E39: BHAGYA STEEL | F39: HARYANA | G39: FARIDABAD | H39: Faridabad | I39: NIKUNJ UDYOG | J39: Rahul Chauhan | K39: Shiv Shankar Sharma | L39: C12828 | M39: North | N39: 121002 | O39: 06BBRPK2883C1ZI | P39: 9870117803 | Q39: Dec'23 | R39: 2024 | S39: 12 | T39: 250 | U39: 0 | V39: Alien | W39: 0 | X39: 0 | Y39: 0 | Z39: 0 | AA39: 0 | AB39: 0 | AC39: 0 | AD39: 0 | AE39: 0 | AF39: 0 | AG39: 0 | AH39: 0 | AI39: 0 | AJ39: 0 | AK39: 0 | AL39: 0 | AM39: 0 | AN39: 0 | AO39: 0 | AP39: 0 | AQ39: 0 | AR39: 0 | AS39: 0 | AT39: 0 | AU39: 0 | AV39: 0 | AW39: =SUM(AL39:AU39) -> 0 | AX39: 0 | AY39: =AW39+AX39 -> 0 | AZ39: =SUM(Z39:AK39) -> 0 | BA39: 0 | BB39: =BA39-AW39 -> 0 | BC39: =IFERROR(BB39/4,0) -> 0 | BD39: =AY39-AZ39 -> 0 | BE39: =AZ39-AW39 -> 0 | BF39: No | BG39: =AVERAGE(AL39:AS39) -> 0 | BH39: Yes | BI39: =IF(BF39="Yes","",IF(BA39>1250,"E",IF(BA39>750,"D", IF(BA39>=500,"C", IF(BA39>=300,"B", IF(BA39>=200,"A", "")))))) | BJ39: =IF(BF39="Yes","",IF(AY39>1250,"E",IF(AY39>750,"D", IF(AY39>=500,"C", IF(AY39>=300,"B", IF(AY39>=200,"A", "")))))) | BK39: =SUM(AR39:AX39) -> 0 | BL39: =SUM(AL39:AQ39) -> 0 | BM39: =IFERROR(BK39/$AY39,"") | BN39: =IFERROR(BL39/$AY39,"") | BO39: =SUM(AL39:AS39) -> 0 | BP39: =IF(BF39="Yes","",IF(BO39>1250,"E",IF(BO39>750,"D", IF(BO39>=500,"C", IF(BO39>=300,"B", IF(BO39>=200,"A", "")))))) | BR39: =SUM(Z39:AE39) -> 0 | BS39: =SUM(AF39:AK39) -> 0 | BT39: =SUM(BR39:BS39) -> 0 | BU39: =IFERROR(_xlfn.XLOOKUP(D39,Sheet1!B:B,Sheet1!L:L),"") | BV39: =_xlfn.XLOOKUP(BU39,Sheet1!S:S,Sheet1!T:T) -> #N/A | BW39: =_xlfn.XLOOKUP(D39,Sheet1!B:B,Sheet1!M:M) -> #N/A | BZ39: =AY39-AW39 -> 0 | CG39: =IF(BO39<80,"Below 80", IF(BO39<=120,"80-120", IF(BO39<=200,"> 120-200", IF(BO39<=300,">200-300", IF(BO39<=500,">300-500", ">500"))))) -> Below 80 | CH39: =IFERROR(_xlfn.XLOOKUP(CG39,Scenario!M:M,Scenario!N:N),"") | CI39: =IF(BI39="", IF(BA39>=1, "Yes", "No")) -> No | CJ39: 0
A40: 39 | B40: 2023 | C40: PBTMTR117 | D40: 0015g00001UBHafAAH | E40: HARI DAYA TRADERS | F40: HARYANA | G40: GURUGRAM | H40: Gurugram | I40: NIKUNJ UDYOG | J40: Shiv Shankar Sharma | K40: Shiv Shankar Sharma | L40: C12828 | M40: North | N40: 122003 | O40: 06ATNPG0870C1ZZ | P40: 9971825952 | Q40: Dec'23 | R40: 2024 | S40: 52 | T40: 300 | U40: 0 | V40: Alien | W40: 0 | X40: 17 | Y40: 23 | Z40: 0 | AA40: 0 | AB40: 0 | AC40: 0 | AD40: 0 | AE40: 9.35 | AF40: 10 | AG40: 0 | AH40: 0 | AI40: 0 | AJ40: 0 | AK40: 0 | AL40: 0 | AM40: 10 | AN40: 0 | AO40: 0 | AP40: 0 | AQ40: 0 | AR40: 0 | AS40: 0 | AT40: 0 | AU40: 0 | AV40: 0 | AW40: =SUM(AL40:AU40) -> 10 | AX40: 20 | AY40: =AW40+AX40 -> 30 | AZ40: =SUM(Z40:AK40) -> 19.35 | BA40: 30 | BB40: =BA40-AW40 -> 20 | BC40: =IFERROR(BB40/4,0) -> 5 | BD40: =AY40-AZ40 -> 10.65 | BE40: =AZ40-AW40 -> 9.35 | BF40: No | BG40: =AVERAGE(AL40:AS40) -> 1.25 | BH40: Yes | BI40: =IF(BF40="Yes","",IF(BA40>1250,"E",IF(BA40>750,"D", IF(BA40>=500,"C", IF(BA40>=300,"B", IF(BA40>=200,"A", "")))))) | BJ40: =IF(BF40="Yes","",IF(AY40>1250,"E",IF(AY40>750,"D", IF(AY40>=500,"C", IF(AY40>=300,"B", IF(AY40>=200,"A", "")))))) | BK40: =SUM(AR40:AX40) -> 30 | BL40: =SUM(AL40:AQ40) -> 10 | BM40: =IFERROR(BK40/$AY40,"") -> 1 | BN40: =IFERROR(BL40/$AY40,"") -> 0.33333333 | BO40: =SUM(AL40:AS40) -> 10 | BP40: =IF(BF40="Yes","",IF(BO40>1250,"E",IF(BO40>750,"D", IF(BO40>=500,"C", IF(BO40>=300,"B", IF(BO40>=200,"A", "")))))) | BQ40: Rathi, Kamdhenu dealer; Specific project based requirement can arise | BR40: =SUM(Z40:AE40) -> 9.35 | BS40: =SUM(AF40:AK40) -> 10 | BT40: =SUM(BR40:BS40) -> 19.35 | BU40: =IFERROR(_xlfn.XLOOKUP(D40,Sheet1!B:B,Sheet1!L:L),"") | BV40: =_xlfn.XLOOKUP(BU40,Sheet1!S:S,Sheet1!T:T) -> #N/A | BW40: =_xlfn.XLOOKUP(D40,Sheet1!B:B,Sheet1!M:M) -> #N/A | BZ40: =AY40-AW40 -> 20 | CB40: =AW40/AY40 -> 0.33333333 | CC40: =AX40/AY40 -> 0.66666667 | CG40: =IF(BO40<80,"Below 80", IF(BO40<=120,"80-120", IF(BO40<=200,"> 120-200", IF(BO40<=300,">200-300", IF(BO40<=500,">300-500", ">500"))))) -> Below 80 | CH40: =IFERROR(_xlfn.XLOOKUP(CG40,Scenario!M:M,Scenario!N:N),"") | CI40: =IF(BI40="", IF(BA40>=1, "Yes", "No")) -> Yes | CJ40: 20
A41: 40 | B41: 2023 | C41: PBTMTR50 | D41: 001J100000RyDBkIAN | E41: BAHALGARH STEEL UDYOG | F41: HARYANA | G41: SONIPAT | H41: Sonipat | I41: JAI DURGA STEELS | J41: Sunny Bhutani | K41: Sunny Bhutani | L41: C12830 | M41: North | N41: 131021 | O41: 06AANFB3002A1ZA | P41: 8930049709 | Q41: Dec'23 | R41: 2024 | S41: 142 | T41: 200 | U41: 0.61173333 | V41: Star | W41: 15 | X41: 16 | Y41: 18 | Z41: 0 | AA41: 0 | AB41: 0 | AC41: 0 | AD41: 0 | AE41: 0 | AF41: 0 | AG41: 0 | AH41: 51 | AI41: 50 | AJ41: 0 | AK41: 0 | AL41: 55 | AM41: 51 | AN41: 52 | AO41: 64 | AP41: 51 | AQ41: 50.14 | AR41: 0 | AS41: 42.31 | AT41: 42.01 | AU41: 0 | AV41: 325.03 | AW41: =SUM(AL41:AU41) -> 407.46 | AX41: =AW41*2 -> 814.92 | AY41: =AW41+AX41 -> 1222.38 | AZ41: =SUM(Z41:AK41) -> 101 | BA41: 750 | BB41: =BA41-AW41 -> 342.54 | BC41: =IFERROR(BB41/4,0) -> 85.635 | BD41: =AY41-AZ41 -> 1121.38 | BE41: =AZ41-AW41 -> -306.46 | BF41: No | BG41: =AVERAGE(AL41:AS41) -> 45.68125 | BH41: Yes | BI41: =IF(BF41="Yes","",IF(BA41>1250,"E",IF(BA41>750,"D", IF(BA41>=500,"C", IF(BA41>=300,"B", IF(BA41>=200,"A", "")))))) -> C | BJ41: =IF(BF41="Yes","",IF(AY41>1250,"E",IF(AY41>750,"D", IF(AY41>=500,"C", IF(AY41>=300,"B", IF(AY41>=200,"A", "")))))) -> D | BK41: =SUM(AR41:AX41) -> 1631.73 | BL41: =SUM(AL41:AQ41) -> 323.14 | BM41: =IFERROR(BK41/$AY41,"") -> 1.3348795 | BN41: =IFERROR(BL41/$AY41,"") -> 0.26435315 | BO41: =SUM(AL41:AS41) -> 365.45 | BP41: =IF(BF41="Yes","",IF(BO41>1250,"E",IF(BO41>750,"D", IF(BO41>=500,"C", IF(BO41>=300,"B", IF(BO41>=200,"A", "")))))) -> B | BR41: =SUM(Z41:AE41) -> 0 | BS41: =SUM(AF41:AK41) -> 101 | BT41: =SUM(BR41:BS41) -> 101 | BU41: =IFERROR(_xlfn.XLOOKUP(D41,Sheet1!B:B,Sheet1!L:L),"") | BV41: =_xlfn.XLOOKUP(BU41,Sheet1!S:S,Sheet1!T:T) -> #N/A | BW41: =_xlfn.XLOOKUP(D41,Sheet1!B:B,Sheet1!M:M) -> #N/A | BX41: New | BZ41: =AY41-AW41 -> 814.92 | CB41: =AW41/AY41 -> 0.33333333 | CC41: =AX41/AY41 -> 0.66666667 | CG41: =IF(BO41<80,"Below 80", IF(BO41<=120,"80-120", IF(BO41<=200,"> 120-200", IF(BO41<=300,">200-300", IF(BO41<=500,">300-500", ">500"))))) -> >300-500 | CH41: =IFERROR(_xlfn.XLOOKUP(CG41,Scenario!M:M,Scenario!N:N),"") -> D | CI41: =IF(BI41="", IF(BA41>=1, "Yes", "No")) -> FALSE | CJ41: 688.59
A42: 41 | B42: 2023 | C42: PBTMTR51 | D42: 0015g00001VBDlGAAX | E42: SHREE KRISHNA BUILDERS | F42: HARYANA | G42: ROHTAK | H42: Rohtak | I42: JAI DURGA STEELS | J42: Sunny Bhutani | K42: Sunny Bhutani | L42: C12830 | M42: North | N42: 124001 | O42: 06AMZPN4800C1Z0 | P42: 9992307868 | Q42: Dec'23 | R42: 2024 | S42: 124 | T42: 90 | U42: 0 | V42: Challenger | W42: 36 | X42: 38 | Y42: 10 | Z42: 40 | AA42: 20 | AB42: 30 | AC42: 20 | AD42: 15 | AE42: 15 | AF42: 0 | AG42: 2 | AH42: 55 | AI42: 50 | AJ42: 185 | AK42: 70 | AL42: 0 | AM42: 0 | AN42: 0 | AO42: 0 | AP42: 0 | AQ42: 0 | AR42: 0 | AS42: 0 | AT42: 0 | AU42: 0 | AV42: 0 | AW42: =SUM(AL42:AU42) -> 0 | AX42: 0 | AY42: =AW42+AX42 -> 0 | AZ42: =SUM(Z42:AK42) -> 502 | BA42: 0 | BB42: =BA42-AW42 -> 0 | BC42: =IFERROR(BB42/4,0) -> 0 | BD42: =AY42-AZ42 -> -502 | BE42: =AZ42-AW42 -> 502 | BF42: No | BG42: =AVERAGE(AL42:AS42) -> 0 | BH42: Yes | BI42: =IF(BF42="Yes","",IF(BA42>1250,"E",IF(BA42>750,"D", IF(BA42>=500,"C", IF(BA42>=300,"B", IF(BA42>=200,"A", "")))))) | BJ42: =IF(BF42="Yes","",IF(AY42>1250,"E",IF(AY42>750,"D", IF(AY42>=500,"C", IF(AY42>=300,"B", IF(AY42>=200,"A", "")))))) | BK42: =SUM(AR42:AX42) -> 0 | BL42: =SUM(AL42:AQ42) -> 0 | BM42: =IFERROR(BK42/$AY42,"") | BN42: =IFERROR(BL42/$AY42,"") | BO42: =SUM(AL42:AS42) -> 0 | BP42: =IF(BF42="Yes","",IF(BO42>1250,"E",IF(BO42>750,"D", IF(BO42>=500,"C", IF(BO42>=300,"B", IF(BO42>=200,"A", "")))))) | BR42: =SUM(Z42:AE42) -> 140 | BS42: =SUM(AF42:AK42) -> 362 | BT42: =SUM(BR42:BS42) -> 502 | BU42: =IFERROR(_xlfn.XLOOKUP(D42,Sheet1!B:B,Sheet1!L:L),"") -> 0 | BV42: =_xlfn.XLOOKUP(BU42,Sheet1!S:S,Sheet1!T:T) -> #N/A | BW42: =_xlfn.XLOOKUP(D42,Sheet1!B:B,Sheet1!M:M) -> 0 | BZ42: =AY42-AW42 -> 0 | CG42: =IF(BO42<80,"Below 80", IF(BO42<=120,"80-120", IF(BO42<=200,"> 120-200", IF(BO42<=300,">200-300", IF(BO42<=500,">300-500", ">500"))))) -> Below 80 | CH42: =IFERROR(_xlfn.XLOOKUP(CG42,Scenario!M:M,Scenario!N:N),"") | CI42: =IF(BI42="", IF(BA42>=1, "Yes", "No")) -> No | CJ42: 0
A43: 42 | B43: 2023 | C43: PBTMTR52 | D43: 0015g00001V9TgnAAF | E43: GUPTA STEELS | F43: HARYANA | G43: SONIPAT | H43: Sonipat | I43: JAI DURGA STEELS | J43: Sunny Bhutani | K43: Sunny Bhutani | L43: C12830 | M43: North | N43: 131001 | O43: 06AAOPG0184F1ZW | P43: 9215541409 | Q43: Dec'23 | R43: 2024 | S43: 101 | T43: 400 | U43: 0 | V43: Alien | W43: 15 | X43: 16 | Y43: 30 | Z43: 0 | AA43: 0 | AB43: 0 | AC43: 0 | AD43: 0 | AE43: 0 | AF43: 0 | AG43: 0 | AH43: 0 | AI43: 0 | AJ43: 0 | AK43: 0 | AL43: 0 | AM43: 0 | AN43: 0 | AO43: 0 | AP43: 0 | AQ43: 0 | AR43: 0 | AS43: 0 | AT43: 0 | AU43: 0 | AV43: 0 | AW43: =SUM(AL43:AU43) -> 0 | AX43: 0 | AY43: =AW43+AX43 -> 0 | AZ43: =SUM(Z43:AK43) -> 0 | BA43: 0 | BB43: =BA43-AW43 -> 0 | BC43: =IFERROR(BB43/4,0) -> 0 | BD43: =AY43-AZ43 -> 0 | BE43: =AZ43-AW43 -> 0 | BF43: No | BG43: =AVERAGE(AL43:AS43) -> 0 | BH43: Yes | BI43: =IF(BF43="Yes","",IF(BA43>1250,"E",IF(BA43>750,"D", IF(BA43>=500,"C", IF(BA43>=300,"B", IF(BA43>=200,"A", "")))))) | BJ43: =IF(BF43="Yes","",IF(AY43>1250,"E",IF(AY43>750,"D", IF(AY43>=500,"C", IF(AY43>=300,"B", IF(AY43>=200,"A", "")))))) | BK43: =SUM(AR43:AX43) -> 0 | BL43: =SUM(AL43:AQ43) -> 0 | BM43: =IFERROR(BK43/$AY43,"") | BN43: =IFERROR(BL43/$AY43,"") | BO43: =SUM(AL43:AS43) -> 0 | BP43: =IF(BF43="Yes","",IF(BO43>1250,"E",IF(BO43>750,"D", IF(BO43>=500,"C", IF(BO43>=300,"B", IF(BO43>=200,"A", "")))))) | BR43: =SUM(Z43:AE43) -> 0 | BS43: =SUM(AF43:AK43) -> 0 | BT43: =SUM(BR43:BS43) -> 0 | BU43: =IFERROR(_xlfn.XLOOKUP(D43,Sheet1!B:B,Sheet1!L:L),"") | BV43: =_xlfn.XLOOKUP(BU43,Sheet1!S:S,Sheet1!T:T) -> #N/A | BW43: =_xlfn.XLOOKUP(D43,Sheet1!B:B,Sheet1!M:M) -> #N/A | BZ43: =AY43-AW43 -> 0 | CG43: =IF(BO43<80,"Below 80", IF(BO43<=120,"80-120", IF(BO43<=200,"> 120-200", IF(BO43<=300,">200-300", IF(BO43<=500,">300-500", ">500"))))) -> Below 80 | CH43: =IFERROR(_xlfn.XLOOKUP(CG43,Scenario!M:M,Scenario!N:N),"") | CI43: =IF(BI43="", IF(BA43>=1, "Yes", "No")) -> No | CJ43: 0
A44: 43 | B44: 2023 | C44: PBTMTR53 | D44: 0015g00001Xaxe2AAB | E44: MAA BHAWANI STEELS | F44: HARYANA | G44: PANIPAT | H44: Panipat | I44: JAI DURGA STEELS | J44: Sunny Bhutani | K44: Sunny Bhutani | L44: C12830 | M44: North | N44: 132103 | O44: 06AFEPD3322H1Z1 | P44: 9896327600 | Q44: Dec'23 | R44: 2024 | S44: 113 | T44: 165 | U44: 0 | V44: Challenger | W44: 20 | X44: 25 | Y44: 28 | Z44: 0 | AA44: 0 | AB44: 0 | AC44: 0 | AD44: 0 | AE44: 0 | AF44: 0 | AG44: 0 | AH44: 0 | AI44: 0 | AJ44: 0 | AK44: 0 | AL44: 0 | AM44: 0 | AN44: 0 | AO44: 0 | AP44: 0 | AQ44: 0 | AR44: 0 | AS44: 0 | AT44: 0 | AU44: 0 | AV44: 0 | AW44: =SUM(AL44:AU44) -> 0 | AX44: 0 | AY44: =AW44+AX44 -> 0 | AZ44: =SUM(Z44:AK44) -> 0 | BA44: 0 | BB44: =BA44-AW44 -> 0 | BC44: =IFERROR(BB44/4,0) -> 0 | BD44: =AY44-AZ44 -> 0 | BE44: =AZ44-AW44 -> 0 | BF44: No | BG44: =AVERAGE(AL44:AS44) -> 0 | BH44: Yes | BI44: =IF(BF44="Yes","",IF(BA44>1250,"E",IF(BA44>750,"D", IF(BA44>=500,"C", IF(BA44>=300,"B", IF(BA44>=200,"A", "")))))) | BJ44: =IF(BF44="Yes","",IF(AY44>1250,"E",IF(AY44>750,"D", IF(AY44>=500,"C", IF(AY44>=300,"B", IF(AY44>=200,"A", "")))))) | BK44: =SUM(AR44:AX44) -> 0 | BL44: =SUM(AL44:AQ44) -> 0 | BM44: =IFERROR(BK44/$AY44,"") | BN44: =IFERROR(BL44/$AY44,"") | BO44: =SUM(AL44:AS44) -> 0 | BP44: =IF(BF44="Yes","",IF(BO44>1250,"E",IF(BO44>750,"D", IF(BO44>=500,"C", IF(BO44>=300,"B", IF(BO44>=200,"A", "")))))) | BR44: =SUM(Z44:AE44) -> 0 | BS44: =SUM(AF44:AK44) -> 0 | BT44: =SUM(BR44:BS44) -> 0 | BU44: =IFERROR(_xlfn.XLOOKUP(D44,Sheet1!B:B,Sheet1!L:L),"") | BV44: =_xlfn.XLOOKUP(BU44,Sheet1!S:S,Sheet1!T:T) -> #N/A | BW44: =_xlfn.XLOOKUP(D44,Sheet1!B:B,Sheet1!M:M) -> #N/A | BZ44: =AY44-AW44 -> 0 | CG44: =IF(BO44<80,"Below 80", IF(BO44<=120,"80-120", IF(BO44<=200,"> 120-200", IF(BO44<=300,">200-300", IF(BO44<=500,">300-500", ">500"))))) -> Below 80 | CH44: =IFERROR(_xlfn.XLOOKUP(CG44,Scenario!M:M,Scenario!N:N),"") | CI44: =IF(BI44="", IF(BA44>=1, "Yes", "No")) -> No | CJ44: 0
A45: 44 | B45: 2023 | C45: PBTMTR54 | D45: 0015g00001V9Ti1AAF | E45: HARYANA IRON STORE | F45: HARYANA | G45: ROHTAK | H45: Meham | I45: JAI DURGA STEELS | J45: Sunny Bhutani | K45: Sunny Bhutani | L45: C12830 | M45: North | N45: 124112 | O45: 06AJBPK8502D1ZO | P45: 9416285792 | Q45: Dec'23 | R45: 2024 | S45: 111 | T45: 50 | U45: 0 | V45: Minor | W45: 20 | X45: 25 | Y45: 26 | Z45: 0 | AA45: 0 | AB45: 0 | AC45: 0 | AD45: 0 | AE45: 0 | AF45: 0 | AG45: 0 | AH45: 0 | AI45: 0 | AJ45: 0 | AK45: 0 | AL45: 0 | AM45: 0 | AN45: 0 | AO45: 0 | AP45: 0 | AQ45: 0 | AR45: 0 | AS45: 0 | AT45: 0 | AU45: 0 | AV45: 0 | AW45: =SUM(AL45:AU45) -> 0 | AX45: 0 | AY45: =AW45+AX45 -> 0 | AZ45: =SUM(Z45:AK45) -> 0 | BA45: 0 | BB45: =BA45-AW45 -> 0 | BC45: =IFERROR(BB45/4,0) -> 0 | BD45: =AY45-AZ45 -> 0 | BE45: =AZ45-AW45 -> 0 | BF45: No | BG45: =AVERAGE(AL45:AS45) -> 0 | BH45: Yes | BI45: =IF(BF45="Yes","",IF(BA45>1250,"E",IF(BA45>750,"D", IF(BA45>=500,"C", IF(BA45>=300,"B", IF(BA45>=200,"A", "")))))) | BJ45: =IF(BF45="Yes","",IF(AY45>1250,"E",IF(AY45>750,"D", IF(AY45>=500,"C", IF(AY45>=300,"B", IF(AY45>=200,"A", "")))))) | BK45: =SUM(AR45:AX45) -> 0 | BL45: =SUM(AL45:AQ45) -> 0 | BM45: =IFERROR(BK45/$AY45,"") | BN45: =IFERROR(BL45/$AY45,"") | BO45: =SUM(AL45:AS45) -> 0 | BP45: =IF(BF45="Yes","",IF(BO45>1250,"E",IF(BO45>750,"D", IF(BO45>=500,"C", IF(BO45>=300,"B", IF(BO45>=200,"A", "")))))) | BR45: =SUM(Z45:AE45) -> 0 | BS45: =SUM(AF45:AK45) -> 0 | BT45: =SUM(BR45:BS45) -> 0 | BU45: =IFERROR(_xlfn.XLOOKUP(D45,Sheet1!B:B,Sheet1!L:L),"") | BV45: =_xlfn.XLOOKUP(BU45,Sheet1!S:S,Sheet1!T:T) -> #N/A | BW45: =_xlfn.XLOOKUP(D45,Sheet1!B:B,Sheet1!M:M) -> #N/A | BZ45: =AY45-AW45 -> 0 | CG45: =IF(BO45<80,"Below 80", IF(BO45<=120,"80-120", IF(BO45<=200,"> 120-200", IF(BO45<=300,">200-300", IF(BO45<=500,">300-500", ">500"))))) -> Below 80 | CH45: =IFERROR(_xlfn.XLOOKUP(CG45,Scenario!M:M,Scenario!N:N),"") | CI45: =IF(BI45="", IF(BA45>=1, "Yes", "No")) -> No | CJ45: 0
A46: 45 | B46: 2023 | C46: PBTMTR55 | D46: 0015g00001cajQSAAY | E46: SHREE BALAJI IRON STORE | F46: HARYANA | G46: JHAJJAR | H46: Jhajjar | I46: JAI DURGA STEELS | J46: Sunny Bhutani | K46: Sunny Bhutani | L46: C12830 | M46: North | N46: 124103 | O46: 06AADHP2192M1ZW | P46: 9992021299 | Q46: Dec'23 | R46: 2024 | S46: 222 | T46: 120 | U46: 0.46402778 | V46: Star | W46: 30 | X46: 35 | Y46: 117 | Z46: 32 | AA46: 38 | AB46: 26 | AC46: 50 | AD46: 15 | AE46: 74 | AF46: 12 | AG46: 50 | AH46: 52 | AI46: 60 | AJ46: 50 | AK46: 51 | AL46: 51 | AM46: 53 | AN46: 51 | AO46: 121 | AP46: 78.24 | AQ46: 50.17 | AR46: 24.62 | AS46: 140.66 | AT46: 0 | AU46: 129 | AV46: 38.05 | AW46: =SUM(AL46:AU46) -> 698.69 | AX46: 821.97 | AY46: 1251 | AZ46: =SUM(Z46:AK46) -> 510 | BA46: 750 | BB46: =BA46-AW46 -> 51.31 | BC46: =IFERROR(BB46/4,0) -> 12.8275 | BD46: =AY46-AZ46 -> 741 | BE46: =AZ46-AW46 -> -188.69 | BF46: No | BG46: =AVERAGE(AL46:AS46) -> 71.21125 | BH46: Yes | BI46: =IF(BF46="Yes","",IF(BA46>1250,"E",IF(BA46>750,"D", IF(BA46>=500,"C", IF(BA46>=300,"B", IF(BA46>=200,"A", "")))))) -> C | BJ46: =IF(BF46="Yes","",IF(AY46>1250,"E",IF(AY46>750,"D", IF(AY46>=500,"C", IF(AY46>=300,"B", IF(AY46>=200,"A", "")))))) -> E | BK46: =SUM(AR46:AX46) -> 1852.99 | BL46: =SUM(AL46:AQ46) -> 404.41 | BM46: =IFERROR(BK46/$AY46,"") -> 1.481207 | BN46: =IFERROR(BL46/$AY46,"") -> 0.32326938 | BO46: =SUM(AL46:AS46) -> 569.69 | BP46: =IF(BF46="Yes","",IF(BO46>1250,"E",IF(BO46>750,"D", IF(BO46>=500,"C", IF(BO46>=300,"B", IF(BO46>=200,"A", "")))))) -> C | BQ46: 750 MT+ to be targeted | BR46: =SUM(Z46:AE46) -> 235 | BS46: =SUM(AF46:AK46) -> 275 | BT46: =SUM(BR46:BS46) -> 510 | BU46: Luxury International Trip (2 pax Dubai) 3N-4D | BV46: =_xlfn.XLOOKUP(BU46,Sheet1!S:S,Sheet1!T:T) -> E | BW46: =_xlfn.XLOOKUP(D46,Sheet1!B:B,Sheet1!M:M) -> #N/A | BX46: Qualified in Tour Scheme FY25 | BY46: 1251 | BZ46: =AY46-AW46 -> 552.31 | CB46: =AW46/AY46 -> 0.5585052 | CC46: =AX46/AY46 -> 0.65705036 | CD46: =AW46*1 -> 698.69 | CF46: =CD46+AW46 -> 1397.38 | CG46: =IF(BO46<80,"Below 80", IF(BO46<=120,"80-120", IF(BO46<=200,"> 120-200", IF(BO46<=300,">200-300", IF(BO46<=500,">300-500", ">500"))))) -> >500 | CH46: =IFERROR(_xlfn.XLOOKUP(CG46,Scenario!M:M,Scenario!N:N),"") -> E | CI46: =IF(BI46="", IF(BA46>=1, "Yes", "No")) -> FALSE | CJ46: 681.31
A47: 46 | B47: 2023 | C47: PBTMTR56 | D47: 0015g00001guqY4AAI | E47: SOHAN TRADING CO. | F47: HARYANA | G47: SONIPAT | H47: Gohana | I47: JAI DURGA STEELS | J47: Sunny Bhutani | K47: Sunny Bhutani | L47: C12830 | M47: North | N47: 131301 | O47: 06AGGPK9893B1Z6 | P47: 8168108460 | Q47: Dec'23 | R47: 2024 | S47: 180 | T47: 100 | U47: 1.1031667 | V47: Star | W47: 71 | X47: 10 | Y47: 12 | Z47: 36 | AA47: 18 | AB47: 72 | AC47: 0 | AD47: 35 | AE47: 0 | AF47: 0 | AG47: 50 | AH47: 60 | AI47: 80 | AJ47: 100 | AK47: 51 | AL47: 0 | AM47: 0 | AN47: 0 | AO47: 99 | AP47: 89.86 | AQ47: 53.36 | AR47: 58.6 | AS47: 85.36 | AT47: 131.8 | AU47: 117 | AV47: 82.15 | AW47: =SUM(AL47:AU47) -> 634.98 | AX47: 200.18 | AY47: 501 | AZ47: =SUM(Z47:AK47) -> 502 | BA47: 550 | BB47: =BA47-AW47 -> -84.98 | BC47: =IFERROR(BB47/4,0) -> -21.245 | BD47: =AY47-AZ47 -> -1 | BE47: =AZ47-AW47 -> -132.98 | BF47: No | BG47: =AVERAGE(AL47:AS47) -> 48.2725 | BH47: Yes | BI47: =IF(BF47="Yes","",IF(BA47>1250,"E",IF(BA47>750,"D", IF(BA47>=500,"C", IF(BA47>=300,"B", IF(BA47>=200,"A", "")))))) -> C | BJ47: =IF(BF47="Yes","",IF(AY47>1250,"E",IF(AY47>750,"D", IF(AY47>=500,"C", IF(AY47>=300,"B", IF(AY47>=200,"A", "")))))) -> C | BK47: =SUM(AR47:AX47) -> 1310.07 | BL47: =SUM(AL47:AQ47) -> 242.22 | BM47: =IFERROR(BK47/$AY47,"") -> 2.6149102 | BN47: =IFERROR(BL47/$AY47,"") -> 0.48347305 | BO47: =SUM(AL47:AS47) -> 386.18 | BP47: =IF(BF47="Yes","",IF(BO47>1250,"E",IF(BO47>750,"D", IF(BO47>=500,"C", IF(BO47>=300,"B", IF(BO47>=200,"A", "")))))) -> B | BR47: =SUM(Z47:AE47) -> 161 | BS47: =SUM(AF47:AK47) -> 341 | BT47: =SUM(BR47:BS47) -> 502 | BU47: International trip (1 pax Almaty) 3N-4D | BV47: =_xlfn.XLOOKUP(BU47,Sheet1!S:S,Sheet1!T:T) -> #N/A | BW47: =_xlfn.XLOOKUP(D47,Sheet1!B:B,Sheet1!M:M) -> #N/A | BX47: Qualified in Tour Scheme FY25 | BY47: 501 | BZ47: =AY47-AW47 -> -133.98 | CB47: =AW47/AY47 -> 1.2674251 | CC47: =AX47/AY47 -> 0.39956088 | CG47: =IF(BO47<80,"Below 80", IF(BO47<=120,"80-120", IF(BO47<=200,"> 120-200", IF(BO47<=300,">200-300", IF(BO47<=500,">300-500", ">500"))))) -> >300-500 | CH47: =IFERROR(_xlfn.XLOOKUP(CG47,Scenario!M:M,Scenario!N:N),"") -> D | CI47: =IF(BI47="", IF(BA47>=1, "Yes", "No")) -> FALSE | CJ47: 114.82
A48: 47 | B48: 2023 | C48: PBTMTR57 | D48: 0015g00001V9ThzAAF | E48: KADIAN TRADING CO. | F48: HARYANA | G48: ROHTAK | H48: Kalanaur | I48: JAI DURGA STEELS | J48: Sunny Bhutani | K48: Sunny Bhutani | L48: C12830 | M48: North | N48: 124113 | O48: 06AOCPK1768D1Z7 | P48: 9416179188 | Q48: Dec'23 | R48: 2024 | S48: 101 | T48: 100 | U48: 0 | V48: Challenger | W48: 12 | X48: 35 | Y48: 14 | Z48: 0 | AA48: 0 | AB48: 0 | AC48: 0 | AD48: 0 | AE48: 0 | AF48: 0 | AG48: 0 | AH48: 0 | AI48: 0 | AJ48: 0 | AK48: 0 | AL48: 0 | AM48: 0 | AN48: 0 | AO48: 0 | AP48: 0 | AQ48: 0 | AR48: 0 | AS48: 0 | AT48: 0 | AU48: 0 | AV48: 0 | AW48: =SUM(AL48:AU48) -> 0 | AX48: 0 | AY48: =AW48+AX48 -> 0 | AZ48: =SUM(Z48:AK48) -> 0 | BA48: 0 | BB48: =BA48-AW48 -> 0 | BC48: =IFERROR(BB48/4,0) -> 0 | BD48: =AY48-AZ48 -> 0 | BE48: =AZ48-AW48 -> 0 | BF48: No | BG48: =AVERAGE(AL48:AS48) -> 0 | BH48: Yes | BI48: =IF(BF48="Yes","",IF(BA48>1250,"E",IF(BA48>750,"D", IF(BA48>=500,"C", IF(BA48>=300,"B", IF(BA48>=200,"A", "")))))) | BJ48: =IF(BF48="Yes","",IF(AY48>1250,"E",IF(AY48>750,"D", IF(AY48>=500,"C", IF(AY48>=300,"B", IF(AY48>=200,"A", "")))))) | BK48: =SUM(AR48:AX48) -> 0 | BL48: =SUM(AL48:AQ48) -> 0 | BM48: =IFERROR(BK48/$AY48,"") | BN48: =IFERROR(BL48/$AY48,"") | BO48: =SUM(AL48:AS48) -> 0 | BP48: =IF(BF48="Yes","",IF(BO48>1250,"E",IF(BO48>750,"D", IF(BO48>=500,"C", IF(BO48>=300,"B", IF(BO48>=200,"A", "")))))) | BR48: =SUM(Z48:AE48) -> 0 | BS48: =SUM(AF48:AK48) -> 0 | BT48: =SUM(BR48:BS48) -> 0 | BU48: =IFERROR(_xlfn.XLOOKUP(D48,Sheet1!B:B,Sheet1!L:L),"") | BV48: =_xlfn.XLOOKUP(BU48,Sheet1!S:S,Sheet1!T:T) -> #N/A | BW48: =_xlfn.XLOOKUP(D48,Sheet1!B:B,Sheet1!M:M) -> #N/A | BZ48: =AY48-AW48 -> 0 | CG48: =IF(BO48<80,"Below 80", IF(BO48<=120,"80-120", IF(BO48<=200,"> 120-200", IF(BO48<=300,">200-300", IF(BO48<=500,">300-500", ">500"))))) -> Below 80 | CH48: =IFERROR(_xlfn.XLOOKUP(CG48,Scenario!M:M,Scenario!N:N),"") | CI48: =IF(BI48="", IF(BA48>=1, "Yes", "No")) -> No | CJ48: 0
A49: 48 | B49: 2023 | C49: PBTMTR12 | D49: 0015g00001VBuKaAAL | E49: S.S. ENTERPRISES | F49: HARYANA | G49: YAMUNANAGAR | H49: Jagadhri | I49: G.C. Steels (India) Pvt. Ltd. | J49: Naseem Makkar | K49: - | M49: North | N49: 135001 | O49: 06ADCFS7765F1ZU | P49: 9034163881 | Q49: Dec'23 | R49: 2024 | S49: 67 | T49: 950 | U49: 0 | V49: Alien | W49: 25 | X49: 12 | Y49: 0 | Z49: 10 | AA49: 0 | AB49: 0 | AC49: 0 | AD49: 0 | AE49: 0 | AF49: 0 | AG49: 0 | AH49: 0 | AI49: 0 | AJ49: 0 | AK49: 0 | AL49: 0 | AM49: 0 | AN49: 0 | AO49: 0 | AP49: 0 | AQ49: 0 | AR49: 0 | AS49: 0 | AT49: 0 | AU49: 0 | AV49: 0 | AW49: =SUM(AL49:AU49) -> 0 | AX49: 0 | AY49: =AW49+AX49 -> 0 | AZ49: =SUM(Z49:AK49) -> 10 | BA49: 0 | BB49: =BA49-AW49 -> 0 | BC49: =IFERROR(BB49/4,0) -> 0 | BD49: =AY49-AZ49 -> -10 | BE49: =AZ49-AW49 -> 10 | BF49: No | BG49: =AVERAGE(AL49:AS49) -> 0 | BH49: Yes | BI49: =IF(BF49="Yes","",IF(BA49>1250,"E",IF(BA49>750,"D", IF(BA49>=500,"C", IF(BA49>=300,"B", IF(BA49>=200,"A", "")))))) | BJ49: =IF(BF49="Yes","",IF(AY49>1250,"E",IF(AY49>750,"D", IF(AY49>=500,"C", IF(AY49>=300,"B", IF(AY49>=200,"A", "")))))) | BK49: =SUM(AR49:AX49) -> 0 | BL49: =SUM(AL49:AQ49) -> 0 | BM49: =IFERROR(BK49/$AY49,"") | BN49: =IFERROR(BL49/$AY49,"") | BO49: =SUM(AL49:AS49) -> 0 | BP49: =IF(BF49="Yes","",IF(BO49>1250,"E",IF(BO49>750,"D", IF(BO49>=500,"C", IF(BO49>=300,"B", IF(BO49>=200,"A", "")))))) | BR49: =SUM(Z49:AE49) -> 10 | BS49: =SUM(AF49:AK49) -> 0 | BT49: =SUM(BR49:BS49) -> 10 | BU49: =IFERROR(_xlfn.XLOOKUP(D49,Sheet1!B:B,Sheet1!L:L),"") | BV49: =_xlfn.XLOOKUP(BU49,Sheet1!S:S,Sheet1!T:T) -> #N/A | BW49: =_xlfn.XLOOKUP(D49,Sheet1!B:B,Sheet1!M:M) -> #N/A | BZ49: =AY49-AW49 -> 0 | CG49: =IF(BO49<80,"Below 80", IF(BO49<=120,"80-120", IF(BO49<=200,"> 120-200", IF(BO49<=300,">200-300", IF(BO49<=500,">300-500", ">500"))))) -> Below 80 | CH49: =IFERROR(_xlfn.XLOOKUP(CG49,Scenario!M:M,Scenario!N:N),"") | CI49: =IF(BI49="", IF(BA49>=1, "Yes", "No")) -> No | CJ49: 0
A50: 49 | B50: 2023 | C50: PBTMTR13 | D50: 0015g00001VBswjAAD | E50: AGGARWAL IRON STORE | F50: HARYANA | G50: AMBALA | H50: Ambala Cantt | I50: G.C. Steels (India) Pvt. Ltd. | J50: Deepak Dhiman | K50: - | M50: North | N50: 133001 | O50: 06AOIPA8696N1Z9 | P50: 9416496623 | Q50: Dec'23 | R50: 2024 | S50: 130 | T50: 150 | U50: 0 | V50: Challenger | W50: 30 | X50: 80 | Y50: 10 | Z50: 10 | AA50: 18 | AB50: 0 | AC50: 0 | AD50: 6.5 | AE50: 5 | AF50: 0 | AG50: 0 | AH50: 0 | AI50: 0 | AJ50: 0 | AK50: 0 | AL50: 0 | AM50: 0 | AN50: 0 | AO50: 0 | AP50: 0 | AQ50: 0 | AR50: 0 | AS50: 0 | AT50: 0 | AU50: 0 | AV50: 0 | AW50: =SUM(AL50:AU50) -> 0 | AX50: 0 | AY50: =AW50+AX50 -> 0 | AZ50: =SUM(Z50:AK50) -> 39.5 | BA50: 0 | BB50: =BA50-AW50 -> 0 | BC50: =IFERROR(BB50/4,0) -> 0 | BD50: =AY50-AZ50 -> -39.5 | BE50: =AZ50-AW50 -> 39.5 | BF50: No | BG50: =AVERAGE(AL50:AS50) -> 0 | BH50: Yes | BI50: =IF(BF50="Yes","",IF(BA50>1250,"E",IF(BA50>750,"D", IF(BA50>=500,"C", IF(BA50>=300,"B", IF(BA50>=200,"A", "")))))) | BJ50: =IF(BF50="Yes","",IF(AY50>1250,"E",IF(AY50>750,"D", IF(AY50>=500,"C", IF(AY50>=300,"B", IF(AY50>=200,"A", "")))))) | BK50: =SUM(AR50:AX50) -> 0 | BL50: =SUM(AL50:AQ50) -> 0 | BM50: =IFERROR(BK50/$AY50,"") | BN50: =IFERROR(BL50/$AY50,"") | BO50: =SUM(AL50:AS50) -> 0 | BP50: =IF(BF50="Yes","",IF(BO50>1250,"E",IF(BO50>750,"D", IF(BO50>=500,"C", IF(BO50>=300,"B", IF(BO50>=200,"A", "")))))) | BR50: =SUM(Z50:AE50) -> 39.5 | BS50: =SUM(AF50:AK50) -> 0 | BT50: =SUM(BR50:BS50) -> 39.5 | BU50: =IFERROR(_xlfn.XLOOKUP(D50,Sheet1!B:B,Sheet1!L:L),"") | BV50: =_xlfn.XLOOKUP(BU50,Sheet1!S:S,Sheet1!T:T) -> #N/A | BW50: =_xlfn.XLOOKUP(D50,Sheet1!B:B,Sheet1!M:M) -> #N/A | BZ50: =AY50-AW50 -> 0 | CG50: =IF(BO50<80,"Below 80", IF(BO50<=120,"80-120", IF(BO50<=200,"> 120-200", IF(BO50<=300,">200-300", IF(BO50<=500,">300-500", ">500"))))) -> Below 80 | CH50: =IFERROR(_xlfn.XLOOKUP(CG50,Scenario!M:M,Scenario!N:N),"") | CI50: =IF(BI50="", IF(BA50>=1, "Yes", "No")) -> No | CJ50: 0
A51: 50 | B51: 2023 | C51: PBTMTR14 | D51: 0015g00001V9wVyAAJ | E51: HINDUSTAN IRON AND STEEL TRADERS | F51: HARYANA | G51: AMBALA | H51: Saha | I51: G.C. Steels (India) Pvt. Ltd. | J51: Deepak Dhiman | K51: - | M51: North | N51: 133104 | O51: 06ACUPK3380K1Z3 | P51: 9896214851 | Q51: Dec'23 | R51: 2024 | S51: 51 | T51: 75 | U51: 0 | V51: Challenger | W51: 21 | X51: 0 | Y51: 21 | Z51: 0 | AA51: 0 | AB51: 0 | AC51: 0 | AD51: 0 | AE51: 0 | AF51: 0 | AG51: 0 | AH51: 0 | AI51: 0 | AJ51: 0 | AK51: 0 | AL51: 0 | AM51: 0 | AN51: 0 | AO51: 0 | AP51: 0 | AQ51: 0 | AR51: 0 | AS51: 0 | AT51: 0 | AU51: 0 | AV51: 0 | AW51: =SUM(AL51:AU51) -> 0 | AX51: 0 | AY51: =AW51+AX51 -> 0 | AZ51: =SUM(Z51:AK51) -> 0 | BA51: 0 | BB51: =BA51-AW51 -> 0 | BC51: =IFERROR(BB51/4,0) -> 0 | BD51: =AY51-AZ51 -> 0 | BE51: =AZ51-AW51 -> 0 | BF51: No | BG51: =AVERAGE(AL51:AS51) -> 0 | BH51: Yes | BI51: =IF(BF51="Yes","",IF(BA51>1250,"E",IF(BA51>750,"D", IF(BA51>=500,"C", IF(BA51>=300,"B", IF(BA51>=200,"A", "")))))) | BJ51: =IF(BF51="Yes","",IF(AY51>1250,"E",IF(AY51>750,"D", IF(AY51>=500,"C", IF(AY51>=300,"B", IF(AY51>=200,"A", "")))))) | BK51: =SUM(AR51:AX51) -> 0 | BL51: =SUM(AL51:AQ51) -> 0 | BM51: =IFERROR(BK51/$AY51,"") | BN51: =IFERROR(BL51/$AY51,"") | BO51: =SUM(AL51:AS51) -> 0 | BP51: =IF(BF51="Yes","",IF(BO51>1250,"E",IF(BO51>750,"D", IF(BO51>=500,"C", IF(BO51>=300,"B", IF(BO51>=200,"A", "")))))) | BR51: =SUM(Z51:AE51) -> 0 | BS51: =SUM(AF51:AK51) -> 0 | BT51: =SUM(BR51:BS51) -> 0 | BU51: =IFERROR(_xlfn.XLOOKUP(D51,Sheet1!B:B,Sheet1!L:L),"") | BV51: =_xlfn.XLOOKUP(BU51,Sheet1!S:S,Sheet1!T:T) -> #N/A | BW51: =_xlfn.XLOOKUP(D51,Sheet1!B:B,Sheet1!M:M) -> #N/A | BZ51: =AY51-AW51 -> 0 | CG51: =IF(BO51<80,"Below 80", IF(BO51<=120,"80-120", IF(BO51<=200,"> 120-200", IF(BO51<=300,">200-300", IF(BO51<=500,">300-500", ">500"))))) -> Below 80 | CH51: =IFERROR(_xlfn.XLOOKUP(CG51,Scenario!M:M,Scenario!N:N),"") | CI51: =IF(BI51="", IF(BA51>=1, "Yes", "No")) -> No | CJ51: 0
A52: 51 | B52: 2023 | C52: PBTMTR131 | D52: 0015g00001V9TgRAAV | E52: BHARAT TIMBER COMPANY | F52: HARYANA | G52: CHARKI DADRI | H52: Charkhi Dadri | I52: PAL CEMENT AND STEEL PVT. LTD. | J52: Dinesh Kumar | K52: Navneet Pal | L52: C12827 | M52: North | N52: 127306 | O52: 06AIBPS3044B1ZR | P52: 9812980921 | Q52: Nov'23 | R52: 2024 | S52: 123 | T52: 110 | U52: 0 | V52: Challenger | W52: 46 | X52: 47 | Y52: 11 | Z52: 0 | AA52: 0 | AB52: 0 | AC52: 0 | AD52: 0 | AE52: 0 | AF52: 0 | AG52: 0 | AH52: 0 | AI52: 0 | AJ52: 0 | AK52: 0 | AL52: 0 | AM52: 0 | AN52: 0 | AO52: 0 | AP52: 0 | AQ52: 0 | AR52: 0 | AS52: 0 | AT52: 0 | AU52: 0 | AV52: 0 | AW52: =SUM(AL52:AU52) -> 0 | AX52: 0 | AY52: =AW52+AX52 -> 0 | AZ52: =SUM(Z52:AK52) -> 0 | BA52: 0 | BB52: =BA52-AW52 -> 0 | BC52: =IFERROR(BB52/4,0) -> 0 | BD52: =AY52-AZ52 -> 0 | BE52: =AZ52-AW52 -> 0 | BF52: No | BG52: =AVERAGE(AL52:AS52) -> 0 | BH52: Yes | BI52: =IF(BF52="Yes","",IF(BA52>1250,"E",IF(BA52>750,"D", IF(BA52>=500,"C", IF(BA52>=300,"B", IF(BA52>=200,"A", "")))))) | BJ52: =IF(BF52="Yes","",IF(AY52>1250,"E",IF(AY52>750,"D", IF(AY52>=500,"C", IF(AY52>=300,"B", IF(AY52>=200,"A", "")))))) | BK52: =SUM(AR52:AX52) -> 0 | BL52: =SUM(AL52:AQ52) -> 0 | BM52: =IFERROR(BK52/$AY52,"") | BN52: =IFERROR(BL52/$AY52,"") | BO52: =SUM(AL52:AS52) -> 0 | BP52: =IF(BF52="Yes","",IF(BO52>1250,"E",IF(BO52>750,"D", IF(BO52>=500,"C", IF(BO52>=300,"B", IF(BO52>=200,"A", "")))))) | BR52: =SUM(Z52:AE52) -> 0 | BS52: =SUM(AF52:AK52) -> 0 | BT52: =SUM(BR52:BS52) -> 0 | BU52: =IFERROR(_xlfn.XLOOKUP(D52,Sheet1!B:B,Sheet1!L:L),"") | BV52: =_xlfn.XLOOKUP(BU52,Sheet1!S:S,Sheet1!T:T) -> #N/A | BW52: =_xlfn.XLOOKUP(D52,Sheet1!B:B,Sheet1!M:M) -> #N/A | BZ52: =AY52-AW52 -> 0 | CG52: =IF(BO52<80,"Below 80", IF(BO52<=120,"80-120", IF(BO52<=200,"> 120-200", IF(BO52<=300,">200-300", IF(BO52<=500,">300-500", ">500"))))) -> Below 80 | CH52: =IFERROR(_xlfn.XLOOKUP(CG52,Scenario!M:M,Scenario!N:N),"") | CI52: =IF(BI52="", IF(BA52>=1, "Yes", "No")) -> No | CJ52: 0
A53: 52 | B53: 2023 | C53: PBTMTR132 | D53: 001J100000AqVaLIAV | E53: SHREE GANESH STEELS | F53: HARYANA | G53: FATEHABAD | H53: Fatehabad | I53: PAL CEMENT AND STEEL PVT. LTD. | J53: Varun Arora | K53: Shubham Gahlot | L53: C12827 | M53: North | N53: 125050 | O53: 06ACHFS1566L1ZR | P53: 9254322222 | Q53: Nov'23 | R53: 2024 | S53: 158 | T53: 180 | U53: 0.03137037 | V53: Challenger | W53: 11 | X53: 12 | Y53: 13 | Z53: 2 | AA53: 2.6 | AB53: 0 | AC53: 0 | AD53: 0 | AE53: 55.6 | AF53: 51 | AG53: 0 | AH53: 36 | AI53: 51 | AJ53: 51 | AK53: 57 | AL53: 53 | AM53: 53 | AN53: 25.58 | AO53: 121.01 | AP53: 15.01 | AQ53: 3 | AR53: 10 | AS53: 5 | AT53: 16.94 | AU53: 0 | AV53: 0 | AW53: =SUM(AL53:AU53) -> 302.54 | AX53: 219.4 | AY53: =BW53 -> 500 | AZ53: =SUM(Z53:AK53) -> 306.2 | BA53: 550 | BB53: =BA53-AW53 -> 247.46 | BC53: =IFERROR(BB53/4,0) -> 61.865 | BD53: =AY53-AZ53 -> 193.8 | BE53: =AZ53-AW53 -> 3.66 | BF53: No | BG53: =AVERAGE(AL53:AS53) -> 35.7 | BH53: Yes | BI53: =IF(BF53="Yes","",IF(BA53>1250,"E",IF(BA53>750,"D", IF(BA53>=500,"C", IF(BA53>=300,"B", IF(BA53>=200,"A", "")))))) -> C | BJ53: =IF(BF53="Yes","",IF(AY53>1250,"E",IF(AY53>750,"D", IF(AY53>=500,"C", IF(AY53>=300,"B", IF(AY53>=200,"A", "")))))) -> C | BK53: =SUM(AR53:AX53) -> 553.88 | BL53: =SUM(AL53:AQ53) -> 270.6 | BM53: =IFERROR(BK53/$AY53,"") -> 1.10776 | BN53: =IFERROR(BL53/$AY53,"") -> 0.5412 | BO53: =SUM(AL53:AS53) -> 285.6 | BP53: =IF(BF53="Yes","",IF(BO53>1250,"E",IF(BO53>750,"D", IF(BO53>=500,"C", IF(BO53>=300,"B", IF(BO53>=200,"A", "")))))) -> A | BR53: =SUM(Z53:AE53) -> 60.2 | BS53: =SUM(AF53:AK53) -> 246 | BT53: =SUM(BR53:BS53) -> 306.2 | BU53: =IFERROR(_xlfn.XLOOKUP(D53,Sheet1!B:B,Sheet1!L:L),"") -> International Trip (1 pax South Asia) 3N-4D | BV53: =_xlfn.XLOOKUP(BU53,Sheet1!S:S,Sheet1!T:T) -> B | BW53: =_xlfn.XLOOKUP(D53,Sheet1!B:B,Sheet1!M:M) -> 500 | BX53: Qualified in Tour Scheme FY25 | BY53: 501 | BZ53: =AY53-AW53 -> 197.46 | CB53: =AW53/AY53 -> 0.60508 | CC53: =AX53/AY53 -> 0.4388 | CG53: =IF(BO53<80,"Below 80", IF(BO53<=120,"80-120", IF(BO53<=200,"> 120-200", IF(BO53<=300,">200-300", IF(BO53<=500,">300-500", ">500"))))) -> >200-300 | CH53: =IFERROR(_xlfn.XLOOKUP(CG53,Scenario!M:M,Scenario!N:N),"") -> C | CI53: =IF(BI53="", IF(BA53>=1, "Yes", "No")) -> FALSE | CJ53: 214.4
A54: 53 | B54: 2023 | C54: PBTMTR133 | D54: 0015g00001c41dNAAQ | E54: SHREE GANESH TRADING COMPANY | F54: HARYANA | G54: FATEHABAD | H54: Fatehabad | I54: PAL CEMENT AND STEEL PVT. LTD. | J54: Varun Arora | K54: Shubham Gahlot | L54: C12827 | M54: North | N54: 125050 | O54: 0 | P54: 0 | Q54: Nov'23 | R54: 2024 | S54: 115 | T54: 400 | U54: 0 | V54: Alien | W54: 40 | X54: 42 | Y54: 10 | Z54: 0 | AA54: 0 | AB54: 0 | AC54: 0 | AD54: 0 | AE54: 0 | AF54: 0 | AG54: 0 | AH54: 0 | AI54: 0 | AJ54: 0 | AK54: 0 | AL54: 0 | AM54: 0 | AN54: 0 | AO54: 0 | AP54: 0 | AQ54: 0 | AR54: 0 | AS54: 0 | AT54: 0 | AU54: 0 | AV54: 0 | AW54: =SUM(AL54:AU54) -> 0 | AX54: 0 | AY54: =AW54+AX54 -> 0 | AZ54: =SUM(Z54:AK54) -> 0 | BA54: 0 | BB54: =BA54-AW54 -> 0 | BC54: =IFERROR(BB54/4,0) -> 0 | BD54: =AY54-AZ54 -> 0 | BE54: =AZ54-AW54 -> 0 | BF54: No | BG54: =AVERAGE(AL54:AS54) -> 0 | BH54: Yes | BI54: =IF(BF54="Yes","",IF(BA54>1250,"E",IF(BA54>750,"D", IF(BA54>=500,"C", IF(BA54>=300,"B", IF(BA54>=200,"A", "")))))) | BJ54: =IF(BF54="Yes","",IF(AY54>1250,"E",IF(AY54>750,"D", IF(AY54>=500,"C", IF(AY54>=300,"B", IF(AY54>=200,"A", "")))))) | BK54: =SUM(AR54:AX54) -> 0 | BL54: =SUM(AL54:AQ54) -> 0 | BM54: =IFERROR(BK54/$AY54,"") | BN54: =IFERROR(BL54/$AY54,"") | BO54: =SUM(AL54:AS54) -> 0 | BP54: =IF(BF54="Yes","",IF(BO54>1250,"E",IF(BO54>750,"D", IF(BO54>=500,"C", IF(BO54>=300,"B", IF(BO54>=200,"A", "")))))) | BR54: =SUM(Z54:AE54) -> 0 | BS54: =SUM(AF54:AK54) -> 0 | BT54: =SUM(BR54:BS54) -> 0 | BU54: =IFERROR(_xlfn.XLOOKUP(D54,Sheet1!B:B,Sheet1!L:L),"") | BV54: =_xlfn.XLOOKUP(BU54,Sheet1!S:S,Sheet1!T:T) -> #N/A | BW54: =_xlfn.XLOOKUP(D54,Sheet1!B:B,Sheet1!M:M) -> #N/A | BZ54: =AY54-AW54 -> 0 | CG54: =IF(BO54<80,"Below 80", IF(BO54<=120,"80-120", IF(BO54<=200,"> 120-200", IF(BO54<=300,">200-300", IF(BO54<=500,">300-500", ">500"))))) -> Below 80 | CH54: =IFERROR(_xlfn.XLOOKUP(CG54,Scenario!M:M,Scenario!N:N),"") | CI54: =IF(BI54="", IF(BA54>=1, "Yes", "No")) -> No | CJ54: 0
A55: 54 | B55: 2023 | C55: PBTMTR134 | D55: 001J10000053Tn5IAE | E55: SULEKH CHAND MITTAR SAIN JAIN | F55: HARYANA | G55: JIND | H55: Safidon | I55: PAL CEMENT AND STEEL PVT. LTD. | J55: Dinesh Kumar | K55: Navneet Pal | L55: C12827 | M55: North | N55: 126112 | O55: 06AZLPJ3280F1ZE | P55: 9996986665 | Q55: Nov'23 | R55: 2024 | S55: 114 | T55: 350 | U55: 0 | V55: Alien | W55: 40 | X55: 42 | Y55: 10 | Z55: 18 | AA55: 1.5 | AB55: 0 | AC55: 0 | AD55: 0 | AE55: 0 | AF55: 0 | AG55: 0 | AH55: 0 | AI55: 0 | AJ55: 0 | AK55: 0 | AL55: 0 | AM55: 0 | AN55: 0 | AO55: 0 | AP55: 0 | AQ55: 0 | AR55: 0 | AS55: 0 | AT55: 0 | AU55: 0 | AV55: 0 | AW55: =SUM(AL55:AU55) -> 0 | AX55: 0 | AY55: =AW55+AX55 -> 0 | AZ55: =SUM(Z55:AK55) -> 19.5 | BA55: 50 | BB55: =BA55-AW55 -> 50 | BC55: =IFERROR(BB55/4,0) -> 12.5 | BD55: =AY55-AZ55 -> -19.5 | BE55: =AZ55-AW55 -> 19.5 | BF55: No | BG55: =AVERAGE(AL55:AS55) -> 0 | BH55: Yes | BI55: =IF(BF55="Yes","",IF(BA55>1250,"E",IF(BA55>750,"D", IF(BA55>=500,"C", IF(BA55>=300,"B", IF(BA55>=200,"A", "")))))) | BJ55: =IF(BF55="Yes","",IF(AY55>1250,"E",IF(AY55>750,"D", IF(AY55>=500,"C", IF(AY55>=300,"B", IF(AY55>=200,"A", "")))))) | BK55: =SUM(AR55:AX55) -> 0 | BL55: =SUM(AL55:AQ55) -> 0 | BM55: =IFERROR(BK55/$AY55,"") | BN55: =IFERROR(BL55/$AY55,"") | BO55: =SUM(AL55:AS55) -> 0 | BP55: =IF(BF55="Yes","",IF(BO55>1250,"E",IF(BO55>750,"D", IF(BO55>=500,"C", IF(BO55>=300,"B", IF(BO55>=200,"A", "")))))) | BR55: =SUM(Z55:AE55) -> 19.5 | BS55: =SUM(AF55:AK55) -> 0 | BT55: =SUM(BR55:BS55) -> 19.5 | BU55: =IFERROR(_xlfn.XLOOKUP(D55,Sheet1!B:B,Sheet1!L:L),"") | BV55: =_xlfn.XLOOKUP(BU55,Sheet1!S:S,Sheet1!T:T) -> #N/A | BW55: =_xlfn.XLOOKUP(D55,Sheet1!B:B,Sheet1!M:M) -> #N/A | BZ55: =AY55-AW55 -> 0 | CG55: =IF(BO55<80,"Below 80", IF(BO55<=120,"80-120", IF(BO55<=200,"> 120-200", IF(BO55<=300,">200-300", IF(BO55<=500,">300-500", ">500"))))) -> Below 80 | CH55: =IFERROR(_xlfn.XLOOKUP(CG55,Scenario!M:M,Scenario!N:N),"") | CI55: =IF(BI55="", IF(BA55>=1, "Yes", "No")) -> Yes | CJ55: 0
A56: 55 | B56: 2023 | C56: PBTMTR135 | D56: 0015g00001XamPUAAZ | E56: VARDHMAN STEEL | F56: HARYANA | G56: JIND | H56: Jind | I56: PAL CEMENT AND STEEL PVT. LTD. | J56: Dinesh Kumar | K56: Navneet Pal | L56: C12827 | M56: North | N56: 126102 | O56: 06BDUPG3332D1ZR | P56: 9253077099 | Q56: Nov'23 | R56: 2024 | S56: 112 | T56: 80 | U56: 0 | V56: Challenger | W56: 30 | X56: 32 | Y56: 10 | Z56: 21 | AA56: 3.2 | AB56: 51 | AC56: 50.08 | AD56: 50.6 | AE56: 0 | AF56: 50.5 | AG56: 55 | AH56: 0 | AI56: 52 | AJ56: 90 | AK56: 90 | AL56: 0 | AM56: 0 | AN56: 0 | AO56: 0 | AP56: 0 | AQ56: 0 | AR56: 0 | AS56: 0 | AT56: 0 | AU56: 0 | AV56: 0 | AW56: =SUM(AL56:AU56) -> 0 | AX56: 0 | AY56: =AW56+AX56 -> 0 | AZ56: =SUM(Z56:AK56) -> 513.38 | BA56: 0 | BB56: =BA56-AW56 -> 0 | BC56: =IFERROR(BB56/4,0) -> 0 | BD56: =AY56-AZ56 -> -513.38 | BE56: =AZ56-AW56 -> 513.38 | BF56: No | BG56: =AVERAGE(AL56:AS56) -> 0 | BH56: Yes | BI56: =IF(BF56="Yes","",IF(BA56>1250,"E",IF(BA56>750,"D", IF(BA56>=500,"C", IF(BA56>=300,"B", IF(BA56>=200,"A", "")))))) | BJ56: =IF(BF56="Yes","",IF(AY56>1250,"E",IF(AY56>750,"D", IF(AY56>=500,"C", IF(AY56>=300,"B", IF(AY56>=200,"A", "")))))) | BK56: =SUM(AR56:AX56) -> 0 | BL56: =SUM(AL56:AQ56) -> 0 | BM56: =IFERROR(BK56/$AY56,"") | BN56: =IFERROR(BL56/$AY56,"") | BO56: =SUM(AL56:AS56) -> 0 | BP56: =IF(BF56="Yes","",IF(BO56>1250,"E",IF(BO56>750,"D", IF(BO56>=500,"C", IF(BO56>=300,"B", IF(BO56>=200,"A", "")))))) | BR56: =SUM(Z56:AE56) -> 175.88 | BS56: =SUM(AF56:AK56) -> 337.5 | BT56: =SUM(BR56:BS56) -> 513.38 | BU56: =IFERROR(_xlfn.XLOOKUP(D56,Sheet1!B:B,Sheet1!L:L),"") -> 0 | BV56: =_xlfn.XLOOKUP(BU56,Sheet1!S:S,Sheet1!T:T) -> #N/A | BW56: =_xlfn.XLOOKUP(D56,Sheet1!B:B,Sheet1!M:M) -> 0 | BZ56: =AY56-AW56 -> 0 | CG56: =IF(BO56<80,"Below 80", IF(BO56<=120,"80-120", IF(BO56<=200,"> 120-200", IF(BO56<=300,">200-300", IF(BO56<=500,">300-500", ">500"))))) -> Below 80 | CH56: =IFERROR(_xlfn.XLOOKUP(CG56,Scenario!M:M,Scenario!N:N),"") | CI56: =IF(BI56="", IF(BA56>=1, "Yes", "No")) -> No | CJ56: 0
A57: 56 | B57: 2023 | C57: PBTMTR136 | D57: 0015g00001gv78XAAQ | E57: BALAJI ENTERPRISES | F57: HARYANA | G57: SIRSA | H57: Sirsa | I57: PAL CEMENT AND STEEL PVT. LTD. | J57: Varun Arora | K57: Shubham Gahlot | L57: C12827 | M57: North | N57: 125055 | O57: 06BSWPG4392L1ZZ | P57: 91241 00009 | Q57: Nov'23 | R57: 2024 | S57: 175 | T57: 50 | U57: 0 | V57: Minor | W57: 30 | X57: 35 | Y57: 10 | Z57: 21 | AA57: 30.01 | AB57: 75 | AC57: 0 | AD57: 0 | AE57: 0 | AF57: 51 | AG57: 0 | AH57: 37 | AI57: 51 | AJ57: 91 | AK57: 69.5 | AL57: 0 | AM57: 0 | AN57: 0 | AO57: 0 | AP57: 0 | AQ57: 0 | AR57: 0 | AS57: 0 | AT57: 0 | AU57: 0 | AV57: 0 | AW57: =SUM(AL57:AU57) -> 0 | AX57: 0 | AY57: =AW57+AX57 -> 0 | AZ57: =SUM(Z57:AK57) -> 425.51 | BA57: 0 | BB57: =BA57-AW57 -> 0 | BC57: =IFERROR(BB57/4,0) -> 0 | BD57: =AY57-AZ57 -> -425.51 | BE57: =AZ57-AW57 -> 425.51 | BF57: No | BG57: =AVERAGE(AL57:AS57) -> 0 | BH57: Yes | BI57: =IF(BF57="Yes","",IF(BA57>1250,"E",IF(BA57>750,"D", IF(BA57>=500,"C", IF(BA57>=300,"B", IF(BA57>=200,"A", "")))))) | BJ57: =IF(BF57="Yes","",IF(AY57>1250,"E",IF(AY57>750,"D", IF(AY57>=500,"C", IF(AY57>=300,"B", IF(AY57>=200,"A", "")))))) | BK57: =SUM(AR57:AX57) -> 0 | BL57: =SUM(AL57:AQ57) -> 0 | BM57: =IFERROR(BK57/$AY57,"") | BN57: =IFERROR(BL57/$AY57,"") | BO57: =SUM(AL57:AS57) -> 0 | BP57: =IF(BF57="Yes","",IF(BO57>1250,"E",IF(BO57>750,"D", IF(BO57>=500,"C", IF(BO57>=300,"B", IF(BO57>=200,"A", "")))))) | BR57: =SUM(Z57:AE57) -> 126.01 | BS57: =SUM(AF57:AK57) -> 299.5 | BT57: =SUM(BR57:BS57) -> 425.51 | BU57: =IFERROR(_xlfn.XLOOKUP(D57,Sheet1!B:B,Sheet1!L:L),"") -> 0 | BV57: =_xlfn.XLOOKUP(BU57,Sheet1!S:S,Sheet1!T:T) -> #N/A | BW57: =_xlfn.XLOOKUP(D57,Sheet1!B:B,Sheet1!M:M) -> 0 | BZ57: =AY57-AW57 -> 0 | CG57: =IF(BO57<80,"Below 80", IF(BO57<=120,"80-120", IF(BO57<=200,"> 120-200", IF(BO57<=300,">200-300", IF(BO57<=500,">300-500", ">500"))))) -> Below 80 | CH57: =IFERROR(_xlfn.XLOOKUP(CG57,Scenario!M:M,Scenario!N:N),"") | CI57: =IF(BI57="", IF(BA57>=1, "Yes", "No")) -> No | CJ57: 0
A58: 57 | B58: 2023 | C58: PBTMTR137 | D58: 0015g00001VCBrZAAX | E58: GANPATI ENTERPRISES | F58: HARYANA | G58: HISAR | H58: Hansi | I58: PAL CEMENT AND STEEL PVT. LTD. | J58: Dinesh Kumar | K58: Navneet Pal | L58: C12827 | M58: North | N58: 125001 | O58: 06EBPPS6458N1ZJ | P58: 9958428844 | Q58: Dec'23 | R58: 2024 | S58: 51 | T58: 50 | U58: 0 | V58: Minor | W58: 10 | X58: 12 | Y58: 18 | Z58: 5 | AA58: 4.796 | AB58: 0 | AC58: 0 | AD58: 0 | AE58: 0 | AF58: 0 | AG58: 0 | AH58: 0 | AI58: 0 | AJ58: 0 | AK58: 0 | AL58: 0 | AM58: 0 | AN58: 0 | AO58: 0 | AP58: 0 | AQ58: 0 | AR58: 0 | AS58: 0 | AT58: 0 | AU58: 0 | AV58: 0 | AW58: =SUM(AL58:AU58) -> 0 | AX58: 0 | AY58: =AW58+AX58 -> 0 | AZ58: =SUM(Z58:AK58) -> 9.796 | BA58: 0 | BB58: =BA58-AW58 -> 0 | BC58: =IFERROR(BB58/4,0) -> 0 | BD58: =AY58-AZ58 -> -9.796 | BE58: =AZ58-AW58 -> 9.796 | BF58: No | BG58: =AVERAGE(AL58:AS58) -> 0 | BH58: Yes | BI58: =IF(BF58="Yes","",IF(BA58>1250,"E",IF(BA58>750,"D", IF(BA58>=500,"C", IF(BA58>=300,"B", IF(BA58>=200,"A", "")))))) | BJ58: =IF(BF58="Yes","",IF(AY58>1250,"E",IF(AY58>750,"D", IF(AY58>=500,"C", IF(AY58>=300,"B", IF(AY58>=200,"A", "")))))) | BK58: =SUM(AR58:AX58) -> 0 | BL58: =SUM(AL58:AQ58) -> 0 | BM58: =IFERROR(BK58/$AY58,"") | BN58: =IFERROR(BL58/$AY58,"") | BO58: =SUM(AL58:AS58) -> 0 | BP58: =IF(BF58="Yes","",IF(BO58>1250,"E",IF(BO58>750,"D", IF(BO58>=500,"C", IF(BO58>=300,"B", IF(BO58>=200,"A", "")))))) | BR58: =SUM(Z58:AE58) -> 9.796 | BS58: =SUM(AF58:AK58) -> 0 | BT58: =SUM(BR58:BS58) -> 9.796 | BU58: =IFERROR(_xlfn.XLOOKUP(D58,Sheet1!B:B,Sheet1!L:L),"") | BV58: =_xlfn.XLOOKUP(BU58,Sheet1!S:S,Sheet1!T:T) -> #N/A | BW58: =_xlfn.XLOOKUP(D58,Sheet1!B:B,Sheet1!M:M) -> #N/A | BZ58: =AY58-AW58 -> 0 | CG58: =IF(BO58<80,"Below 80", IF(BO58<=120,"80-120", IF(BO58<=200,"> 120-200", IF(BO58<=300,">200-300", IF(BO58<=500,">300-500", ">500"))))) -> Below 80 | CH58: =IFERROR(_xlfn.XLOOKUP(CG58,Scenario!M:M,Scenario!N:N),"") | CI58: =IF(BI58="", IF(BA58>=1, "Yes", "No")) -> No | CJ58: 0
A59: 58 | B59: 2023 | C59: PBTMTR138 | D59: 0015g00001V9TgUAAV | E59: MAA DARSHAN TRADING CO. | F59: HARYANA | G59: HISAR | H59: Hansi | I59: PAL CEMENT AND STEEL PVT. LTD. | J59: Dinesh Kumar | K59: Navneet Pal | L59: C12827 | M59: North | N59: 125033 | O59: 06CRHPS9039R1ZP | P59: 9253732625 | Q59: Dec'23 | R59: 2024 | S59: 50 | T59: 200 | U59: 0 | V59: Challenger | W59: 10 | X59: 12 | Y59: 18 | Z59: 0 | AA59: 0 | AB59: 0 | AC59: 0 | AD59: 0 | AE59: 0 | AF59: 0 | AG59: 0 | AH59: 0 | AI59: 0 | AJ59: 0 | AK59: 0 | AL59: 0 | AM59: 0 | AN59: 0 | AO59: 0 | AP59: 0 | AQ59: 0 | AR59: 0 | AS59: 0 | AT59: 0 | AU59: 0 | AV59: 0 | AW59: =SUM(AL59:AU59) -> 0 | AX59: 0 | AY59: =AW59+AX59 -> 0 | AZ59: =SUM(Z59:AK59) -> 0 | BA59: 0 | BB59: =BA59-AW59 -> 0 | BC59: =IFERROR(BB59/4,0) -> 0 | BD59: =AY59-AZ59 -> 0 | BE59: =AZ59-AW59 -> 0 | BF59: No | BG59: =AVERAGE(AL59:AS59) -> 0 | BH59: Yes | BI59: =IF(BF59="Yes","",IF(BA59>1250,"E",IF(BA59>750,"D", IF(BA59>=500,"C", IF(BA59>=300,"B", IF(BA59>=200,"A", "")))))) | BJ59: =IF(BF59="Yes","",IF(AY59>1250,"E",IF(AY59>750,"D", IF(AY59>=500,"C", IF(AY59>=300,"B", IF(AY59>=200,"A", "")))))) | BK59: =SUM(AR59:AX59) -> 0 | BL59: =SUM(AL59:AQ59) -> 0 | BM59: =IFERROR(BK59/$AY59,"") | BN59: =IFERROR(BL59/$AY59,"") | BO59: =SUM(AL59:AS59) -> 0 | BP59: =IF(BF59="Yes","",IF(BO59>1250,"E",IF(BO59>750,"D", IF(BO59>=500,"C", IF(BO59>=300,"B", IF(BO59>=200,"A", "")))))) | BR59: =SUM(Z59:AE59) -> 0 | BS59: =SUM(AF59:AK59) -> 0 | BT59: =SUM(BR59:BS59) -> 0 | BU59: =IFERROR(_xlfn.XLOOKUP(D59,Sheet1!B:B,Sheet1!L:L),"") | BV59: =_xlfn.XLOOKUP(BU59,Sheet1!S:S,Sheet1!T:T) -> #N/A | BW59: =_xlfn.XLOOKUP(D59,Sheet1!B:B,Sheet1!M:M) -> #N/A | BZ59: =AY59-AW59 -> 0 | CG59: =IF(BO59<80,"Below 80", IF(BO59<=120,"80-120", IF(BO59<=200,"> 120-200", IF(BO59<=300,">200-300", IF(BO59<=500,">300-500", ">500"))))) -> Below 80 | CH59: =IFERROR(_xlfn.XLOOKUP(CG59,Scenario!M:M,Scenario!N:N),"") | CI59: =IF(BI59="", IF(BA59>=1, "Yes", "No")) -> No | CJ59: 0
A60: 59 | B60: 2023 | C60: PBTMTR139 | D60: 001J100000F4iokIAB | E60: MODERN EDUCATION SOCIETY | F60: HARYANA | G60: FATEHABAD | H60: Tohana | I60: PAL CEMENT AND STEEL PVT. LTD. | J60: Dinesh Kumar | K60: Shubham Gahlot | L60: C12827 | M60: North | N60: 0 | O60: 27AAATM1656J2ZF | P60: 0 | Q60: Dec'23 | R60: 2024 | S60: 50 | T60: 75 | U60: 0 | V60: Challenger | W60: 11 | X60: 13 | Y60: 16 | Z60: 0 | AA60: 0 | AB60: 0 | AC60: 0 | AD60: 0 | AE60: 0 | AF60: 0 | AG60: 0 | AH60: 0 | AI60: 0 | AJ60: 0 | AK60: 0 | AL60: 0 | AM60: 0 | AN60: 0 | AO60: 0 | AP60: 0 | AQ60: 0 | AR60: 0 | AS60: 0 | AT60: 0 | AU60: 0 | AV60: 0 | AW60: =SUM(AL60:AU60) -> 0 | AX60: 0 | AY60: =AW60+AX60 -> 0 | AZ60: =SUM(Z60:AK60) -> 0 | BA60: 0 | BB60: =BA60-AW60 -> 0 | BC60: =IFERROR(BB60/4,0) -> 0 | BD60: =AY60-AZ60 -> 0 | BE60: =AZ60-AW60 -> 0 | BF60: No | BG60: =AVERAGE(AL60:AS60) -> 0 | BH60: Yes | BI60: =IF(BF60="Yes","",IF(BA60>1250,"E",IF(BA60>750,"D", IF(BA60>=500,"C", IF(BA60>=300,"B", IF(BA60>=200,"A", "")))))) | BJ60: =IF(BF60="Yes","",IF(AY60>1250,"E",IF(AY60>750,"D", IF(AY60>=500,"C", IF(AY60>=300,"B", IF(AY60>=200,"A", "")))))) | BK60: =SUM(AR60:AX60) -> 0 | BL60: =SUM(AL60:AQ60) -> 0 | BM60: =IFERROR(BK60/$AY60,"") | BN60: =IFERROR(BL60/$AY60,"") | BO60: =SUM(AL60:AS60) -> 0 | BP60: =IF(BF60="Yes","",IF(BO60>1250,"E",IF(BO60>750,"D", IF(BO60>=500,"C", IF(BO60>=300,"B", IF(BO60>=200,"A", "")))))) | BR60: =SUM(Z60:AE60) -> 0 | BS60: =SUM(AF60:AK60) -> 0 | BT60: =SUM(BR60:BS60) -> 0 | BU60: =IFERROR(_xlfn.XLOOKUP(D60,Sheet1!B:B,Sheet1!L:L),"") | BV60: =_xlfn.XLOOKUP(BU60,Sheet1!S:S,Sheet1!T:T) -> #N/A | BW60: =_xlfn.XLOOKUP(D60,Sheet1!B:B,Sheet1!M:M) -> #N/A | BZ60: =AY60-AW60 -> 0 | CG60: =IF(BO60<80,"Below 80", IF(BO60<=120,"80-120", IF(BO60<=200,"> 120-200", IF(BO60<=300,">200-300", IF(BO60<=500,">300-500", ">500"))))) -> Below 80 | CH60: =IFERROR(_xlfn.XLOOKUP(CG60,Scenario!M:M,Scenario!N:N),"") | CI60: =IF(BI60="", IF(BA60>=1, "Yes", "No")) -> No | CJ60: 0
A61: 60 | B61: 2023 | C61: PBTMTR140 | D61: 0015g00001c41dOAAQ | E61: R P Sales Corporation | F61: HARYANA | G61: SIRSA | H61: Malout | I61: PAL CEMENT AND STEEL PVT. LTD. | J61: Varun Arora | K61: Abhishek Wadhwa | L61: C12827 | M61: North | N61: 125055 | O61: 0 | P61: 7988567070 | Q61: Dec'23 | R61: 2024 | S61: 105 | T61: 50 | U61: 0 | V61: Minor | W61: 30 | X61: 32 | Y61: 33 | Z61: 29 | AA61: 1.4 | AB61: 0 | AC61: 0 | AD61: 0 | AE61: 0 | AF61: 0 | AG61: 0 | AH61: 0 | AI61: 0 | AJ61: 0 | AK61: 0 | AL61: 0 | AM61: 0 | AN61: 0 | AO61: 0 | AP61: 0 | AQ61: 0 | AR61: 0 | AS61: 0 | AT61: 0 | AU61: 0 | AV61: 0 | AW61: =SUM(AL61:AU61) -> 0 | AX61: 0 | AY61: =AW61+AX61 -> 0 | AZ61: =SUM(Z61:AK61) -> 30.4 | BA61: 0 | BB61: =BA61-AW61 -> 0 | BC61: =IFERROR(BB61/4,0) -> 0 | BD61: =AY61-AZ61 -> -30.4 | BE61: =AZ61-AW61 -> 30.4 | BF61: No | BG61: =AVERAGE(AL61:AS61) -> 0 | BH61: Yes | BI61: =IF(BF61="Yes","",IF(BA61>1250,"E",IF(BA61>750,"D", IF(BA61>=500,"C", IF(BA61>=300,"B", IF(BA61>=200,"A", "")))))) | BJ61: =IF(BF61="Yes","",IF(AY61>1250,"E",IF(AY61>750,"D", IF(AY61>=500,"C", IF(AY61>=300,"B", IF(AY61>=200,"A", "")))))) | BK61: =SUM(AR61:AX61) -> 0 | BL61: =SUM(AL61:AQ61) -> 0 | BM61: =IFERROR(BK61/$AY61,"") | BN61: =IFERROR(BL61/$AY61,"") | BO61: =SUM(AL61:AS61) -> 0 | BP61: =IF(BF61="Yes","",IF(BO61>1250,"E",IF(BO61>750,"D", IF(BO61>=500,"C", IF(BO61>=300,"B", IF(BO61>=200,"A", "")))))) | BR61: =SUM(Z61:AE61) -> 30.4 | BS61: =SUM(AF61:AK61) -> 0 | BT61: =SUM(BR61:BS61) -> 30.4 | BU61: =IFERROR(_xlfn.XLOOKUP(D61,Sheet1!B:B,Sheet1!L:L),"") | BV61: =_xlfn.XLOOKUP(BU61,Sheet1!S:S,Sheet1!T:T) -> #N/A | BW61: =_xlfn.XLOOKUP(D61,Sheet1!B:B,Sheet1!M:M) -> #N/A | BZ61: =AY61-AW61 -> 0 | CG61: =IF(BO61<80,"Below 80", IF(BO61<=120,"80-120", IF(BO61<=200,"> 120-200", IF(BO61<=300,">200-300", IF(BO61<=500,">300-500", ">500"))))) -> Below 80 | CH61: =IFERROR(_xlfn.XLOOKUP(CG61,Scenario!M:M,Scenario!N:N),"") | CI61: =IF(BI61="", IF(BA61>=1, "Yes", "No")) -> No | CJ61: 0
A62: 61 | B62: 2023 | C62: PBTMTR141 | D62: 0015g00001V91N9AAJ | E62: SAJJAN KUMAR AND SONS | F62: HARYANA | G62: HISAR | H62: Hisar | I62: PAL CEMENT AND STEEL PVT. LTD. | J62: Dinesh Kumar | K62: Navneet Pal | L62: C12827 | M62: North | N62: 125001 | O62: 06AKFPD1770K1ZA | P62: 9215000505 | Q62: Dec'23 | R62: 2024 | S62: 66 | T62: 150 | U62: 0 | V62: Challenger | W62: 10 | X62: 12 | Y62: 12 | Z62: 0 | AA62: 0 | AB62: 0 | AC62: 0 | AD62: 0 | AE62: 0 | AF62: 0 | AG62: 0 | AH62: 0 | AI62: 0 | AJ62: 0 | AK62: 0 | AL62: 0 | AM62: 0 | AN62: 0 | AO62: 0 | AP62: 0 | AQ62: 0 | AR62: 0 | AS62: 0 | AT62: 0 | AU62: 0 | AV62: 0 | AW62: =SUM(AL62:AU62) -> 0 | AX62: 0 | AY62: =AW62+AX62 -> 0 | AZ62: =SUM(Z62:AK62) -> 0 | BA62: 0 | BB62: =BA62-AW62 -> 0 | BC62: =IFERROR(BB62/4,0) -> 0 | BD62: =AY62-AZ62 -> 0 | BE62: =AZ62-AW62 -> 0 | BF62: No | BG62: =AVERAGE(AL62:AS62) -> 0 | BH62: Yes | BI62: =IF(BF62="Yes","",IF(BA62>1250,"E",IF(BA62>750,"D", IF(BA62>=500,"C", IF(BA62>=300,"B", IF(BA62>=200,"A", "")))))) | BJ62: =IF(BF62="Yes","",IF(AY62>1250,"E",IF(AY62>750,"D", IF(AY62>=500,"C", IF(AY62>=300,"B", IF(AY62>=200,"A", "")))))) | BK62: =SUM(AR62:AX62) -> 0 | BL62: =SUM(AL62:AQ62) -> 0 | BM62: =IFERROR(BK62/$AY62,"") | BN62: =IFERROR(BL62/$AY62,"") | BO62: =SUM(AL62:AS62) -> 0 | BP62: =IF(BF62="Yes","",IF(BO62>1250,"E",IF(BO62>750,"D", IF(BO62>=500,"C", IF(BO62>=300,"B", IF(BO62>=200,"A", "")))))) | BR62: =SUM(Z62:AE62) -> 0 | BS62: =SUM(AF62:AK62) -> 0 | BT62: =SUM(BR62:BS62) -> 0 | BU62: =IFERROR(_xlfn.XLOOKUP(D62,Sheet1!B:B,Sheet1!L:L),"") | BV62: =_xlfn.XLOOKUP(BU62,Sheet1!S:S,Sheet1!T:T) -> #N/A | BW62: =_xlfn.XLOOKUP(D62,Sheet1!B:B,Sheet1!M:M) -> #N/A | BZ62: =AY62-AW62 -> 0 | CG62: =IF(BO62<80,"Below 80", IF(BO62<=120,"80-120", IF(BO62<=200,"> 120-200", IF(BO62<=300,">200-300", IF(BO62<=500,">300-500", ">500"))))) -> Below 80 | CH62: =IFERROR(_xlfn.XLOOKUP(CG62,Scenario!M:M,Scenario!N:N),"") | CI62: =IF(BI62="", IF(BA62>=1, "Yes", "No")) -> No | CJ62: 0
A63: 62 | B63: 2023 | C63: PBTMTR142 | D63: 0015g00001YRULwAAP | E63: SALASAR ENTERPRISES | F63: HARYANA | G63: HISAR | H63: Hisar | I63: PAL CEMENT AND STEEL PVT. LTD. | J63: Dinesh Kumar | K63: Navneet Pal | L63: C12827 | M63: North | N63: 125001 | O63: 06AITPG2966N1ZJ | P63: 8168241200 | Q63: Dec'23 | R63: 2024 | S63: 101 | T63: 130 | U63: 0 | V63: Challenger | W63: 32 | X63: 36 | Y63: 22 | Z63: 5 | AA63: 1 | AB63: 0 | AC63: 0 | AD63: 0 | AE63: 0 | AF63: 0 | AG63: 0 | AH63: 0 | AI63: 0 | AJ63: 0 | AK63: 0 | AL63: 0 | AM63: 0 | AN63: 0 | AO63: 0 | AP63: 0 | AQ63: 0 | AR63: 0 | AS63: 0 | AT63: 0 | AU63: 0 | AV63: 0 | AW63: =SUM(AL63:AU63) -> 0 | AX63: 0 | AY63: =AW63+AX63 -> 0 | AZ63: =SUM(Z63:AK63) -> 6 | BA63: 0 | BB63: =BA63-AW63 -> 0 | BC63: =IFERROR(BB63/4,0) -> 0 | BD63: =AY63-AZ63 -> -6 | BE63: =AZ63-AW63 -> 6 | BF63: No | BG63: =AVERAGE(AL63:AS63) -> 0 | BH63: Yes | BI63: =IF(BF63="Yes","",IF(BA63>1250,"E",IF(BA63>750,"D", IF(BA63>=500,"C", IF(BA63>=300,"B", IF(BA63>=200,"A", "")))))) | BJ63: =IF(BF63="Yes","",IF(AY63>1250,"E",IF(AY63>750,"D", IF(AY63>=500,"C", IF(AY63>=300,"B", IF(AY63>=200,"A", "")))))) | BK63: =SUM(AR63:AX63) -> 0 | BL63: =SUM(AL63:AQ63) -> 0 | BM63: =IFERROR(BK63/$AY63,"") | BN63: =IFERROR(BL63/$AY63,"") | BO63: =SUM(AL63:AS63) -> 0 | BP63: =IF(BF63="Yes","",IF(BO63>1250,"E",IF(BO63>750,"D", IF(BO63>=500,"C", IF(BO63>=300,"B", IF(BO63>=200,"A", "")))))) | BR63: =SUM(Z63:AE63) -> 6 | BS63: =SUM(AF63:AK63) -> 0 | BT63: =SUM(BR63:BS63) -> 6 | BU63: =IFERROR(_xlfn.XLOOKUP(D63,Sheet1!B:B,Sheet1!L:L),"") | BV63: =_xlfn.XLOOKUP(BU63,Sheet1!S:S,Sheet1!T:T) -> #N/A | BW63: =_xlfn.XLOOKUP(D63,Sheet1!B:B,Sheet1!M:M) -> #N/A | BZ63: =AY63-AW63 -> 0 | CG63: =IF(BO63<80,"Below 80", IF(BO63<=120,"80-120", IF(BO63<=200,"> 120-200", IF(BO63<=300,">200-300", IF(BO63<=500,">300-500", ">500"))))) -> Below 80 | CH63: =IFERROR(_xlfn.XLOOKUP(CG63,Scenario!M:M,Scenario!N:N),"") | CI63: =IF(BI63="", IF(BA63>=1, "Yes", "No")) -> No | CJ63: 0
A64: 63 | B64: 2023 | C64: PBTMTR143 | D64: 0015g00001VBvVMAA1 | E64: SHASHI ENTERPRISES | F64: HARYANA | G64: HISAR | H64: Hisar | I64: PAL CEMENT AND STEEL PVT. LTD. | J64: Dinesh Kumar | K64: Navneet Pal | L64: C12827 | M64: North | N64: 125001 | O64: 06ABFPJ0323D1ZF | P64: 7206141881 | Q64: Dec'23 | R64: 2024 | S64: 59 | T64: 250 | U64: 0 | V64: Alien | W64: 15 | X64: 16 | Y64: 17 | Z64: 0 | AA64: 0 | AB64: 0 | AC64: 0 | AD64: 0 | AE64: 0 | AF64: 0 | AG64: 51 | AH64: 0 | AI64: 51 | AJ64: 69 | AK64: 50 | AL64: 0 | AM64: 0 | AN64: 0 | AO64: 0 | AP64: 0 | AQ64: 0 | AR64: 0 | AS64: 0 | AT64: 0 | AU64: 0 | AV64: 0 | AW64: =SUM(AL64:AU64) -> 0 | AX64: 0 | AY64: =AW64+AX64 -> 0 | AZ64: =SUM(Z64:AK64) -> 221 | BA64: 0 | BB64: =BA64-AW64 -> 0 | BC64: =IFERROR(BB64/4,0) -> 0 | BD64: =AY64-AZ64 -> -221 | BE64: =AZ64-AW64 -> 221 | BF64: No | BG64: =AVERAGE(AL64:AS64) -> 0 | BH64: Yes | BI64: =IF(BF64="Yes","",IF(BA64>1250,"E",IF(BA64>750,"D", IF(BA64>=500,"C", IF(BA64>=300,"B", IF(BA64>=200,"A", "")))))) | BJ64: =IF(BF64="Yes","",IF(AY64>1250,"E",IF(AY64>750,"D", IF(AY64>=500,"C", IF(AY64>=300,"B", IF(AY64>=200,"A", "")))))) | BK64: =SUM(AR64:AX64) -> 0 | BL64: =SUM(AL64:AQ64) -> 0 | BM64: =IFERROR(BK64/$AY64,"") | BN64: =IFERROR(BL64/$AY64,"") | BO64: =SUM(AL64:AS64) -> 0 | BP64: =IF(BF64="Yes","",IF(BO64>1250,"E",IF(BO64>750,"D", IF(BO64>=500,"C", IF(BO64>=300,"B", IF(BO64>=200,"A", "")))))) | BR64: =SUM(Z64:AE64) -> 0 | BS64: =SUM(AF64:AK64) -> 221 | BT64: =SUM(BR64:BS64) -> 221 | BU64: =IFERROR(_xlfn.XLOOKUP(D64,Sheet1!B:B,Sheet1!L:L),"") | BV64: =_xlfn.XLOOKUP(BU64,Sheet1!S:S,Sheet1!T:T) -> #N/A | BW64: =_xlfn.XLOOKUP(D64,Sheet1!B:B,Sheet1!M:M) -> #N/A | BZ64: =AY64-AW64 -> 0 | CG64: =IF(BO64<80,"Below 80", IF(BO64<=120,"80-120", IF(BO64<=200,"> 120-200", IF(BO64<=300,">200-300", IF(BO64<=500,">300-500", ">500"))))) -> Below 80 | CH64: =IFERROR(_xlfn.XLOOKUP(CG64,Scenario!M:M,Scenario!N:N),"") | CI64: =IF(BI64="", IF(BA64>=1, "Yes", "No")) -> No | CJ64: 0 | CK64: Yes
A65: 64 | B65: 2023 | C65: PBTMTR144 | D65: 0015g00001V9TgbAAF | E65: SIWANI STEEL TRADERS | F65: HARYANA | G65: BHIWANI | H65: Narnaund | I65: PAL CEMENT AND STEEL PVT. LTD. | J65: Dinesh Kumar | K65: Navneet Pal | L65: C12827 | M65: North | N65: 127046 | O65: 06AHVPS9112K1ZM | P65: 9896000758 | Q65: Dec'23 | R65: 2024 | S65: 51 | T65: 150 | U65: 0 | V65: Challenger | W65: 10 | X65: 15 | Y65: 16 | Z65: 0 | AA65: 0 | AB65: 0 | AC65: 0 | AD65: 0 | AE65: 0 | AF65: 0 | AG65: 0 | AH65: 0 | AI65: 0 | AJ65: 0 | AK65: 0 | AL65: 0 | AM65: 0 | AN65: 0 | AO65: 0 | AP65: 0 | AQ65: 0 | AR65: 0 | AS65: 0 | AT65: 0 | AU65: 0 | AV65: 0 | AW65: =SUM(AL65:AU65) -> 0 | AX65: 0 | AY65: =AW65+AX65 -> 0 | AZ65: =SUM(Z65:AK65) -> 0 | BA65: 0 | BB65: =BA65-AW65 -> 0 | BC65: =IFERROR(BB65/4,0) -> 0 | BD65: =AY65-AZ65 -> 0 | BE65: =AZ65-AW65 -> 0 | BF65: No | BG65: =AVERAGE(AL65:AS65) -> 0 | BH65: Yes | BI65: =IF(BF65="Yes","",IF(BA65>1250,"E",IF(BA65>750,"D", IF(BA65>=500,"C", IF(BA65>=300,"B", IF(BA65>=200,"A", "")))))) | BJ65: =IF(BF65="Yes","",IF(AY65>1250,"E",IF(AY65>750,"D", IF(AY65>=500,"C", IF(AY65>=300,"B", IF(AY65>=200,"A", "")))))) | BK65: =SUM(AR65:AX65) -> 0 | BL65: =SUM(AL65:AQ65) -> 0 | BM65: =IFERROR(BK65/$AY65,"") | BN65: =IFERROR(BL65/$AY65,"") | BO65: =SUM(AL65:AS65) -> 0 | BP65: =IF(BF65="Yes","",IF(BO65>1250,"E",IF(BO65>750,"D", IF(BO65>=500,"C", IF(BO65>=300,"B", IF(BO65>=200,"A", "")))))) | BR65: =SUM(Z65:AE65) -> 0 | BS65: =SUM(AF65:AK65) -> 0 | BT65: =SUM(BR65:BS65) -> 0 | BU65: =IFERROR(_xlfn.XLOOKUP(D65,Sheet1!B:B,Sheet1!L:L),"") | BV65: =_xlfn.XLOOKUP(BU65,Sheet1!S:S,Sheet1!T:T) -> #N/A | BW65: =_xlfn.XLOOKUP(D65,Sheet1!B:B,Sheet1!M:M) -> #N/A | BZ65: =AY65-AW65 -> 0 | CG65: =IF(BO65<80,"Below 80", IF(BO65<=120,"80-120", IF(BO65<=200,"> 120-200", IF(BO65<=300,">200-300", IF(BO65<=500,">300-500", ">500"))))) -> Below 80 | CH65: =IFERROR(_xlfn.XLOOKUP(CG65,Scenario!M:M,Scenario!N:N),"") | CI65: =IF(BI65="", IF(BA65>=1, "Yes", "No")) -> No | CJ65: 0
A66: 65 | B66: 2023 | C66: PBTMTR145 | D66: 001J100000F4j2TIAR | E66: SUPREME PACKER | F66: HARYANA | G66: HISAR | H66: Hisar | I66: PAL CEMENT AND STEEL PVT. LTD. | J66: Dinesh Kumar | K66: Navneet Pal | L66: C12827 | M66: North | N66: 0 | O66: 06AARFS7620K1ZO | P66: 0 | Q66: Dec'23 | R66: 2024 | S66: 2 | T66: 0 | U66: 0 | V66: Minor | W66: 0 | X66: 0 | Y66: 0 | Z66: 0 | AA66: 0 | AB66: 0 | AC66: 0 | AD66: 0 | AE66: 0 | AF66: 0 | AG66: 0 | AH66: 0 | AI66: 0 | AJ66: 0 | AK66: 0 | AL66: 0 | AM66: 0 | AN66: 0 | AO66: 0 | AP66: 0 | AQ66: 0 | AR66: 0 | AS66: 0 | AT66: 0 | AU66: 0 | AV66: 0 | AW66: =SUM(AL66:AU66) -> 0 | AX66: 0 | AY66: =AW66+AX66 -> 0 | AZ66: =SUM(Z66:AK66) -> 0 | BA66: 0 | BB66: =BA66-AW66 -> 0 | BC66: =IFERROR(BB66/4,0) -> 0 | BD66: =AY66-AZ66 -> 0 | BE66: =AZ66-AW66 -> 0 | BF66: No | BG66: =AVERAGE(AL66:AS66) -> 0 | BH66: Yes | BI66: =IF(BF66="Yes","",IF(BA66>1250,"E",IF(BA66>750,"D", IF(BA66>=500,"C", IF(BA66>=300,"B", IF(BA66>=200,"A", "")))))) | BJ66: =IF(BF66="Yes","",IF(AY66>1250,"E",IF(AY66>750,"D", IF(AY66>=500,"C", IF(AY66>=300,"B", IF(AY66>=200,"A", "")))))) | BK66: =SUM(AR66:AX66) -> 0 | BL66: =SUM(AL66:AQ66) -> 0 | BM66: =IFERROR(BK66/$AY66,"") | BN66: =IFERROR(BL66/$AY66,"") | BO66: =SUM(AL66:AS66) -> 0 | BP66: =IF(BF66="Yes","",IF(BO66>1250,"E",IF(BO66>750,"D", IF(BO66>=500,"C", IF(BO66>=300,"B", IF(BO66>=200,"A", "")))))) | BR66: =SUM(Z66:AE66) -> 0 | BS66: =SUM(AF66:AK66) -> 0 | BT66: =SUM(BR66:BS66) -> 0 | BU66: =IFERROR(_xlfn.XLOOKUP(D66,Sheet1!B:B,Sheet1!L:L),"") | BV66: =_xlfn.XLOOKUP(BU66,Sheet1!S:S,Sheet1!T:T) -> #N/A | BW66: =_xlfn.XLOOKUP(D66,Sheet1!B:B,Sheet1!M:M) -> #N/A | BZ66: =AY66-AW66 -> 0 | CG66: =IF(BO66<80,"Below 80", IF(BO66<=120,"80-120", IF(BO66<=200,"> 120-200", IF(BO66<=300,">200-300", IF(BO66<=500,">300-500", ">500"))))) -> Below 80 | CH66: =IFERROR(_xlfn.XLOOKUP(CG66,Scenario!M:M,Scenario!N:N),"") | CI66: =IF(BI66="", IF(BA66>=1, "Yes", "No")) -> No | CJ66: 0
A67: 66 | B67: 2023 | C67: PBTMTR146 | D67: 0 | E67: Surya Trading Co, | F67: HARYANA | G67: HISAR | H67: Hisar | I67: PAL CEMENT AND STEEL PVT. LTD. | J67: #VALUE! | K67: Navneet Pal | L67: C12827 | M67: North | N67: #VALUE! | O67: #VALUE! | P67: #VALUE! | Q67: Dec'23 | R67: 2024 | S67: 102 | U67: 0 | V67: Potential Not updated | W67: 26 | X67: 28 | Y67: 32 | Z67: 18 | AA67: 1.6 | AB67: 0 | AC67: 0 | AD67: 0 | AE67: 0 | AF67: 0 | AG67: 0 | AH67: 0 | AI67: 0 | AJ67: 0 | AK67: 0 | AL67: 0 | AM67: 0 | AN67: 0 | AO67: 0 | AP67: 0 | AQ67: 0 | AR67: 0 | AS67: 0 | AT67: 0 | AU67: 0 | AV67: 0 | AW67: =SUM(AL67:AU67) -> 0 | AX67: 0 | AY67: =AW67+AX67 -> 0 | AZ67: =SUM(Z67:AK67) -> 19.6 | BA67: 0 | BB67: =BA67-AW67 -> 0 | BC67: =IFERROR(BB67/4,0) -> 0 | BD67: =AY67-AZ67 -> -19.6 | BE67: =AZ67-AW67 -> 19.6 | BF67: No | BG67: =AVERAGE(AL67:AS67) -> 0 | BH67: Yes | BI67: =IF(BF67="Yes","",IF(BA67>1250,"E",IF(BA67>750,"D", IF(BA67>=500,"C", IF(BA67>=300,"B", IF(BA67>=200,"A", "")))))) | BJ67: =IF(BF67="Yes","",IF(AY67>1250,"E",IF(AY67>750,"D", IF(AY67>=500,"C", IF(AY67>=300,"B", IF(AY67>=200,"A", "")))))) | BK67: =SUM(AR67:AX67) -> 0 | BL67: =SUM(AL67:AQ67) -> 0 | BM67: =IFERROR(BK67/$AY67,"") | BN67: =IFERROR(BL67/$AY67,"") | BO67: =SUM(AL67:AS67) -> 0 | BP67: =IF(BF67="Yes","",IF(BO67>1250,"E",IF(BO67>750,"D", IF(BO67>=500,"C", IF(BO67>=300,"B", IF(BO67>=200,"A", "")))))) | BR67: =SUM(Z67:AE67) -> 19.6 | BS67: =SUM(AF67:AK67) -> 0 | BT67: =SUM(BR67:BS67) -> 19.6 | BU67: =IFERROR(_xlfn.XLOOKUP(D67,Sheet1!B:B,Sheet1!L:L),"") -> 0 | BV67: =_xlfn.XLOOKUP(BU67,Sheet1!S:S,Sheet1!T:T) -> #N/A | BW67: =_xlfn.XLOOKUP(D67,Sheet1!B:B,Sheet1!M:M) -> 0 | BZ67: =AY67-AW67 -> 0 | CG67: =IF(BO67<80,"Below 80", IF(BO67<=120,"80-120", IF(BO67<=200,"> 120-200", IF(BO67<=300,">200-300", IF(BO67<=500,">300-500", ">500"))))) -> Below 80 | CH67: =IFERROR(_xlfn.XLOOKUP(CG67,Scenario!M:M,Scenario!N:N),"") | CI67: =IF(BI67="", IF(BA67>=1, "Yes", "No")) -> No | CJ67: 0
A68: 67 | B68: 2023 | C68: PBTMTR147 | D68: 0015g00001e8kaNAAQ | E68: PAL CEMENT AND STEEL PVT. LTD | F68: PUNJAB | G68: S.A.S Nagar | H68: Hisar | I68: PAL CEMENT AND STEEL PVT. LTD. | J68: Abhishek Wadhwa | K68: Navneet Pal | L68: C12827 | M68: North | N68: 140308 | O68: 03AAGCP3809H1ZM | P68: 9215510500 | Q68: Dec'23 | R68: 2024 | S68: 124 | T68: 1600 | U68: 0 | V68: Alien | W68: 10 | X68: 12 | Y68: 12 | Z68: 0 | AA68: 0 | AB68: 0 | AC68: 0 | AD68: 0 | AE68: 0 | AF68: 0 | AG68: 0 | AH68: 0 | AI68: 0 | AJ68: 0 | AK68: 0 | AL68: 0 | AM68: 0 | AN68: 0 | AO68: 0 | AP68: 0 | AQ68: 0 | AR68: 0 | AS68: 0 | AT68: 0 | AU68: 0 | AV68: 0 | AW68: =SUM(AL68:AU68) -> 0 | AX68: 0 | AY68: =AW68+AX68 -> 0 | AZ68: =SUM(Z68:AK68) -> 0 | BA68: 0 | BB68: =BA68-AW68 -> 0 | BC68: =IFERROR(BB68/4,0) -> 0 | BD68: =AY68-AZ68 -> 0 | BE68: =AZ68-AW68 -> 0 | BF68: No | BG68: =AVERAGE(AL68:AS68) -> 0 | BH68: Yes | BI68: =IF(BF68="Yes","",IF(BA68>1250,"E",IF(BA68>750,"D", IF(BA68>=500,"C", IF(BA68>=300,"B", IF(BA68>=200,"A", "")))))) | BJ68: =IF(BF68="Yes","",IF(AY68>1250,"E",IF(AY68>750,"D", IF(AY68>=500,"C", IF(AY68>=300,"B", IF(AY68>=200,"A", "")))))) | BK68: =SUM(AR68:AX68) -> 0 | BL68: =SUM(AL68:AQ68) -> 0 | BM68: =IFERROR(BK68/$AY68,"") | BN68: =IFERROR(BL68/$AY68,"") | BO68: =SUM(AL68:AS68) -> 0 | BP68: =IF(BF68="Yes","",IF(BO68>1250,"E",IF(BO68>750,"D", IF(BO68>=500,"C", IF(BO68>=300,"B", IF(BO68>=200,"A", "")))))) | BR68: =SUM(Z68:AE68) -> 0 | BS68: =SUM(AF68:AK68) -> 0 | BT68: =SUM(BR68:BS68) -> 0 | BU68: =IFERROR(_xlfn.XLOOKUP(D68,Sheet1!B:B,Sheet1!L:L),"") | BV68: =_xlfn.XLOOKUP(BU68,Sheet1!S:S,Sheet1!T:T) -> #N/A | BW68: =_xlfn.XLOOKUP(D68,Sheet1!B:B,Sheet1!M:M) -> #N/A | BZ68: =AY68-AW68 -> 0 | CG68: =IF(BO68<80,"Below 80", IF(BO68<=120,"80-120", IF(BO68<=200,"> 120-200", IF(BO68<=300,">200-300", IF(BO68<=500,">300-500", ">500"))))) -> Below 80 | CH68: =IFERROR(_xlfn.XLOOKUP(CG68,Scenario!M:M,Scenario!N:N),"") | CI68: =IF(BI68="", IF(BA68>=1, "Yes", "No")) -> No | CJ68: 0
A69: 68 | B69: 2023 | C69: PBTMTR148 | D69: 001J100000F4iiqIAB | E69: PUSHPA CONSTRUCTION COMPANY | F69: HARYANA | G69: HISAR | H69: Hisar | I69: PAL CEMENT AND STEEL PVT. LTD. | J69: Dinesh Kumar | K69: Navneet Pal | L69: C12827 | M69: North | N69: 125001 | O69: 06BPYPA0200A1ZP | P69: 9518155708 | Q69: Dec'23 | R69: 2024 | S69: 121 | T69: 50 | U69: 3.6198667 | V69: Friendly | W69: 20 | X69: 22 | Y69: 10 | Z69: 0 | AA69: 0 | AB69: 0 | AC69: 0 | AD69: 0 | AE69: 0 | AF69: 0 | AG69: 0 | AH69: 0 | AI69: 0 | AJ69: 0 | AK69: 0 | AL69: 0 | AM69: 0 | AN69: 0 | AO69: 113.19 | AP69: 178.08 | AQ69: 135.5 | AR69: 51.5 | AS69: 81.86 | AT69: 265.16 | AU69: 236 | AV69: 41.82 | AW69: =SUM(AL69:AU69) -> 1061.29 | AX69: =AW69*2 -> 2122.58 | AY69: =AW69+AX69 -> 3183.87 | AZ69: =SUM(Z69:AK69) -> 0 | BA69: 750 | BB69: =BA69-AW69 -> -311.29 | BC69: =IFERROR(BB69/4,0) -> -77.8225 | BD69: =AY69-AZ69 -> 3183.87 | BE69: =AZ69-AW69 -> -1061.29 | BF69: No | BG69: =AVERAGE(AL69:AS69) -> 70.01625 | BH69: Yes | BI69: =IF(BF69="Yes","",IF(BA69>1250,"E",IF(BA69>750,"D", IF(BA69>=500,"C", IF(BA69>=300,"B", IF(BA69>=200,"A", "")))))) -> C | BJ69: =IF(BF69="Yes","",IF(AY69>1250,"E",IF(AY69>750,"D", IF(AY69>=500,"C", IF(AY69>=300,"B", IF(AY69>=200,"A", "")))))) -> E | BK69: =SUM(AR69:AX69) -> 3860.21 | BL69: =SUM(AL69:AQ69) -> 426.77 | BM69: =IFERROR(BK69/$AY69,"") -> 1.212427 | BN69: =IFERROR(BL69/$AY69,"") -> 0.13404128 | BO69: =SUM(AL69:AS69) -> 560.13 | BP69: =IF(BF69="Yes","",IF(BO69>1250,"E",IF(BO69>750,"D", IF(BO69>=500,"C", IF(BO69>=300,"B", IF(BO69>=200,"A", "")))))) -> C | BQ69: Will push for 1250 MT slab | BR69: =SUM(Z69:AE69) -> 0 | BS69: =SUM(AF69:AK69) -> 0 | BT69: =SUM(BR69:BS69) -> 0 | BU69: =IFERROR(_xlfn.XLOOKUP(D69,Sheet1!B:B,Sheet1!L:L),"") | BV69: =_xlfn.XLOOKUP(BU69,Sheet1!S:S,Sheet1!T:T) -> #N/A | BW69: =_xlfn.XLOOKUP(D69,Sheet1!B:B,Sheet1!M:M) -> #N/A | BX69: New | BZ69: =AY69-AW69 -> 2122.58 | CB69: =AW69/AY69 -> 0.33333333 | CC69: =AX69/AY69 -> 0.66666667 | CG69: =IF(BO69<80,"Below 80", IF(BO69<=120,"80-120", IF(BO69<=200,"> 120-200", IF(BO69<=300,">200-300", IF(BO69<=500,">300-500", ">500"))))) -> >500 | CH69: =IFERROR(_xlfn.XLOOKUP(CG69,Scenario!M:M,Scenario!N:N),"") -> E | CI69: =IF(BI69="", IF(BA69>=1, "Yes", "No")) -> FALSE | CJ69: 1038.4
A70: 69 | B70: 2024 | C70: PBTMTR237 | D70: 0015g00001c4Q9sAAE | E70: CHARVIK TRADING COMPANY | F70: RAJASTHAN | G70: ALWAR | H70: Alwar | I70: Swastik Tradevision Pvt. Ltd. | J70: Ravi Kumar Kulmi | K70: Ravi Kumar Kulmi | L70: C12822 | M70: North | N70: 301001 | O70: 08BDXPD6291B1ZB | P70: 8302515922 | Q70: Feb'24 | R70: 2024 | S70: 52 | T70: 300 | U70: 0.0614 | V70: Alien | W70: 0 | X70: 26 | Y70: 26 | Z70: 0 | AA70: 33.29 | AB70: 20 | AC70: 0 | AD70: 0 | AE70: 25 | AF70: 0 | AG70: 25 | AH70: 0 | AI70: 25.04 | AJ70: 0 | AK70: 24.98 | AL70: 25 | AM70: 0 | AN70: 20 | AO70: 0 | AP70: 25.01 | AQ70: 0 | AR70: 0 | AS70: 0 | AT70: 30.14 | AU70: 0 | AV70: 25.12 | AW70: =SUM(AL70:AU70) -> 100.15 | AX70: =AW70*2 -> 200.3 | AY70: =AW70+AX70 -> 300.45 | AZ70: =SUM(Z70:AK70) -> 153.31 | BA70: 200 | BB70: =BA70-AW70 -> 99.85 | BC70: =IFERROR(BB70/4,0) -> 24.9625 | BD70: =AY70-AZ70 -> 147.14 | BE70: =AZ70-AW70 -> 53.16 | BF70: No | BG70: =AVERAGE(AL70:AS70) -> 8.75125 | BH70: Yes | BI70: =IF(BF70="Yes","",IF(BA70>1250,"E",IF(BA70>750,"D", IF(BA70>=500,"C", IF(BA70>=300,"B", IF(BA70>=200,"A", "")))))) -> A | BJ70: =IF(BF70="Yes","",IF(AY70>1250,"E",IF(AY70>750,"D", IF(AY70>=500,"C", IF(AY70>=300,"B", IF(AY70>=200,"A", "")))))) -> B | BK70: =SUM(AR70:AX70) -> 355.71 | BL70: =SUM(AL70:AQ70) -> 70.01 | BM70: =IFERROR(BK70/$AY70,"") -> 1.1839241 | BN70: =IFERROR(BL70/$AY70,"") -> 0.23301714 | BO70: =SUM(AL70:AS70) -> 70.01 | BP70: =IF(BF70="Yes","",IF(BO70>1250,"E",IF(BO70>750,"D", IF(BO70>=500,"C", IF(BO70>=300,"B", IF(BO70>=200,"A", "")))))) | BR70: =SUM(Z70:AE70) -> 78.29 | BS70: =SUM(AF70:AK70) -> 75.02 | BT70: =SUM(BR70:BS70) -> 153.31 | BU70: =IFERROR(_xlfn.XLOOKUP(D70,Sheet1!B:B,Sheet1!L:L),"") | BV70: =_xlfn.XLOOKUP(BU70,Sheet1!S:S,Sheet1!T:T) -> #N/A | BW70: =_xlfn.XLOOKUP(D70,Sheet1!B:B,Sheet1!M:M) -> #N/A | BX70: New | BZ70: =AY70-AW70 -> 200.3 | CB70: =AW70/AY70 -> 0.33333333 | CC70: =AX70/AY70 -> 0.66666667 | CG70: =IF(BO70<80,"Below 80", IF(BO70<=120,"80-120", IF(BO70<=200,"> 120-200", IF(BO70<=300,">200-300", IF(BO70<=500,">300-500", ">500"))))) -> Below 80 | CH70: =IFERROR(_xlfn.XLOOKUP(CG70,Scenario!M:M,Scenario!N:N),"") | CI70: =IF(BI70="", IF(BA70>=1, "Yes", "No")) -> FALSE | CJ70: 140.02
